Workbook

Sheet How to Use
B2: How to audit a client's freight quotation
B3: UAT version 1.0 (frozen 23 Oct 2026). One quotation per audit. Five steps. Everything in grey, the findings and the Summary sheet fill in automatically - no macros.
B5: 1 Collect documents | C5: The forwarder's quotation, the commercial invoice (CI), the packing list (PL) and any rate agreement or contract. Without an itemised quotation, CI or PL the status shows 'Insufficient Information'.
B6: 2 Enter shipment details | C6: Audit sheet, section 1: copy the cargo from the CI/PL (pieces, cartons and pallets separately, weight, volume, value) and answer 'PL volume covers all cargo?'. Record the Incoterm exactly as on the CI and the client's role (buyer or seller). In section 3, answer 'Requested by client?' for each service.
B7: 3 Enter the quotation charges | C7: Section 2: forwarder, date, freight validity and - only if stated - origin and destination charge validity (blank = Not Confirmed), currency, mode and containers, route, transit, free time; enter the cargo figures only if the quotation states them. Section 4: one row per quoted charge - Charge, Category, Basis, Rate, Status. Leave Currency blank for the quotation currency. Enter the forwarder's line total only if the quotation shows it (this is what makes a line 'Verified'). Enter Agreed rate only when a rate agreement was provided.
B8: 4 Review the automatic findings | C8: Section 5 shows the status, the firm charges, estimates, conditional and unpriced items, and the findings in priority order. Use the 'Reviewer flag' column to record your own judgement on a line (e.g. possible duplicate) - it becomes a finding with the line amount. Accept a weight or CBM difference only with a reason (Accept diff. = Yes).
B9: 5 Generate the audit summary | C9: Open the Summary sheet: it is already filled in. File > Print (or Download as PDF in Google Sheets). It is set to fit one page wide.
B11: Colour key
B12: Type here | C12: Input cell. Dropdowns appear where a fixed list applies.
B13: Calculated | C13: Formula - do not overwrite.
B15: Status (one per audit)
B16: Insufficient Information | C16: CI or PL missing, quotation not itemised, or no line can be calculated.
B17: Corrections Required | C17: At least one confirmed error: a line amount or stated total that does not reconcile, a rate above the agreed rate, or quoted pieces/packages that contradict the CI/PL.
B18: Needs Clarification | C18: No confirmed errors, but open questions or risks (e.g. unpriced or excluded requested services, at-cost items, expiring rates).
B19: Audit Complete — No Issues Identified | C19: Only when no error, question or risk is open. It cannot appear while requested services are unpriced, excluded or estimated.
B21: Finding types
B22: Error | C22: Confirmed and must be corrected by the forwarder.
B23: Question | C23: Must be clarified before the client proceeds. Amounts shown are 'under question', not confirmed savings.
B24: Risk | C24: Cost could change or is not covered by the quotation.
B26: Good to know
B27: • | C27: 'Verified' appears only when the forwarder's own line amount is entered and reconciles. Otherwise a line shows 'Calculated — Not Independently Verified'.
B28: • | C28: Quantities fill in from the basis: per container = containers quoted; per CBM = shipped CBM; per RT = greater of CBM and tonnes; per kg = chargeable kg (air uses the stated divisor, else the default in Lists). Use 'Qty / base override' for per-unit lines and for the base of % charges.
B29: • | C29: Statuses: Firm = in the firm figure · Estimate = shown separately · If required = conditional, only if the event occurs · At cost / TBC = no amount yet · Included / Excluded / Not applicable = no amount.
B30: • | C30: The tool never judges prices against 'the market' and holds no duty or VAT rates. Agreed rates are checked only when entered from a rate agreement.
B31: • | C31: Incoterm questions are raised only for services that Incoterms 2020 normally place on the other party (table in Lists). They are questions, not errors.
B32: • | C32: Up to 50 charge lines and 30 findings are shown. To start a new audit, use a fresh copy of the blank template.
B33: • | C33: A hidden sheet named 'Checks' runs the 20 checks with ordinary formulas. Do not edit or delete it. Settings (air divisor, validity warning, review threshold, rounding tolerance) are on the Lists sheet.

Sheet Audit
B1: MOVE · Freight Quotation Audit
B2: One quotation per audit. Yellow cells = type here · Grey cells = calculated · Dropdowns where shown. Checks run automatically.
B3: AUDIT STATUS | C3: =Checks!$AF$2 -> Not started | G3: =Checks!$AF$20 -> Known Firm Charges — Not All-In | J3: =Checks!$AF$10 -> 0 | L3: =Checks!$AF$3&" errors · "&Checks!$AF$4&" questions · "&Checks!$AF$5&" risks — see section 5" -> 0 errors · 0 questions · 0 risks — see section 5
B5: 1 SHIPMENT INFORMATION From the commercial invoice, packing list and the client's request
B6: Audit reference | G6: Audit date
B7: Client | G7: Client role in the sale
B8: Commercial Incoterm | G8: Named place
B9: Port / airport of loading | G9: Port / airport of discharge
B10: Pickup address | G10: Delivery address
B11: Cargo ready date | G11: Commodity
B12: HS code | G12: Goods value (from CI)
B13: Goods value currency | G13: Pieces
B14: Cartons (count) | G14: Pallets (count; 0 if none)
B15: Gross weight (kg) | G15: Volume as shipped (CBM)
B16: Package / pallet dimensions | G16: Stackable
B17: Wood packaging | G17: Special cargo (DG, oversize, overweight)
... B21: Prepared by | G21: PL volume covers all cargo?
B22: 2 QUOTATION INFORMATION The quotation being audited
B23: Forwarder | G23: Quotation reference
B24: Quotation source and date | G24: Freight valid until
B25: Quotation currency | G25: Mode
B26: Containers (quantity) | G26: Container type
B27: Quoted term as written | G27: Routing (direct / via)
B28: Transit time | G28: Free time at destination (days)
B29: Load plan confirmed by forwarder | G29: Quoted route matches the request
B30: Air divisor stated (cm3/kg) | G30: Forwarder's stated total
B31: Other currency 1 (code) | G31: Rate: 1 unit = ? quote currency
B32: Other currency 2 (code) | G32: Rate: 1 unit = ? quote currency
B33: Origin charges valid until (blank = Not Confirmed) | G33: Destination charges valid until (blank = Not Confirmed)
B34: Cargo basis (blank Quoted = not stated) | C34: CI/PL (auto) | D34: Quoted | E34: Difference | F34: Diff % | G34: Accept diff.? | H34: Check (auto)
B35: Pieces | C35: =IF(Audit!$J$13="","",Audit!$J$13) | E35: =IF(OR(C35="",D35=""),"",D35-C35) | F35: =IF(OR(C35="",D35="",C35=0),"",(D35-C35)/C35) | G35: Must match | H35: =IF(D35="","Not stated in quotation",IF(C35="","CI/PL value missing",IF(D35=C35,"Matches","ERROR - does not match the CI/PL"))) -> Not stated in quotation
B36: Packages (cartons or pallets) | C36: =IF(Audit!$C$14="","",Audit!$C$14&" ctns / "&IF(Audit!$J$14="","0",Audit!$J$14)&" plts") | G36: Must match | H36: =IF(D36="","Not stated in quotation",IF(AND(Audit!$C$14="",Audit!$J$14=""),"CI/PL value missing",IF(D36=Audit!$C$14,"Matches cartons",IF(AND(ISNUMBER(Audit!$J$14),D36=Audit!$J$14),"Matches pallets","ERROR - matches neither cartons nor pallets")))) -> Not stated in quotation
B37: Gross weight (kg) | C37: =IF(Audit!$C$15="","",Audit!$C$15) | E37: =IF(OR(C37="",D37=""),"",D37-C37) | F37: =IF(OR(C37="",D37="",C37=0),"",(D37-C37)/C37) | H37: =IF(D37="","Not stated in quotation",IF(C37="","CI/PL value missing",IF(D37=C37,"Matches",IF(G37="Yes","Difference accepted by auditor","Review - differs by "&TEXT(E37,"#,##0.###")&" ("&TEXT(F37,"0.0%")&")")))) -> Not stated in quotation
B38: Volume (CBM) | C38: =IF(Audit!$J$15="","",Audit!$J$15) | E38: =IF(OR(C38="",D38=""),"",D38-C38) | F38: =IF(OR(C38="",D38="",C38=0),"",(D38-C38)/C38) | H38: =IF(D38="","Not stated in quotation",IF(C38="","CI/PL value missing",IF(D38=C38,"Matches",IF(G38="Yes","Difference accepted by auditor","Review - differs by "&TEXT(E38,"#,##0.###")&" ("&TEXT(F38,"0.0%")&")")))) -> Not stated in quotation
B39: Revenue tonnes (auto, LCL) | C39: =Checks!$AF$30 | G39: Chargeable weight kg (auto) | J39: =Checks!$AF$31 | L39: =IF(Audit!$J$25="Air","Divisor used: "&Checks!$AF$32,"")
B41: 3 REQUESTED SERVICES & COVERAGE Coverage fills in from the charge lines; only mark a service that has no lines
B42: Service | C42: Requested by client? | D42: Found in quotation (auto) | G42: Mark if no lines | H42: Coverage (auto) | J42: Firm amount (auto) | M42: Normally paid by (auto)
B43: Pickup | D43: =Checks!$H$55 -> No lines | H43: =Checks!$J$55 -> - | J43: =Checks!$K$55 -> 0 | M43: =Checks!$L$55
B44: Export & origin | D44: =Checks!$H$56 -> No lines | H44: =Checks!$J$56 -> - | J44: =Checks!$K$56 -> 0 | M44: =Checks!$L$56
B45: Main freight | D45: =Checks!$H$57 -> No lines | H45: =Checks!$J$57 -> - | J45: =Checks!$K$57 -> 0 | M45: =Checks!$L$57
B46: Destination port & handling | D46: =Checks!$H$58 -> No lines | H46: =Checks!$J$58 -> - | J46: =Checks!$K$58 -> 0 | M46: =Checks!$L$58
B47: Import clearance | D47: =Checks!$H$59 -> No lines | H47: =Checks!$J$59 -> - | J47: =Checks!$K$59 -> 0 | M47: =Checks!$L$59
B48: Delivery | D48: =Checks!$H$60 -> No lines | H48: =Checks!$J$60 -> - | J48: =Checks!$K$60 -> 0 | M48: =Checks!$L$60
B49: Duties & taxes | D49: =Checks!$H$61 -> No lines | H49: =Checks!$J$61 -> - | J49: =Checks!$K$61 -> 0 | M49: =Checks!$L$61
B51: 4 CHARGE BREAKDOWN One row per quoted charge. Required: Charge, Category, Basis, Rate (unless at cost/TBC), Status
A52: # | B52: Charge (as quoted) | C52: Category | D52: Basis | E52: Rate | F52: Currency | G52: Status | H52: Qty used (auto) | I52: Qty / base override | J52: Minimum charge | K52: Local tax % | L52: Forwarder's line total | M52: Agreed rate | N52: Reviewer flag | O52: Note | P52: Calculated total (quote cur.) | Q52: Check (auto) | R52: Group (auto)
A53: e.g. | B53: THC | C53: O2 Origin terminal & handling | D53: per container | E53: 155 | F53: USD | G53: Firm | H53: 1 | K53: 0.08 | L53: 167.4 | O53: Leave Currency blank = quote currency | P53: 167.40 | Q53: Verified | R53: Origin
A54: 1 | H54: =Checks!$K$2 | P54: =Checks!$N$2 | Q54: =Checks!$Q$2 | R54: =Checks!$E$2
A55: 2 | H55: =Checks!$K$3 | P55: =Checks!$N$3 | Q55: =Checks!$Q$3 | R55: =Checks!$E$3
A56: 3 | H56: =Checks!$K$4 | P56: =Checks!$N$4 | Q56: =Checks!$Q$4 | R56: =Checks!$E$4
A57: 4 | H57: =Checks!$K$5 | P57: =Checks!$N$5 | Q57: =Checks!$Q$5 | R57: =Checks!$E$5
A58: 5 | H58: =Checks!$K$6 | P58: =Checks!$N$6 | Q58: =Checks!$Q$6 | R58: =Checks!$E$6
A59: 6 | H59: =Checks!$K$7 | P59: =Checks!$N$7 | Q59: =Checks!$Q$7 | R59: =Checks!$E$7
A60: 7 | H60: =Checks!$K$8 | P60: =Checks!$N$8 | Q60: =Checks!$Q$8 | R60: =Checks!$E$8
A61: 8 | H61: =Checks!$K$9 | P61: =Checks!$N$9 | Q61: =Checks!$Q$9 | R61: =Checks!$E$9
A62: 9 | H62: =Checks!$K$10 | P62: =Checks!$N$10 | Q62: =Checks!$Q$10 | R62: =Checks!$E$10
A63: 10 | H63: =Checks!$K$11 | P63: =Checks!$N$11 | Q63: =Checks!$Q$11 | R63: =Checks!$E$11
A64: 11 | H64: =Checks!$K$12 | P64: =Checks!$N$12 | Q64: =Checks!$Q$12 | R64: =Checks!$E$12
A65: 12 | H65: =Checks!$K$13 | P65: =Checks!$N$13 | Q65: =Checks!$Q$13 | R65: =Checks!$E$13
A66: 13 | H66: =Checks!$K$14 | P66: =Checks!$N$14 | Q66: =Checks!$Q$14 | R66: =Checks!$E$14
A67: 14 | H67: =Checks!$K$15 | P67: =Checks!$N$15 | Q67: =Checks!$Q$15 | R67: =Checks!$E$15
A68: 15 | H68: =Checks!$K$16 | P68: =Checks!$N$16 | Q68: =Checks!$Q$16 | R68: =Checks!$E$16
A69: 16 | H69: =Checks!$K$17 | P69: =Checks!$N$17 | Q69: =Checks!$Q$17 | R69: =Checks!$E$17
A70: 17 | H70: =Checks!$K$18 | P70: =Checks!$N$18 | Q70: =Checks!$Q$18 | R70: =Checks!$E$18
A71: 18 | H71: =Checks!$K$19 | P71: =Checks!$N$19 | Q71: =Checks!$Q$19 | R71: =Checks!$E$19
A72: 19 | H72: =Checks!$K$20 | P72: =Checks!$N$20 | Q72: =Checks!$Q$20 | R72: =Checks!$E$20
A73: 20 | H73: =Checks!$K$21 | P73: =Checks!$N$21 | Q73: =Checks!$Q$21 | R73: =Checks!$E$21
A74: 21 | H74: =Checks!$K$22 | P74: =Checks!$N$22 | Q74: =Checks!$Q$22 | R74: =Checks!$E$22
A75: 22 | H75: =Checks!$K$23 | P75: =Checks!$N$23 | Q75: =Checks!$Q$23 | R75: =Checks!$E$23
A76: 23 | H76: =Checks!$K$24 | P76: =Checks!$N$24 | Q76: =Checks!$Q$24 | R76: =Checks!$E$24
A77: 24 | H77: =Checks!$K$25 | P77: =Checks!$N$25 | Q77: =Checks!$Q$25 | R77: =Checks!$E$25
A78: 25 | H78: =Checks!$K$26 | P78: =Checks!$N$26 | Q78: =Checks!$Q$26 | R78: =Checks!$E$26
A79: 26 | H79: =Checks!$K$27 | P79: =Checks!$N$27 | Q79: =Checks!$Q$27 | R79: =Checks!$E$27
A80: 27 | H80: =Checks!$K$28 | P80: =Checks!$N$28 | Q80: =Checks!$Q$28 | R80: =Checks!$E$28
A81: 28 | H81: =Checks!$K$29 | P81: =Checks!$N$29 | Q81: =Checks!$Q$29 | R81: =Checks!$E$29
A82: 29 | H82: =Checks!$K$30 | P82: =Checks!$N$30 | Q82: =Checks!$Q$30 | R82: =Checks!$E$30
A83: 30 | H83: =Checks!$K$31 | P83: =Checks!$N$31 | Q83: =Checks!$Q$31 | R83: =Checks!$E$31
A84: 31 | H84: =Checks!$K$32 | P84: =Checks!$N$32 | Q84: =Checks!$Q$32 | R84: =Checks!$E$32
A85: 32 | H85: =Checks!$K$33 | P85: =Checks!$N$33 | Q85: =Checks!$Q$33 | R85: =Checks!$E$33
A86: 33 | H86: =Checks!$K$34 | P86: =Checks!$N$34 | Q86: =Checks!$Q$34 | R86: =Checks!$E$34
A87: 34 | H87: =Checks!$K$35 | P87: =Checks!$N$35 | Q87: =Checks!$Q$35 | R87: =Checks!$E$35
A88: 35 | H88: =Checks!$K$36 | P88: =Checks!$N$36 | Q88: =Checks!$Q$36 | R88: =Checks!$E$36
A89: 36 | H89: =Checks!$K$37 | P89: =Checks!$N$37 | Q89: =Checks!$Q$37 | R89: =Checks!$E$37
A90: 37 | H90: =Checks!$K$38 | P90: =Checks!$N$38 | Q90: =Checks!$Q$38 | R90: =Checks!$E$38
A91: 38 | H91: =Checks!$K$39 | P91: =Checks!$N$39 | Q91: =Checks!$Q$39 | R91: =Checks!$E$39
A92: 39 | H92: =Checks!$K$40 | P92: =Checks!$N$40 | Q92: =Checks!$Q$40 | R92: =Checks!$E$40
A93: 40 | H93: =Checks!$K$41 | P93: =Checks!$N$41 | Q93: =Checks!$Q$41 | R93: =Checks!$E$41
A94: 41 | H94: =Checks!$K$42 | P94: =Checks!$N$42 | Q94: =Checks!$Q$42 | R94: =Checks!$E$42
A95: 42 | H95: =Checks!$K$43 | P95: =Checks!$N$43 | Q95: =Checks!$Q$43 | R95: =Checks!$E$43
A96: 43 | H96: =Checks!$K$44 | P96: =Checks!$N$44 | Q96: =Checks!$Q$44 | R96: =Checks!$E$44
A97: 44 | H97: =Checks!$K$45 | P97: =Checks!$N$45 | Q97: =Checks!$Q$45 | R97: =Checks!$E$45
A98: 45 | H98: =Checks!$K$46 | P98: =Checks!$N$46 | Q98: =Checks!$Q$46 | R98: =Checks!$E$46
A99: 46 | H99: =Checks!$K$47 | P99: =Checks!$N$47 | Q99: =Checks!$Q$47 | R99: =Checks!$E$47
A100: 47 | H100: =Checks!$K$48 | P100: =Checks!$N$48 | Q100: =Checks!$Q$48 | R100: =Checks!$E$48
A101: 48 | H101: =Checks!$K$49 | P101: =Checks!$N$49 | Q101: =Checks!$Q$49 | R101: =Checks!$E$49
A102: 49 | H102: =Checks!$K$50 | P102: =Checks!$N$50 | Q102: =Checks!$Q$50 | R102: =Checks!$E$50
A103: 50 | H103: =Checks!$K$51 | P103: =Checks!$N$51 | Q103: =Checks!$Q$51 | R103: =Checks!$E$51
B104: =Checks!$AF$20 -> Known Firm Charges — Not All-In | P104: =Checks!$AF$10 -> 0
B107: 5 AUDIT RESULTS Automatic - significant findings only
B108: Overall status | C108: =Checks!$AF$2 -> Not started | G108: =Checks!$AF$21 -> Enter shipment, quotation and charge details to start the audit.
...

Sheet Summary
A1: MOVE SUPPLY CHAIN | E1: ="Prepared for: "&Audit!$C$7 -> Prepared for:
A2: Freight Quotation Audit - Summary | E2: ="By: "&Audit!$C$21&" · Audit date: "&IF(ISNUMBER(Audit!$J$6),TEXT(Audit!$J$6,"d mmm yyyy"),"") -> By: · Audit date:
E3: ="Reference: "&Audit!$C$6 -> Reference:
A5: Status | C5: =Checks!$AF$2 -> Not started | E5: =Checks!$AF$21 -> Enter shipment, quotation and charge details to start the audit.
A7: Quotation audited
A8: Forwarder | C8: =Audit!$C$23 -> 0 | D8: Validity | E8: ="Freight: "&IF(ISNUMBER(Audit!$J$24),TEXT(Audit!$J$24,"d mmm yyyy"),"not stated")&" · origin charges: "&IF(ISNUMBER(Audit!$C$33),TEXT(Audit!$C$33,"d mmm yyyy"),"Not Confirmed")&" · destination charges: "&IF(ISNUMBER(Audit!$J$33),TEXT(Audit!$J$33,"d mmm yyyy"),"Not Confirmed") -> Freight: not stated · origin charges: Not Confirmed · destination charges: Not Confirmed
A9: Service | C9: =Audit!$J$25&IF(Audit!$J$25="Sea FCL"," · "&Audit!$C$26&" x "&Audit!$J$26,"") | D9: Route | E9: =Audit!$C$9&" to "&Audit!$J$9&IF(Audit!$J$27<>""," ("&Audit!$J$27&")","") -> to
A10: Shipment | C10: =Audit!$J$13&" pcs · "&Audit!$C$14&" cartons · "&Audit!$J$14&" pallets" -> pcs · cartons · pallets | D10: Cargo | E10: =TEXT(Audit!$C$15,"#,##0.##")&" kg · "&TEXT(Audit!$J$15,"#,##0.###")&" CBM · "&Audit!$C$8&" "&Audit!$J$8 -> 0 kg · 0 CBM ·
A12: Cost picture
A13: =Checks!$AF$20 -> Known Firm Charges — Not All-In | D13: =Checks!$AF$10 -> 0 | E13: =Checks!$AF$22 -> Not all-in:
A14: Estimates (not in firm figure) | D14: =Checks!$AF$11 -> 0
A15: Conditional charges - only if they occur | D15: =Checks!$AF$13 -> 0 | E15: ="Plus "&Checks!$AF$14&" if-required item(s) with no amount" -> Plus 0 if-required item(s) with no amount
A16: Unpriced items (at cost / TBC) | D16: =Checks!$AF$15 -> 0
A17: Confirmed discrepancies (Errors, net) | D17: =Checks!$AF$16 -> 0
A18: Amount under question - NOT a confirmed saving | D18: =Checks!$AF$17 -> 0
A20: Requested services
A21: Service | C21: Requested | D21: Coverage | E21: Normally paid by (Incoterm) | F21: Firm amount
A22: =Audit!$B$43 -> Pickup | C22: =IF(Audit!$C$43="","-",Audit!$C$43) -> - | D22: =Audit!$H$43 -> - | E22: =IF(Audit!$M$43="","-",Audit!$M$43) -> - | F22: =Audit!$J$43 -> 0
A23: =Audit!$B$44 -> Export & origin | C23: =IF(Audit!$C$44="","-",Audit!$C$44) -> - | D23: =Audit!$H$44 -> - | E23: =IF(Audit!$M$44="","-",Audit!$M$44) -> - | F23: =Audit!$J$44 -> 0
A24: =Audit!$B$45 -> Main freight | C24: =IF(Audit!$C$45="","-",Audit!$C$45) -> - | D24: =Audit!$H$45 -> - | E24: =IF(Audit!$M$45="","-",Audit!$M$45) -> - | F24: =Audit!$J$45 -> 0
A25: =Audit!$B$46 -> Destination port & handling | C25: =IF(Audit!$C$46="","-",Audit!$C$46) -> - | D25: =Audit!$H$46 -> - | E25: =IF(Audit!$M$46="","-",Audit!$M$46) -> - | F25: =Audit!$J$46 -> 0
A26: =Audit!$B$47 -> Import clearance | C26: =IF(Audit!$C$47="","-",Audit!$C$47) -> - | D26: =Audit!$H$47 -> - | E26: =IF(Audit!$M$47="","-",Audit!$M$47) -> - | F26: =Audit!$J$47 -> 0
A27: =Audit!$B$48 -> Delivery | C27: =IF(Audit!$C$48="","-",Audit!$C$48) -> - | D27: =Audit!$H$48 -> - | E27: =IF(Audit!$M$48="","-",Audit!$M$48) -> - | F27: =Audit!$J$48 -> 0
A28: =Audit!$B$49 -> Duties & taxes | C28: =IF(Audit!$C$49="","-",Audit!$C$49) -> - | D28: =Audit!$H$49 -> - | E28: =IF(Audit!$M$49="","-",Audit!$M$49) -> - | F28: =Audit!$J$49 -> 0
A30: Findings and recommended actions
A31: # | B31: Type | C31: Charge | D31: Issue | E31: Recommended correction or question | F31: Amount at stake
A32: =Audit!$A$119 | B32: =Audit!$B$119 | C32: =Audit!$C$119 | D32: =Audit!$E$119 | E32: =Audit!$N$119 | F32: =Audit!$Q$119
A33: =Audit!$A$120 | B33: =Audit!$B$120 | C33: =Audit!$C$120 | D33: =Audit!$E$120 | E33: =Audit!$N$120 | F33: =Audit!$Q$120
A34: =Audit!$A$121 | B34: =Audit!$B$121 | C34: =Audit!$C$121 | D34: =Audit!$E$121 | E34: =Audit!$N$121 | F34: =Audit!$Q$121
A35: =Audit!$A$122 | B35: =Audit!$B$122 | C35: =Audit!$C$122 | D35: =Audit!$E$122 | E35: =Audit!$N$122 | F35: =Audit!$Q$122
A36: =Audit!$A$123 | B36: =Audit!$B$123 | C36: =Audit!$C$123 | D36: =Audit!$E$123 | E36: =Audit!$N$123 | F36: =Audit!$Q$123
A37: =Audit!$A$124 | B37: =Audit!$B$124 | C37: =Audit!$C$124 | D37: =Audit!$E$124 | E37: =Audit!$N$124 | F37: =Audit!$Q$124
A38: =Audit!$A$125 | B38: =Audit!$B$125 | C38: =Audit!$C$125 | D38: =Audit!$E$125 | E38: =Audit!$N$125 | F38: =Audit!$Q$125
A39: =Audit!$A$126 | B39: =Audit!$B$126 | C39: =Audit!$C$126 | D39: =Audit!$E$126 | E39: =Audit!$N$126 | F39: =Audit!$Q$126
A40: =Audit!$A$127 | B40: =Audit!$B$127 | C40: =Audit!$C$127 | D40: =Audit!$E$127 | E40: =Audit!$N$127 | F40: =Audit!$Q$127
A41: =Audit!$A$128 | B41: =Audit!$B$128 | C41: =Audit!$C$128 | D41: =Audit!$E$128 | E41: =Audit!$N$128 | F41: =Audit!$Q$128
A42: =Audit!$A$129 | B42: =Audit!$B$129 | C42: =Audit!$C$129 | D42: =Audit!$E$129 | E42: =Audit!$N$129 | F42: =Audit!$Q$129
A43: =Audit!$A$130 | B43: =Audit!$B$130 | C43: =Audit!$C$130 | D43: =Audit!$E$130 | E43: =Audit!$N$130 | F43: =Audit!$Q$130
A44: =Audit!$A$131 | B44: =Audit!$B$131 | C44: =Audit!$C$131 | D44: =Audit!$E$131 | E44: =Audit!$N$131 | F44: =Audit!$Q$131
A45: =Audit!$A$132 | B45: =Audit!$B$132 | C45: =Audit!$C$132 | D45: =Audit!$E$132 | E45: =Audit!$N$132 | F45: =Audit!$Q$132
A46: =Audit!$A$133 | B46: =Audit!$B$133 | C46: =Audit!$C$133 | D46: =Audit!$E$133 | E46: =Audit!$N$133 | F46: =Audit!$Q$133
A47: =Audit!$A$134 | B47: =Audit!$B$134 | C47: =Audit!$C$134 | D47: =Audit!$E$134 | E47: =Audit!$N$134 | F47: =Audit!$Q$134
A48: =Audit!$A$135 | B48: =Audit!$B$135 | C48: =Audit!$C$135 | D48: =Audit!$E$135 | E48: =Audit!$N$135 | F48: =Audit!$Q$135
A49: =Audit!$A$136 | B49: =Audit!$B$136 | C49: =Audit!$C$136 | D49: =Audit!$E$136 | E49: =Audit!$N$136 | F49: =Audit!$Q$136
A50: =Audit!$A$137 | B50: =Audit!$B$137 | C50: =Audit!$C$137 | D50: =Audit!$E$137 | E50: =Audit!$N$137 | F50: =Audit!$Q$137
A51: =Audit!$A$138 | B51: =Audit!$B$138 | C51: =Audit!$C$138 | D51: =Audit!$E$138 | E51: =Audit!$N$138 | F51: =Audit!$Q$138
A52: =Audit!$A$139 | B52: =Audit!$B$139 | C52: =Audit!$C$139 | D52: =Audit!$E$139 | E52: =Audit!$N$139 | F52: =Audit!$Q$139
A53: =Audit!$A$140 | B53: =Audit!$B$140 | C53: =Audit!$C$140 | D53: =Audit!$E$140 | E53: =Audit!$N$140 | F53: =Audit!$Q$140
A54: =Audit!$A$141 | B54: =Audit!$B$141 | C54: =Audit!$C$141 | D54: =Audit!$E$141 | E54: =Audit!$N$141 | F54: =Audit!$Q$141
A55: =Audit!$A$142 | B55: =Audit!$B$142 | C55: =Audit!$C$142 | D55: =Audit!$E$142 | E55: =Audit!$N$142 | F55: =Audit!$Q$142
A56: =Audit!$A$143 | B56: =Audit!$B$143 | C56: =Audit!$C$143 | D56: =Audit!$E$143 | E56: =Audit!$N$143 | F56: =Audit!$Q$143
A57: =Audit!$A$144 | B57: =Audit!$B$144 | C57: =Audit!$C$144 | D57: =Audit!$E$144 | E57: =Audit!$N$144 | F57: =Audit!$Q$144
A58: =Audit!$A$145 | B58: =Audit!$B$145 | C58: =Audit!$C$145 | D58: =Audit!$E$145 | E58: =Audit!$N$145 | F58: =Audit!$Q$145
A59: =Audit!$A$146 | B59: =Audit!$B$146 | C59: =Audit!$C$146 | D59: =Audit!$E$146 | E59: =Audit!$N$146 | F59: =Audit!$Q$146
A60: =Audit!$A$147 | B60: =Audit!$B$147 | C60: =Audit!$C$147 | D60: =Audit!$E$147 | E60: =Audit!$N$147 | F60: =Audit!$Q$147
A61: =Audit!$A$148 | B61: =Audit!$B$148 | C61: =Audit!$C$148 | D61: =Audit!$E$148 | E61: =Audit!$N$148 | F61: =Audit!$Q$148
A63: Questions to send to the forwarder
A64: =IF(Checks!$AN$2="","",1&".") | B64: =IF(Checks!$AN$2="","",INDEX(Checks!$E$70:$E$470,Checks!$AN$2)&" - "&INDEX(Checks!$H$70:$H$470,Checks!$AN$2))
A65: =IF(Checks!$AN$3="","",2&".") | B65: =IF(Checks!$AN$3="","",INDEX(Checks!$E$70:$E$470,Checks!$AN$3)&" - "&INDEX(Checks!$H$70:$H$470,Checks!$AN$3))
A66: =IF(Checks!$AN$4="","",3&".") | B66: =IF(Checks!$AN$4="","",INDEX(Checks!$E$70:$E$470,Checks!$AN$4)&" - "&INDEX(Checks!$H$70:$H$470,Checks!$AN$4))
A67: =IF(Checks!$AN$5="","",4&".") | B67: =IF(Checks!$AN$5="","",INDEX(Checks!$E$70:$E$470,Checks!$AN$5)&" - "&INDEX(Checks!$H$70:$H$470,Checks!$AN$5))
A68: =IF(Checks!$AN$6="","",5&".") | B68: =IF(Checks!$AN$6="","",INDEX(Checks!$E$70:$E$470,Checks!$AN$6)&" - "&INDEX(Checks!$H$70:$H$470,Checks!$AN$6))
A69: =IF(Checks!$AN$7="","",6&".") | B69: =IF(Checks!$AN$7="","",INDEX(Checks!$E$70:$E$470,Checks!$AN$7)&" - "&INDEX(Checks!$H$70:$H$470,Checks!$AN$7))
A70: =IF(Checks!$AN$8="","",7&".") | B70: =IF(Checks!$AN$8="","",INDEX(Checks!$E$70:$E$470,Checks!$AN$8)&" - "&INDEX(Checks!$H$70:$H$470,Checks!$AN$8))
A71: =IF(Checks!$AN$9="","",8&".") | B71: =IF(Checks!$AN$9="","",INDEX(Checks!$E$70:$E$470,Checks!$AN$9)&" - "&INDEX(Checks!$H$70:$H$470,Checks!$AN$9))
A72: =IF(Checks!$AN$10="","",9&".") | B72: =IF(Checks!$AN$10="","",INDEX(Checks!$E$70:$E$470,Checks!$AN$10)&" - "&INDEX(Checks!$H$70:$H$470,Checks!$AN$10))
A73: =IF(Checks!$AN$11="","",10&".") | B73: =IF(Checks!$AN$11="","",INDEX(Checks!$E$70:$E$470,Checks!$AN$11)&" - "&INDEX(Checks!$H$70:$H$470,Checks!$AN$11))
A74: =IF(Checks!$AN$12="","",11&".") | B74: =IF(Checks!$AN$12="","",INDEX(Checks!$E$70:$E$470,Checks!$AN$12)&" - "&INDEX(Checks!$H$70:$H$470,Checks!$AN$12))
A75: =IF(Checks!$AN$13="","",12&".") | B75: =IF(Checks!$AN$13="","",INDEX(Checks!$E$70:$E$470,Checks!$AN$13)&" - "&INDEX(Checks!$H$70:$H$470,Checks!$AN$13))
A76: =IF(Checks!$AN$14="","",13&".") | B76: =IF(Checks!$AN$14="","",INDEX(Checks!$E$70:$E$470,Checks!$AN$14)&" - "&INDEX(Checks!$H$70:$H$470,Checks!$AN$14))
A77: =IF(Checks!$AN$15="","",14&".") | B77: =IF(Checks!$AN$15="","",INDEX(Checks!$E$70:$E$470,Checks!$AN$15)&" - "&INDEX(Checks!$H$70:$H$470,Checks!$AN$15))
A78: =IF(Checks!$AN$16="","",15&".") | B78: =IF(Checks!$AN$16="","",INDEX(Checks!$E$70:$E$470,Checks!$AN$16)&" - "&INDEX(Checks!$H$70:$H$470,Checks!$AN$16))
A80: Scope of this audit
A81: ="Checked: calculations, charging bases and quantities, consistency with the commercial invoice and packing list, duplicated or unexplained charges, missing charges, coverage of the requested services"&IF(Audit!$C$19="Yes",", and agreed rates.",".") -> Checked: calculations, charging bases and quantities, consistency with the commercial invoice and packing list, duplicated or unexplained charges, missing charges, coverage of the requested services.
A82: ="Not checked: "&Checks!$AF$24 -> Not checked: Agreed rates (no rate agreement provided); market price levels (no benchmark used); duty and tax rates (to be confirmed by a licensed customs broker).
A83: ="Line verification: "&Checks!$AF$23&". 'Verified' means the forwarder's own line amount reconciles; other lines are calculated from the entered rates only." -> Line verification: 0 verified · 0 calculated, not independently verified · 0 with errors. 'Verified' means the forwarder's own line amount reconciles; other lines are calculated from the entered rates only.

Sheet Lists
A1: Lists & settings (used by the dropdowns and checks; edit settings in column B rows 41-44 only)
A3: Category | B3: Group | C3: Service | E3: Basis | G3: Status | I3: Incoterm | J3: Pickup | K3: Export & origin | L3: Main freight | M3: Destination port & handling | N3: Import clearance | O3: Delivery | P3: Duties & taxes
A4: O1 Pickup | B4: Origin | C4: Pickup | E4: per container | G4: Firm | I4: EXW | J4: Buyer | K4: Buyer | L4: Buyer | M4: Buyer | N4: Buyer | O4: Buyer | P4: Buyer
A5: O2 Origin terminal & handling | B5: Origin | C5: Export & origin | E5: per B/L | G5: Estimate | I5: FCA | J5: Buyer | K5: Shared | L5: Buyer | M5: Buyer | N5: Buyer | O5: Buyer | P5: Buyer
A6: O3 Export docs, filing & clearance | B6: Origin | C6: Export & origin | E6: per shipment | G6: If required | I6: FAS | J6: Seller | K6: Shared | L6: Buyer | M6: Buyer | N6: Buyer | O6: Buyer | P6: Buyer
A7: F1 Base freight | B7: Main Freight | C7: Main freight | E7: per declaration / set | G7: At cost | I7: FOB | J7: Seller | K7: Seller | L7: Buyer | M7: Buyer | N7: Buyer | O7: Buyer | P7: Buyer
A8: F2 Freight surcharges | B8: Main Freight | C8: Main freight | E8: per CBM | G8: TBC | I8: CFR | J8: Seller | K8: Seller | L8: Seller | M8: Shared | N8: Buyer | O8: Buyer | P8: Buyer
A9: D1 Destination terminal & port | B9: Destination | C9: Destination port & handling | E9: per RT (CBM or tonne) | G9: Included | I9: CIF | J9: Seller | K9: Seller | L9: Seller | M9: Shared | N9: Buyer | O9: Buyer | P9: Buyer
A10: D2 Destination docs & handling | B10: Destination | C10: Destination port & handling | E10: per kg | G10: Excluded | I10: CPT | J10: Seller | K10: Seller | L10: Seller | M10: Shared | N10: Buyer | O10: Shared | P10: Buyer
A11: D3 Import customs clearance | B11: Destination | C11: Import clearance | E11: per unit (enter qty) | G11: Not applicable | I11: CIP | J11: Seller | K11: Seller | L11: Seller | M11: Shared | N11: Buyer | O11: Shared | P11: Buyer
A12: D4 Delivery | B12: Destination | C12: Delivery | E12: % of base (enter base) | I12: DAP | J12: Seller | K12: Seller | L12: Seller | M12: Seller | N12: Buyer | O12: Seller | P12: Buyer
A13: T1 Import duty | B13: Duties/Taxes | C13: Duties & taxes | E13: lump sum | I13: DPU | J13: Seller | K13: Seller | L13: Seller | M13: Seller | N13: Buyer | O13: Seller | P13: Buyer
A14: T2 Import VAT / GST | B14: Duties/Taxes | C14: Duties & taxes | E14: at cost | I14: DDP | J14: Seller | K14: Seller | L14: Seller | M14: Seller | N14: Seller | O14: Seller | P14: Seller
A15: T3 Tax-related fees | B15: Duties/Taxes | C15: Duties & taxes
A16: Unclassified | B16: Other | C16: Other | I16: Who normally pays each service under Incoterms 2020 (general practice; 'Shared' = depends on named place or terminal practice, so no question is raised).
A20: Reviewer flag | B20: Issue | C20: Default explanation | E20: Recommended action | G20: Use line amount
A21: Possible duplicate | B21: Possible duplicate charge | C21: The same service may already be charged in another line. | E21: Ask whether this service is already included elsewhere; remove it if duplicated. | G21: 1
A22: Unclear / unexplained | B22: Charge not explained | C22: The charge name or purpose is not clear from the quotation. | E22: Ask the forwarder what this charge covers and why it applies. | G22: 1
A23: Not applicable to this cargo | B23: May not apply to this shipment | C23: The charge does not appear to apply to this cargo or route. | E23: Ask the forwarder to remove it or explain why it applies. | G23: 1
A24: Questionable basis or unit | B24: Charging basis looks wrong | C24: The unit or quantity used does not suit this charge. | E24: Ask the forwarder to confirm the unit and quantity used. | G24: 0
A25: Other - see note | B25: Reviewer query | C25: See the note on this line. | E25: Raise the note with the forwarder. | G25: 0
A29: Services (order fixed)
A30: Pickup
A31: Export & origin
A32: Main freight
A33: Destination port & handling
A34: Import clearance
A35: Delivery
A36: Duties & taxes
A40: Setting | B40: Value | C40: Meaning
A41: Default air volume divisor (cm3 per kg) | B41: 6000 | C41: Used only when the quotation or carrier tariff states no divisor.
A42: Validity warning (days) | B42: 7 | C42: A Risk is raised when rates expire within this many days of the audit date.
A43: Weight / CBM review threshold (%) | B43: 0 | C43: 0 = every difference is raised for review. Differences are never accepted automatically.
A44: Rounding tolerance (amount) | B44: 0.01 | C44: Differences up to this amount are treated as rounding when reconciling line totals.

Sheet Checks
A1: Line | B1: Name | C1: Category | D1: Service | E1: Group | F1: Status | G1: Basis code | H1: Rate | I1: Currency | J1: FX | K1: Qty used | L1: Pre-tax (line cur) | M1: Incl. tax (line cur) | N1: Total (quote cur) | O1: Priced | P1: Fwd total | Q1: Verification | R1: Diff (quote cur) | S1: Agreed excess | T1: Flag | U1: Dup | V1: In scope | W1: Unpriced | X1: Q kind | Y1: Tax
A2: 1 | B2: =TRIM(Audit!$B$54) | C2: =Audit!$C$54&"" | D2: =IF(B2="","",IF(C2="","Other",IFERROR(INDEX(Lists!$C$4:$C$16,MATCH(C2,Lists!$A$4:$A$16,0)),"Other"))) | E2: =IF(B2="","",IF(C2="","Other",IFERROR(INDEX(Lists!$B$4:$B$16,MATCH(C2,Lists!$A$4:$A$16,0)),"Other"))) | F2: =Audit!$G$54&"" | G2: =IFERROR(MATCH(Audit!$D$54,Lists!$E$4:$E$14,0),0) -> 0 | H2: =IF(ISNUMBER(Audit!$E$54),Audit!$E$54,"") | I2: =IF(TRIM(Audit!$F$54)="",Audit!$C$25,TRIM(Audit!$F$54)) -> 0 | J2: =IF(OR(I2=Audit!$C$25,I2=""),1,IF(AND(I2=Audit!$C$31,ISNUMBER(Audit!$J$31)),Audit!$J$31,IF(AND(I2=Audit!$C$32,ISNUMBER(Audit!$J$32)),Audit!$J$32,""))) -> 1 | K2: =IF(B2="","",IF(ISNUMBER(Audit!$I$54),Audit!$I$54,IF(G2=0,"",CHOOSE(G2,IF(ISNUMBER(Audit!$C$26),Audit!$C$26,1),1,1,1,$AF$33,$AF$30,$AF$31,1,"",1,0)))) | L2: =IF(O2=1,ROUND(MAX(H2*K2,IF(ISNUMBER(Audit!$J$54),Audit!$J$54,0)),2),"") | M2: =IF(O2=1,ROUND(L2*(1+Y2),2),"") | N2: =IF(O2=1,IF(ISNUMBER(J2),ROUND(M2*J2,2),""),"") | O2: =IF(AND(B2<>"",OR(F2="Firm",F2="Estimate",F2="If required"),ISNUMBER(H2),G2>0,G2<>11,ISNUMBER(K2)),1,0) -> 0 | P2: =IF(ISNUMBER(Audit!$L$54),Audit!$L$54,"") | Q2: =IF(B2="","",IF(OR(F2="At cost",F2="TBC"),"Not priced ("&F2&")",IF(OR(F2="Included",F2="Excluded",F2="Not applicable"),F2,IF(F2="","Status missing",IF(AND(F2="If required",NOT(ISNUMBER(H2))),"Not priced (if required)",IF(G2=0,"Basis missing",IF(G2=11,"Not priced (at cost)",IF(NOT(ISNUMBER(H2)),"Rate missing",IF(AND(G2=9,NOT(ISNUMBER(Audit!$I$54))),"Base amount missing",IF(NOT(ISNUMBER(J2)),"Exchange rate missing",IF(NOT(ISNUMBER(P2)),"Calculated — Not Independently Verified",IF(ABS(R2)<=Lists!$B$44,"Verified","Error - differs by "&TEXT(R2,"#,##0.00")&" "&I2)))))))))))) | R2: =IF(AND(O2=1,ISNUMBER(P2)),IF(ABS(P2-L2)<=ABS(P2-M2),P2-L2,P2-M2),"") | S2: =IF(AND(O2=1,ISNUMBER(Audit!$M$54),ISNUMBER(J2)),IF(H2-Audit!$M$54>0.005,ROUND((H2-Audit!$M$54)*K2*(1+Y2)*J2,2),0),0) -> 0 | T2: =Audit!$N$54&"" | U2: =IF(B2="",0,IF(COUNTIFS($B$2:$B$51,B2,$D$2:$D$51,D2)>1,1,0)) -> 0 | V2: =IF(D2="","",IFERROR(INDEX(Audit!$C$43:$C$49,MATCH(D2,Lists!$A$30:$A$36,0)),"")) | W2: =IF(AND(B2<>"",OR(F2="At cost",F2="TBC",AND(F2<>"If required",G2=11))),1,0) -> 0 | X2: =IF(B2="","",IF(T2<>"","flag",IF(F2="","status",IF(AND(G2=0,OR(F2="Firm",F2="Estimate",AND(F2="If required",ISNUMBER(H2)))),"basis",IF(AND(OR(F2="Firm",F2="Estimate"),G2<>11,NOT(ISNUMBER(H2))),"rate",IF(AND(O2=0,G2=9,OR(F2="Firm",F2="Estimate"),ISNUMBER(H2)),"base",IF(OR(C2="",C2="Unclassified"),"unclass",IF(U2=1,"dup",IF(AND(Audit!$C$19="Yes",O2=1,NOT(ISNUMBER(Audit!$M$54))),"noagree",""))))))))) | Y2: =IF(ISNUMBER(Audit!$K$54),Audit!$K$54,0) -> 0 | Z2: =IF(AND(F2="Firm",O2=1,ISNUMBER(J2)),L2*J2,0) -> 0 | AE2: Status | AF2: =IF(AF34=1,"Not started",IF(AF6=1,"Insufficient Information",IF(AF3>0,"Corrections Required",IF(AF4+AF5>0,"Needs Clarification","Audit Complete — No Issues Identified")))) -> Not started | AH2: 1 | AI2: =IFERROR(SMALL($J$70:$J$470,AH2),"") | AJ2: =IF(AI2="","",MATCH(AI2,$J$70:$J$470,0)) | AL2: 1 | AM2: =IFERROR(SMALL($K$70:$K$470,AL2),"") | AN2: =IF(AM2="","",MATCH(AM2,$K$70:$K$470,0))
A3: 2 | B3: =TRIM(Audit!$B$55) | C3: =Audit!$C$55&"" | D3: =IF(B3="","",IF(C3="","Other",IFERROR(INDEX(Lists!$C$4:$C$16,MATCH(C3,Lists!$A$4:$A$16,0)),"Other"))) | E3: =IF(B3="","",IF(C3="","Other",IFERROR(INDEX(Lists!$B$4:$B$16,MATCH(C3,Lists!$A$4:$A$16,0)),"Other"))) | F3: =Audit!$G$55&"" | G3: =IFERROR(MATCH(Audit!$D$55,Lists!$E$4:$E$14,0),0) -> 0 | H3: =IF(ISNUMBER(Audit!$E$55),Audit!$E$55,"") | I3: =IF(TRIM(Audit!$F$55)="",Audit!$C$25,TRIM(Audit!$F$55)) -> 0 | J3: =IF(OR(I3=Audit!$C$25,I3=""),1,IF(AND(I3=Audit!$C$31,ISNUMBER(Audit!$J$31)),Audit!$J$31,IF(AND(I3=Audit!$C$32,ISNUMBER(Audit!$J$32)),Audit!$J$32,""))) -> 1 | K3: =IF(B3="","",IF(ISNUMBER(Audit!$I$55),Audit!$I$55,IF(G3=0,"",CHOOSE(G3,IF(ISNUMBER(Audit!$C$26),Audit!$C$26,1),1,1,1,$AF$33,$AF$30,$AF$31,1,"",1,0)))) | L3: =IF(O3=1,ROUND(MAX(H3*K3,IF(ISNUMBER(Audit!$J$55),Audit!$J$55,0)),2),"") | M3: =IF(O3=1,ROUND(L3*(1+Y3),2),"") | N3: =IF(O3=1,IF(ISNUMBER(J3),ROUND(M3*J3,2),""),"") | O3: =IF(AND(B3<>"",OR(F3="Firm",F3="Estimate",F3="If required"),ISNUMBER(H3),G3>0,G3<>11,ISNUMBER(K3)),1,0) -> 0 | P3: =IF(ISNUMBER(Audit!$L$55),Audit!$L$55,"") | Q3: =IF(B3="","",IF(OR(F3="At cost",F3="TBC"),"Not priced ("&F3&")",IF(OR(F3="Included",F3="Excluded",F3="Not applicable"),F3,IF(F3="","Status missing",IF(AND(F3="If required",NOT(ISNUMBER(H3))),"Not priced (if required)",IF(G3=0,"Basis missing",IF(G3=11,"Not priced (at cost)",IF(NOT(ISNUMBER(H3)),"Rate missing",IF(AND(G3=9,NOT(ISNUMBER(Audit!$I$55))),"Base amount missing",IF(NOT(ISNUMBER(J3)),"Exchange rate missing",IF(NOT(ISNUMBER(P3)),"Calculated — Not Independently Verified",IF(ABS(R3)<=Lists!$B$44,"Verified","Error - differs by "&TEXT(R3,"#,##0.00")&" "&I3)))))))))))) | R3: =IF(AND(O3=1,ISNUMBER(P3)),IF(ABS(P3-L3)<=ABS(P3-M3),P3-L3,P3-M3),"") | S3: =IF(AND(O3=1,ISNUMBER(Audit!$M$55),ISNUMBER(J3)),IF(H3-Audit!$M$55>0.005,ROUND((H3-Audit!$M$55)*K3*(1+Y3)*J3,2),0),0) -> 0 | T3: =Audit!$N$55&"" | U3: =IF(B3="",0,IF(COUNTIFS($B$2:$B$51,B3,$D$2:$D$51,D3)>1,1,0)) -> 0 | V3: =IF(D3="","",IFERROR(INDEX(Audit!$C$43:$C$49,MATCH(D3,Lists!$A$30:$A$36,0)),"")) | W3: =IF(AND(B3<>"",OR(F3="At cost",F3="TBC",AND(F3<>"If required",G3=11))),1,0) -> 0 | X3: =IF(B3="","",IF(T3<>"","flag",IF(F3="","status",IF(AND(G3=0,OR(F3="Firm",F3="Estimate",AND(F3="If required",ISNUMBER(H3)))),"basis",IF(AND(OR(F3="Firm",F3="Estimate"),G3<>11,NOT(ISNUMBER(H3))),"rate",IF(AND(O3=0,G3=9,OR(F3="Firm",F3="Estimate"),ISNUMBER(H3)),"base",IF(OR(C3="",C3="Unclassified"),"unclass",IF(U3=1,"dup",IF(AND(Audit!$C$19="Yes",O3=1,NOT(ISNUMBER(Audit!$M$55))),"noagree",""))))))))) | Y3: =IF(ISNUMBER(Audit!$K$55),Audit!$K$55,0) -> 0 | Z3: =IF(AND(F3="Firm",O3=1,ISNUMBER(J3)),L3*J3,0) -> 0 | AE3: Errors | AF3: =SUMIFS($B$70:$B$470,$C$70:$C$470,"Error") -> 0 | AH3: 2 | AI3: =IFERROR(SMALL($J$70:$J$470,AH3),"") | AJ3: =IF(AI3="","",MATCH(AI3,$J$70:$J$470,0)) | AL3: 2 | AM3: =IFERROR(SMALL($K$70:$K$470,AL3),"") | AN3: =IF(AM3="","",MATCH(AM3,$K$70:$K$470,0))
A4: 3 | B4: =TRIM(Audit!$B$56) | C4: =Audit!$C$56&"" | D4: =IF(B4="","",IF(C4="","Other",IFERROR(INDEX(Lists!$C$4:$C$16,MATCH(C4,Lists!$A$4:$A$16,0)),"Other"))) | E4: =IF(B4="","",IF(C4="","Other",IFERROR(INDEX(Lists!$B$4:$B$16,MATCH(C4,Lists!$A$4:$A$16,0)),"Other"))) | F4: =Audit!$G$56&"" | G4: =IFERROR(MATCH(Audit!$D$56,Lists!$E$4:$E$14,0),0) -> 0 | H4: =IF(ISNUMBER(Audit!$E$56),Audit!$E$56,"") | I4: =IF(TRIM(Audit!$F$56)="",Audit!$C$25,TRIM(Audit!$F$56)) -> 0 | J4: =IF(OR(I4=Audit!$C$25,I4=""),1,IF(AND(I4=Audit!$C$31,ISNUMBER(Audit!$J$31)),Audit!$J$31,IF(AND(I4=Audit!$C$32,ISNUMBER(Audit!$J$32)),Audit!$J$32,""))) -> 1 | K4: =IF(B4="","",IF(ISNUMBER(Audit!$I$56),Audit!$I$56,IF(G4=0,"",CHOOSE(G4,IF(ISNUMBER(Audit!$C$26),Audit!$C$26,1),1,1,1,$AF$33,$AF$30,$AF$31,1,"",1,0)))) | L4: =IF(O4=1,ROUND(MAX(H4*K4,IF(ISNUMBER(Audit!$J$56),Audit!$J$56,0)),2),"") | M4: =IF(O4=1,ROUND(L4*(1+Y4),2),"") | N4: =IF(O4=1,IF(ISNUMBER(J4),ROUND(M4*J4,2),""),"") | O4: =IF(AND(B4<>"",OR(F4="Firm",F4="Estimate",F4="If required"),ISNUMBER(H4),G4>0,G4<>11,ISNUMBER(K4)),1,0) -> 0 | P4: =IF(ISNUMBER(Audit!$L$56),Audit!$L$56,"") | Q4: =IF(B4="","",IF(OR(F4="At cost",F4="TBC"),"Not priced ("&F4&")",IF(OR(F4="Included",F4="Excluded",F4="Not applicable"),F4,IF(F4="","Status missing",IF(AND(F4="If required",NOT(ISNUMBER(H4))),"Not priced (if required)",IF(G4=0,"Basis missing",IF(G4=11,"Not priced (at cost)",IF(NOT(ISNUMBER(H4)),"Rate missing",IF(AND(G4=9,NOT(ISNUMBER(Audit!$I$56))),"Base amount missing",IF(NOT(ISNUMBER(J4)),"Exchange rate missing",IF(NOT(ISNUMBER(P4)),"Calculated — Not Independently Verified",IF(ABS(R4)<=Lists!$B$44,"Verified","Error - differs by "&TEXT(R4,"#,##0.00")&" "&I4)))))))))))) | R4: =IF(AND(O4=1,ISNUMBER(P4)),IF(ABS(P4-L4)<=ABS(P4-M4),P4-L4,P4-M4),"") | S4: =IF(AND(O4=1,ISNUMBER(Audit!$M$56),ISNUMBER(J4)),IF(H4-Audit!$M$56>0.005,ROUND((H4-Audit!$M$56)*K4*(1+Y4)*J4,2),0),0) -> 0 | T4: =Audit!$N$56&"" | U4: =IF(B4="",0,IF(COUNTIFS($B$2:$B$51,B4,$D$2:$D$51,D4)>1,1,0)) -> 0 | V4: =IF(D4="","",IFERROR(INDEX(Audit!$C$43:$C$49,MATCH(D4,Lists!$A$30:$A$36,0)),"")) | W4: =IF(AND(B4<>"",OR(F4="At cost",F4="TBC",AND(F4<>"If required",G4=11))),1,0) -> 0 | X4: =IF(B4="","",IF(T4<>"","flag",IF(F4="","status",IF(AND(G4=0,OR(F4="Firm",F4="Estimate",AND(F4="If required",ISNUMBER(H4)))),"basis",IF(AND(OR(F4="Firm",F4="Estimate"),G4<>11,NOT(ISNUMBER(H4))),"rate",IF(AND(O4=0,G4=9,OR(F4="Firm",F4="Estimate"),ISNUMBER(H4)),"base",IF(OR(C4="",C4="Unclassified"),"unclass",IF(U4=1,"dup",IF(AND(Audit!$C$19="Yes",O4=1,NOT(ISNUMBER(Audit!$M$56))),"noagree",""))))))))) | Y4: =IF(ISNUMBER(Audit!$K$56),Audit!$K$56,0) -> 0 | Z4: =IF(AND(F4="Firm",O4=1,ISNUMBER(J4)),L4*J4,0) -> 0 | AE4: Questions | AF4: =SUMIFS($B$70:$B$470,$C$70:$C$470,"Question") -> 0 | AH4: 3 | AI4: =IFERROR(SMALL($J$70:$J$470,AH4),"") | AJ4: =IF(AI4="","",MATCH(AI4,$J$70:$J$470,0)) | AL4: 3 | AM4: =IFERROR(SMALL($K$70:$K$470,AL4),"") | AN4: =IF(AM4="","",MATCH(AM4,$K$70:$K$470,0))
A5: 4 | B5: =TRIM(Audit!$B$57) | C5: =Audit!$C$57&"" | D5: =IF(B5="","",IF(C5="","Other",IFERROR(INDEX(Lists!$C$4:$C$16,MATCH(C5,Lists!$A$4:$A$16,0)),"Other"))) | E5: =IF(B5="","",IF(C5="","Other",IFERROR(INDEX(Lists!$B$4:$B$16,MATCH(C5,Lists!$A$4:$A$16,0)),"Other"))) | F5: =Audit!$G$57&"" | G5: =IFERROR(MATCH(Audit!$D$57,Lists!$E$4:$E$14,0),0) -> 0 | H5: =IF(ISNUMBER(Audit!$E$57),Audit!$E$57,"") | I5: =IF(TRIM(Audit!$F$57)="",Audit!$C$25,TRIM(Audit!$F$57)) -> 0 | J5: =IF(OR(I5=Audit!$C$25,I5=""),1,IF(AND(I5=Audit!$C$31,ISNUMBER(Audit!$J$31)),Audit!$J$31,IF(AND(I5=Audit!$C$32,ISNUMBER(Audit!$J$32)),Audit!$J$32,""))) -> 1 | K5: =IF(B5="","",IF(ISNUMBER(Audit!$I$57),Audit!$I$57,IF(G5=0,"",CHOOSE(G5,IF(ISNUMBER(Audit!$C$26),Audit!$C$26,1),1,1,1,$AF$33,$AF$30,$AF$31,1,"",1,0)))) | L5: =IF(O5=1,ROUND(MAX(H5*K5,IF(ISNUMBER(Audit!$J$57),Audit!$J$57,0)),2),"") | M5: =IF(O5=1,ROUND(L5*(1+Y5),2),"") | N5: =IF(O5=1,IF(ISNUMBER(J5),ROUND(M5*J5,2),""),"") | O5: =IF(AND(B5<>"",OR(F5="Firm",F5="Estimate",F5="If required"),ISNUMBER(H5),G5>0,G5<>11,ISNUMBER(K5)),1,0) -> 0 | P5: =IF(ISNUMBER(Audit!$L$57),Audit!$L$57,"") | Q5: =IF(B5="","",IF(OR(F5="At cost",F5="TBC"),"Not priced ("&F5&")",IF(OR(F5="Included",F5="Excluded",F5="Not applicable"),F5,IF(F5="","Status missing",IF(AND(F5="If required",NOT(ISNUMBER(H5))),"Not priced (if required)",IF(G5=0,"Basis missing",IF(G5=11,"Not priced (at cost)",IF(NOT(ISNUMBER(H5)),"Rate missing",IF(AND(G5=9,NOT(ISNUMBER(Audit!$I$57))),"Base amount missing",IF(NOT(ISNUMBER(J5)),"Exchange rate missing",IF(NOT(ISNUMBER(P5)),"Calculated — Not Independently Verified",IF(ABS(R5)<=Lists!$B$44,"Verified","Error - differs by "&TEXT(R5,"#,##0.00")&" "&I5)))))))))))) | R5: =IF(AND(O5=1,ISNUMBER(P5)),IF(ABS(P5-L5)<=ABS(P5-M5),P5-L5,P5-M5),"") | S5: =IF(AND(O5=1,ISNUMBER(Audit!$M$57),ISNUMBER(J5)),IF(H5-Audit!$M$57>0.005,ROUND((H5-Audit!$M$57)*K5*(1+Y5)*J5,2),0),0) -> 0 | T5: =Audit!$N$57&"" | U5: =IF(B5="",0,IF(COUNTIFS($B$2:$B$51,B5,$D$2:$D$51,D5)>1,1,0)) -> 0 | V5: =IF(D5="","",IFERROR(INDEX(Audit!$C$43:$C$49,MATCH(D5,Lists!$A$30:$A$36,0)),"")) | W5: =IF(AND(B5<>"",OR(F5="At cost",F5="TBC",AND(F5<>"If required",G5=11))),1,0) -> 0 | X5: =IF(B5="","",IF(T5<>"","flag",IF(F5="","status",IF(AND(G5=0,OR(F5="Firm",F5="Estimate",AND(F5="If required",ISNUMBER(H5)))),"basis",IF(AND(OR(F5="Firm",F5="Estimate"),G5<>11,NOT(ISNUMBER(H5))),"rate",IF(AND(O5=0,G5=9,OR(F5="Firm",F5="Estimate"),ISNUMBER(H5)),"base",IF(OR(C5="",C5="Unclassified"),"unclass",IF(U5=1,"dup",IF(AND(Audit!$C$19="Yes",O5=1,NOT(ISNUMBER(Audit!$M$57))),"noagree",""))))))))) | Y5: =IF(ISNUMBER(Audit!$K$57),Audit!$K$57,0) -> 0 | Z5: =IF(AND(F5="Firm",O5=1,ISNUMBER(J5)),L5*J5,0) -> 0 | AE5: Risks | AF5: =SUMIFS($B$70:$B$470,$C$70:$C$470,"Risk") -> 0 | AH5: 4 | AI5: =IFERROR(SMALL($J$70:$J$470,AH5),"") | AJ5: =IF(AI5="","",MATCH(AI5,$J$70:$J$470,0)) | AL5: 4 | AM5: =IFERROR(SMALL($K$70:$K$470,AL5),"") | AN5: =IF(AM5="","",MATCH(AM5,$K$70:$K$470,0))
A6: 5 | B6: =TRIM(Audit!$B$58) | C6: =Audit!$C$58&"" | D6: =IF(B6="","",IF(C6="","Other",IFERROR(INDEX(Lists!$C$4:$C$16,MATCH(C6,Lists!$A$4:$A$16,0)),"Other"))) | E6: =IF(B6="","",IF(C6="","Other",IFERROR(INDEX(Lists!$B$4:$B$16,MATCH(C6,Lists!$A$4:$A$16,0)),"Other"))) | F6: =Audit!$G$58&"" | G6: =IFERROR(MATCH(Audit!$D$58,Lists!$E$4:$E$14,0),0) -> 0 | H6: =IF(ISNUMBER(Audit!$E$58),Audit!$E$58,"") | I6: =IF(TRIM(Audit!$F$58)="",Audit!$C$25,TRIM(Audit!$F$58)) -> 0 | J6: =IF(OR(I6=Audit!$C$25,I6=""),1,IF(AND(I6=Audit!$C$31,ISNUMBER(Audit!$J$31)),Audit!$J$31,IF(AND(I6=Audit!$C$32,ISNUMBER(Audit!$J$32)),Audit!$J$32,""))) -> 1 | K6: =IF(B6="","",IF(ISNUMBER(Audit!$I$58),Audit!$I$58,IF(G6=0,"",CHOOSE(G6,IF(ISNUMBER(Audit!$C$26),Audit!$C$26,1),1,1,1,$AF$33,$AF$30,$AF$31,1,"",1,0)))) | L6: =IF(O6=1,ROUND(MAX(H6*K6,IF(ISNUMBER(Audit!$J$58),Audit!$J$58,0)),2),"") | M6: =IF(O6=1,ROUND(L6*(1+Y6),2),"") | N6: =IF(O6=1,IF(ISNUMBER(J6),ROUND(M6*J6,2),""),"") | O6: =IF(AND(B6<>"",OR(F6="Firm",F6="Estimate",F6="If required"),ISNUMBER(H6),G6>0,G6<>11,ISNUMBER(K6)),1,0) -> 0 | P6: =IF(ISNUMBER(Audit!$L$58),Audit!$L$58,"") | Q6: =IF(B6="","",IF(OR(F6="At cost",F6="TBC"),"Not priced ("&F6&")",IF(OR(F6="Included",F6="Excluded",F6="Not applicable"),F6,IF(F6="","Status missing",IF(AND(F6="If required",NOT(ISNUMBER(H6))),"Not priced (if required)",IF(G6=0,"Basis missing",IF(G6=11,"Not priced (at cost)",IF(NOT(ISNUMBER(H6)),"Rate missing",IF(AND(G6=9,NOT(ISNUMBER(Audit!$I$58))),"Base amount missing",IF(NOT(ISNUMBER(J6)),"Exchange rate missing",IF(NOT(ISNUMBER(P6)),"Calculated — Not Independently Verified",IF(ABS(R6)<=Lists!$B$44,"Verified","Error - differs by "&TEXT(R6,"#,##0.00")&" "&I6)))))))))))) | R6: =IF(AND(O6=1,ISNUMBER(P6)),IF(ABS(P6-L6)<=ABS(P6-M6),P6-L6,P6-M6),"") | S6: =IF(AND(O6=1,ISNUMBER(Audit!$M$58),ISNUMBER(J6)),IF(H6-Audit!$M$58>0.005,ROUND((H6-Audit!$M$58)*K6*(1+Y6)*J6,2),0),0) -> 0 | T6: =Audit!$N$58&"" | U6: =IF(B6="",0,IF(COUNTIFS($B$2:$B$51,B6,$D$2:$D$51,D6)>1,1,0)) -> 0 | V6: =IF(D6="","",IFERROR(INDEX(Audit!$C$43:$C$49,MATCH(D6,Lists!$A$30:$A$36,0)),"")) | W6: =IF(AND(B6<>"",OR(F6="At cost",F6="TBC",AND(F6<>"If required",G6=11))),1,0) -> 0 | X6: =IF(B6="","",IF(T6<>"","flag",IF(F6="","status",IF(AND(G6=0,OR(F6="Firm",F6="Estimate",AND(F6="If required",ISNUMBER(H6)))),"basis",IF(AND(OR(F6="Firm",F6="Estimate"),G6<>11,NOT(ISNUMBER(H6))),"rate",IF(AND(O6=0,G6=9,OR(F6="Firm",F6="Estimate"),ISNUMBER(H6)),"base",IF(OR(C6="",C6="Unclassified"),"unclass",IF(U6=1,"dup",IF(AND(Audit!$C$19="Yes",O6=1,NOT(ISNUMBER(Audit!$M$58))),"noagree",""))))))))) | Y6: =IF(ISNUMBER(Audit!$K$58),Audit!$K$58,0) -> 0 | Z6: =IF(AND(F6="Firm",O6=1,ISNUMBER(J6)),L6*J6,0) -> 0 | AE6: Insufficient | AF6: =IF(OR(Audit!$C$18="No",Audit!$J$18="No",Audit!$J$19="No",AND(AF7>0,AF8=0)),1,0) -> 0 | AH6: 5 | AI6: =IFERROR(SMALL($J$70:$J$470,AH6),"") | AJ6: =IF(AI6="","",MATCH(AI6,$J$70:$J$470,0)) | AL6: 5 | AM6: =IFERROR(SMALL($K$70:$K$470,AL6),"") | AN6: =IF(AM6="","",MATCH(AM6,$K$70:$K$470,0))
A7: 6 | B7: =TRIM(Audit!$B$59) | C7: =Audit!$C$59&"" | D7: =IF(B7="","",IF(C7="","Other",IFERROR(INDEX(Lists!$C$4:$C$16,MATCH(C7,Lists!$A$4:$A$16,0)),"Other"))) | E7: =IF(B7="","",IF(C7="","Other",IFERROR(INDEX(Lists!$B$4:$B$16,MATCH(C7,Lists!$A$4:$A$16,0)),"Other"))) | F7: =Audit!$G$59&"" | G7: =IFERROR(MATCH(Audit!$D$59,Lists!$E$4:$E$14,0),0) -> 0 | H7: =IF(ISNUMBER(Audit!$E$59),Audit!$E$59,"") | I7: =IF(TRIM(Audit!$F$59)="",Audit!$C$25,TRIM(Audit!$F$59)) -> 0 | J7: =IF(OR(I7=Audit!$C$25,I7=""),1,IF(AND(I7=Audit!$C$31,ISNUMBER(Audit!$J$31)),Audit!$J$31,IF(AND(I7=Audit!$C$32,ISNUMBER(Audit!$J$32)),Audit!$J$32,""))) -> 1 | K7: =IF(B7="","",IF(ISNUMBER(Audit!$I$59),Audit!$I$59,IF(G7=0,"",CHOOSE(G7,IF(ISNUMBER(Audit!$C$26),Audit!$C$26,1),1,1,1,$AF$33,$AF$30,$AF$31,1,"",1,0)))) | L7: =IF(O7=1,ROUND(MAX(H7*K7,IF(ISNUMBER(Audit!$J$59),Audit!$J$59,0)),2),"") | M7: =IF(O7=1,ROUND(L7*(1+Y7),2),"") | N7: =IF(O7=1,IF(ISNUMBER(J7),ROUND(M7*J7,2),""),"") | O7: =IF(AND(B7<>"",OR(F7="Firm",F7="Estimate",F7="If required"),ISNUMBER(H7),G7>0,G7<>11,ISNUMBER(K7)),1,0) -> 0 | P7: =IF(ISNUMBER(Audit!$L$59),Audit!$L$59,"") | Q7: =IF(B7="","",IF(OR(F7="At cost",F7="TBC"),"Not priced ("&F7&")",IF(OR(F7="Included",F7="Excluded",F7="Not applicable"),F7,IF(F7="","Status missing",IF(AND(F7="If required",NOT(ISNUMBER(H7))),"Not priced (if required)",IF(G7=0,"Basis missing",IF(G7=11,"Not priced (at cost)",IF(NOT(ISNUMBER(H7)),"Rate missing",IF(AND(G7=9,NOT(ISNUMBER(Audit!$I$59))),"Base amount missing",IF(NOT(ISNUMBER(J7)),"Exchange rate missing",IF(NOT(ISNUMBER(P7)),"Calculated — Not Independently Verified",IF(ABS(R7)<=Lists!$B$44,"Verified","Error - differs by "&TEXT(R7,"#,##0.00")&" "&I7)))))))))))) | R7: =IF(AND(O7=1,ISNUMBER(P7)),IF(ABS(P7-L7)<=ABS(P7-M7),P7-L7,P7-M7),"") | S7: =IF(AND(O7=1,ISNUMBER(Audit!$M$59),ISNUMBER(J7)),IF(H7-Audit!$M$59>0.005,ROUND((H7-Audit!$M$59)*K7*(1+Y7)*J7,2),0),0) -> 0 | T7: =Audit!$N$59&"" | U7: =IF(B7="",0,IF(COUNTIFS($B$2:$B$51,B7,$D$2:$D$51,D7)>1,1,0)) -> 0 | V7: =IF(D7="","",IFERROR(INDEX(Audit!$C$43:$C$49,MATCH(D7,Lists!$A$30:$A$36,0)),"")) | W7: =IF(AND(B7<>"",OR(F7="At cost",F7="TBC",AND(F7<>"If required",G7=11))),1,0) -> 0 | X7: =IF(B7="","",IF(T7<>"","flag",IF(F7="","status",IF(AND(G7=0,OR(F7="Firm",F7="Estimate",AND(F7="If required",ISNUMBER(H7)))),"basis",IF(AND(OR(F7="Firm",F7="Estimate"),G7<>11,NOT(ISNUMBER(H7))),"rate",IF(AND(O7=0,G7=9,OR(F7="Firm",F7="Estimate"),ISNUMBER(H7)),"base",IF(OR(C7="",C7="Unclassified"),"unclass",IF(U7=1,"dup",IF(AND(Audit!$C$19="Yes",O7=1,NOT(ISNUMBER(Audit!$M$59))),"noagree",""))))))))) | Y7: =IF(ISNUMBER(Audit!$K$59),Audit!$K$59,0) -> 0 | Z7: =IF(AND(F7="Firm",O7=1,ISNUMBER(J7)),L7*J7,0) -> 0 | AE7: Lines entered | AF7: =COUNTIF($B$2:$B$51,"?*") -> 0 | AH7: 6 | AI7: =IFERROR(SMALL($J$70:$J$470,AH7),"") | AJ7: =IF(AI7="","",MATCH(AI7,$J$70:$J$470,0)) | AL7: 6 | AM7: =IFERROR(SMALL($K$70:$K$470,AL7),"") | AN7: =IF(AM7="","",MATCH(AM7,$K$70:$K$470,0))
A8: 7 | B8: =TRIM(Audit!$B$60) | C8: =Audit!$C$60&"" | D8: =IF(B8="","",IF(C8="","Other",IFERROR(INDEX(Lists!$C$4:$C$16,MATCH(C8,Lists!$A$4:$A$16,0)),"Other"))) | E8: =IF(B8="","",IF(C8="","Other",IFERROR(INDEX(Lists!$B$4:$B$16,MATCH(C8,Lists!$A$4:$A$16,0)),"Other"))) | F8: =Audit!$G$60&"" | G8: =IFERROR(MATCH(Audit!$D$60,Lists!$E$4:$E$14,0),0) -> 0 | H8: =IF(ISNUMBER(Audit!$E$60),Audit!$E$60,"") | I8: =IF(TRIM(Audit!$F$60)="",Audit!$C$25,TRIM(Audit!$F$60)) -> 0 | J8: =IF(OR(I8=Audit!$C$25,I8=""),1,IF(AND(I8=Audit!$C$31,ISNUMBER(Audit!$J$31)),Audit!$J$31,IF(AND(I8=Audit!$C$32,ISNUMBER(Audit!$J$32)),Audit!$J$32,""))) -> 1 | K8: =IF(B8="","",IF(ISNUMBER(Audit!$I$60),Audit!$I$60,IF(G8=0,"",CHOOSE(G8,IF(ISNUMBER(Audit!$C$26),Audit!$C$26,1),1,1,1,$AF$33,$AF$30,$AF$31,1,"",1,0)))) | L8: =IF(O8=1,ROUND(MAX(H8*K8,IF(ISNUMBER(Audit!$J$60),Audit!$J$60,0)),2),"") | M8: =IF(O8=1,ROUND(L8*(1+Y8),2),"") | N8: =IF(O8=1,IF(ISNUMBER(J8),ROUND(M8*J8,2),""),"") | O8: =IF(AND(B8<>"",OR(F8="Firm",F8="Estimate",F8="If required"),ISNUMBER(H8),G8>0,G8<>11,ISNUMBER(K8)),1,0) -> 0 | P8: =IF(ISNUMBER(Audit!$L$60),Audit!$L$60,"") | Q8: =IF(B8="","",IF(OR(F8="At cost",F8="TBC"),"Not priced ("&F8&")",IF(OR(F8="Included",F8="Excluded",F8="Not applicable"),F8,IF(F8="","Status missing",IF(AND(F8="If required",NOT(ISNUMBER(H8))),"Not priced (if required)",IF(G8=0,"Basis missing",IF(G8=11,"Not priced (at cost)",IF(NOT(ISNUMBER(H8)),"Rate missing",IF(AND(G8=9,NOT(ISNUMBER(Audit!$I$60))),"Base amount missing",IF(NOT(ISNUMBER(J8)),"Exchange rate missing",IF(NOT(ISNUMBER(P8)),"Calculated — Not Independently Verified",IF(ABS(R8)<=Lists!$B$44,"Verified","Error - differs by "&TEXT(R8,"#,##0.00")&" "&I8)))))))))))) | R8: =IF(AND(O8=1,ISNUMBER(P8)),IF(ABS(P8-L8)<=ABS(P8-M8),P8-L8,P8-M8),"") | S8: =IF(AND(O8=1,ISNUMBER(Audit!$M$60),ISNUMBER(J8)),IF(H8-Audit!$M$60>0.005,ROUND((H8-Audit!$M$60)*K8*(1+Y8)*J8,2),0),0) -> 0 | T8: =Audit!$N$60&"" | U8: =IF(B8="",0,IF(COUNTIFS($B$2:$B$51,B8,$D$2:$D$51,D8)>1,1,0)) -> 0 | V8: =IF(D8="","",IFERROR(INDEX(Audit!$C$43:$C$49,MATCH(D8,Lists!$A$30:$A$36,0)),"")) | W8: =IF(AND(B8<>"",OR(F8="At cost",F8="TBC",AND(F8<>"If required",G8=11))),1,0) -> 0 | X8: =IF(B8="","",IF(T8<>"","flag",IF(F8="","status",IF(AND(G8=0,OR(F8="Firm",F8="Estimate",AND(F8="If required",ISNUMBER(H8)))),"basis",IF(AND(OR(F8="Firm",F8="Estimate"),G8<>11,NOT(ISNUMBER(H8))),"rate",IF(AND(O8=0,G8=9,OR(F8="Firm",F8="Estimate"),ISNUMBER(H8)),"base",IF(OR(C8="",C8="Unclassified"),"unclass",IF(U8=1,"dup",IF(AND(Audit!$C$19="Yes",O8=1,NOT(ISNUMBER(Audit!$M$60))),"noagree",""))))))))) | Y8: =IF(ISNUMBER(Audit!$K$60),Audit!$K$60,0) -> 0 | Z8: =IF(AND(F8="Firm",O8=1,ISNUMBER(J8)),L8*J8,0) -> 0 | AE8: Priced lines | AF8: =SUM($O$2:$O$51) -> 0 | AH8: 7 | AI8: =IFERROR(SMALL($J$70:$J$470,AH8),"") | AJ8: =IF(AI8="","",MATCH(AI8,$J$70:$J$470,0)) | AL8: 7 | AM8: =IFERROR(SMALL($K$70:$K$470,AL8),"") | AN8: =IF(AM8="","",MATCH(AM8,$K$70:$K$470,0))
A9: 8 | B9: =TRIM(Audit!$B$61) | C9: =Audit!$C$61&"" | D9: =IF(B9="","",IF(C9="","Other",IFERROR(INDEX(Lists!$C$4:$C$16,MATCH(C9,Lists!$A$4:$A$16,0)),"Other"))) | E9: =IF(B9="","",IF(C9="","Other",IFERROR(INDEX(Lists!$B$4:$B$16,MATCH(C9,Lists!$A$4:$A$16,0)),"Other"))) | F9: =Audit!$G$61&"" | G9: =IFERROR(MATCH(Audit!$D$61,Lists!$E$4:$E$14,0),0) -> 0 | H9: =IF(ISNUMBER(Audit!$E$61),Audit!$E$61,"") | I9: =IF(TRIM(Audit!$F$61)="",Audit!$C$25,TRIM(Audit!$F$61)) -> 0 | J9: =IF(OR(I9=Audit!$C$25,I9=""),1,IF(AND(I9=Audit!$C$31,ISNUMBER(Audit!$J$31)),Audit!$J$31,IF(AND(I9=Audit!$C$32,ISNUMBER(Audit!$J$32)),Audit!$J$32,""))) -> 1 | K9: =IF(B9="","",IF(ISNUMBER(Audit!$I$61),Audit!$I$61,IF(G9=0,"",CHOOSE(G9,IF(ISNUMBER(Audit!$C$26),Audit!$C$26,1),1,1,1,$AF$33,$AF$30,$AF$31,1,"",1,0)))) | L9: =IF(O9=1,ROUND(MAX(H9*K9,IF(ISNUMBER(Audit!$J$61),Audit!$J$61,0)),2),"") | M9: =IF(O9=1,ROUND(L9*(1+Y9),2),"") | N9: =IF(O9=1,IF(ISNUMBER(J9),ROUND(M9*J9,2),""),"") | O9: =IF(AND(B9<>"",OR(F9="Firm",F9="Estimate",F9="If required"),ISNUMBER(H9),G9>0,G9<>11,ISNUMBER(K9)),1,0) -> 0 | P9: =IF(ISNUMBER(Audit!$L$61),Audit!$L$61,"") | Q9: =IF(B9="","",IF(OR(F9="At cost",F9="TBC"),"Not priced ("&F9&")",IF(OR(F9="Included",F9="Excluded",F9="Not applicable"),F9,IF(F9="","Status missing",IF(AND(F9="If required",NOT(ISNUMBER(H9))),"Not priced (if required)",IF(G9=0,"Basis missing",IF(G9=11,"Not priced (at cost)",IF(NOT(ISNUMBER(H9)),"Rate missing",IF(AND(G9=9,NOT(ISNUMBER(Audit!$I$61))),"Base amount missing",IF(NOT(ISNUMBER(J9)),"Exchange rate missing",IF(NOT(ISNUMBER(P9)),"Calculated — Not Independently Verified",IF(ABS(R9)<=Lists!$B$44,"Verified","Error - differs by "&TEXT(R9,"#,##0.00")&" "&I9)))))))))))) | R9: =IF(AND(O9=1,ISNUMBER(P9)),IF(ABS(P9-L9)<=ABS(P9-M9),P9-L9,P9-M9),"") | S9: =IF(AND(O9=1,ISNUMBER(Audit!$M$61),ISNUMBER(J9)),IF(H9-Audit!$M$61>0.005,ROUND((H9-Audit!$M$61)*K9*(1+Y9)*J9,2),0),0) -> 0 | T9: =Audit!$N$61&"" | U9: =IF(B9="",0,IF(COUNTIFS($B$2:$B$51,B9,$D$2:$D$51,D9)>1,1,0)) -> 0 | V9: =IF(D9="","",IFERROR(INDEX(Audit!$C$43:$C$49,MATCH(D9,Lists!$A$30:$A$36,0)),"")) | W9: =IF(AND(B9<>"",OR(F9="At cost",F9="TBC",AND(F9<>"If required",G9=11))),1,0) -> 0 | X9: =IF(B9="","",IF(T9<>"","flag",IF(F9="","status",IF(AND(G9=0,OR(F9="Firm",F9="Estimate",AND(F9="If required",ISNUMBER(H9)))),"basis",IF(AND(OR(F9="Firm",F9="Estimate"),G9<>11,NOT(ISNUMBER(H9))),"rate",IF(AND(O9=0,G9=9,OR(F9="Firm",F9="Estimate"),ISNUMBER(H9)),"base",IF(OR(C9="",C9="Unclassified"),"unclass",IF(U9=1,"dup",IF(AND(Audit!$C$19="Yes",O9=1,NOT(ISNUMBER(Audit!$M$61))),"noagree",""))))))))) | Y9: =IF(ISNUMBER(Audit!$K$61),Audit!$K$61,0) -> 0 | Z9: =IF(AND(F9="Firm",O9=1,ISNUMBER(J9)),L9*J9,0) -> 0 | AE9: FX missing | AF9: =COUNTIFS($Q$2:$Q$51,"Exchange rate missing") -> 0 | AH9: 8 | AI9: =IFERROR(SMALL($J$70:$J$470,AH9),"") | AJ9: =IF(AI9="","",MATCH(AI9,$J$70:$J$470,0)) | AL9: 8 | AM9: =IFERROR(SMALL($K$70:$K$470,AL9),"") | AN9: =IF(AM9="","",MATCH(AM9,$K$70:$K$470,0))
A10: 9 | B10: =TRIM(Audit!$B$62) | C10: =Audit!$C$62&"" | D10: =IF(B10="","",IF(C10="","Other",IFERROR(INDEX(Lists!$C$4:$C$16,MATCH(C10,Lists!$A$4:$A$16,0)),"Other"))) | E10: =IF(B10="","",IF(C10="","Other",IFERROR(INDEX(Lists!$B$4:$B$16,MATCH(C10,Lists!$A$4:$A$16,0)),"Other"))) | F10: =Audit!$G$62&"" | G10: =IFERROR(MATCH(Audit!$D$62,Lists!$E$4:$E$14,0),0) -> 0 | H10: =IF(ISNUMBER(Audit!$E$62),Audit!$E$62,"") | I10: =IF(TRIM(Audit!$F$62)="",Audit!$C$25,TRIM(Audit!$F$62)) -> 0 | J10: =IF(OR(I10=Audit!$C$25,I10=""),1,IF(AND(I10=Audit!$C$31,ISNUMBER(Audit!$J$31)),Audit!$J$31,IF(AND(I10=Audit!$C$32,ISNUMBER(Audit!$J$32)),Audit!$J$32,""))) -> 1 | K10: =IF(B10="","",IF(ISNUMBER(Audit!$I$62),Audit!$I$62,IF(G10=0,"",CHOOSE(G10,IF(ISNUMBER(Audit!$C$26),Audit!$C$26,1),1,1,1,$AF$33,$AF$30,$AF$31,1,"",1,0)))) | L10: =IF(O10=1,ROUND(MAX(H10*K10,IF(ISNUMBER(Audit!$J$62),Audit!$J$62,0)),2),"") | M10: =IF(O10=1,ROUND(L10*(1+Y10),2),"") | N10: =IF(O10=1,IF(ISNUMBER(J10),ROUND(M10*J10,2),""),"") | O10: =IF(AND(B10<>"",OR(F10="Firm",F10="Estimate",F10="If required"),ISNUMBER(H10),G10>0,G10<>11,ISNUMBER(K10)),1,0) -> 0 | P10: =IF(ISNUMBER(Audit!$L$62),Audit!$L$62,"") | Q10: =IF(B10="","",IF(OR(F10="At cost",F10="TBC"),"Not priced ("&F10&")",IF(OR(F10="Included",F10="Excluded",F10="Not applicable"),F10,IF(F10="","Status missing",IF(AND(F10="If required",NOT(ISNUMBER(H10))),"Not priced (if required)",IF(G10=0,"Basis missing",IF(G10=11,"Not priced (at cost)",IF(NOT(ISNUMBER(H10)),"Rate missing",IF(AND(G10=9,NOT(ISNUMBER(Audit!$I$62))),"Base amount missing",IF(NOT(ISNUMBER(J10)),"Exchange rate missing",IF(NOT(ISNUMBER(P10)),"Calculated — Not Independently Verified",IF(ABS(R10)<=Lists!$B$44,"Verified","Error - differs by "&TEXT(R10,"#,##0.00")&" "&I10)))))))))))) | R10: =IF(AND(O10=1,ISNUMBER(P10)),IF(ABS(P10-L10)<=ABS(P10-M10),P10-L10,P10-M10),"") | S10: =IF(AND(O10=1,ISNUMBER(Audit!$M$62),ISNUMBER(J10)),IF(H10-Audit!$M$62>0.005,ROUND((H10-Audit!$M$62)*K10*(1+Y10)*J10,2),0),0) -> 0 | T10: =Audit!$N$62&"" | U10: =IF(B10="",0,IF(COUNTIFS($B$2:$B$51,B10,$D$2:$D$51,D10)>1,1,0)) -> 0 | V10: =IF(D10="","",IFERROR(INDEX(Audit!$C$43:$C$49,MATCH(D10,Lists!$A$30:$A$36,0)),"")) | W10: =IF(AND(B10<>"",OR(F10="At cost",F10="TBC",AND(F10<>"If required",G10=11))),1,0) -> 0 | X10: =IF(B10="","",IF(T10<>"","flag",IF(F10="","status",IF(AND(G10=0,OR(F10="Firm",F10="Estimate",AND(F10="If required",ISNUMBER(H10)))),"basis",IF(AND(OR(F10="Firm",F10="Estimate"),G10<>11,NOT(ISNUMBER(H10))),"rate",IF(AND(O10=0,G10=9,OR(F10="Firm",F10="Estimate"),ISNUMBER(H10)),"base",IF(OR(C10="",C10="Unclassified"),"unclass",IF(U10=1,"dup",IF(AND(Audit!$C$19="Yes",O10=1,NOT(ISNUMBER(Audit!$M$62))),"noagree",""))))))))) | Y10: =IF(ISNUMBER(Audit!$K$62),Audit!$K$62,0) -> 0 | Z10: =IF(AND(F10="Firm",O10=1,ISNUMBER(J10)),L10*J10,0) -> 0 | AE10: Known firm (quote cur) | AF10: =SUMIFS($N$2:$N$51,$F$2:$F$51,"Firm") -> 0 | AH10: 9 | AI10: =IFERROR(SMALL($J$70:$J$470,AH10),"") | AJ10: =IF(AI10="","",MATCH(AI10,$J$70:$J$470,0)) | AL10: 9 | AM10: =IFERROR(SMALL($K$70:$K$470,AL10),"") | AN10: =IF(AM10="","",MATCH(AM10,$K$70:$K$470,0))
A11: 10 | B11: =TRIM(Audit!$B$63) | C11: =Audit!$C$63&"" | D11: =IF(B11="","",IF(C11="","Other",IFERROR(INDEX(Lists!$C$4:$C$16,MATCH(C11,Lists!$A$4:$A$16,0)),"Other"))) | E11: =IF(B11="","",IF(C11="","Other",IFERROR(INDEX(Lists!$B$4:$B$16,MATCH(C11,Lists!$A$4:$A$16,0)),"Other"))) | F11: =Audit!$G$63&"" | G11: =IFERROR(MATCH(Audit!$D$63,Lists!$E$4:$E$14,0),0) -> 0 | H11: =IF(ISNUMBER(Audit!$E$63),Audit!$E$63,"") | I11: =IF(TRIM(Audit!$F$63)="",Audit!$C$25,TRIM(Audit!$F$63)) -> 0 | J11: =IF(OR(I11=Audit!$C$25,I11=""),1,IF(AND(I11=Audit!$C$31,ISNUMBER(Audit!$J$31)),Audit!$J$31,IF(AND(I11=Audit!$C$32,ISNUMBER(Audit!$J$32)),Audit!$J$32,""))) -> 1 | K11: =IF(B11="","",IF(ISNUMBER(Audit!$I$63),Audit!$I$63,IF(G11=0,"",CHOOSE(G11,IF(ISNUMBER(Audit!$C$26),Audit!$C$26,1),1,1,1,$AF$33,$AF$30,$AF$31,1,"",1,0)))) | L11: =IF(O11=1,ROUND(MAX(H11*K11,IF(ISNUMBER(Audit!$J$63),Audit!$J$63,0)),2),"") | M11: =IF(O11=1,ROUND(L11*(1+Y11),2),"") | N11: =IF(O11=1,IF(ISNUMBER(J11),ROUND(M11*J11,2),""),"") | O11: =IF(AND(B11<>"",OR(F11="Firm",F11="Estimate",F11="If required"),ISNUMBER(H11),G11>0,G11<>11,ISNUMBER(K11)),1,0) -> 0 | P11: =IF(ISNUMBER(Audit!$L$63),Audit!$L$63,"") | Q11: =IF(B11="","",IF(OR(F11="At cost",F11="TBC"),"Not priced ("&F11&")",IF(OR(F11="Included",F11="Excluded",F11="Not applicable"),F11,IF(F11="","Status missing",IF(AND(F11="If required",NOT(ISNUMBER(H11))),"Not priced (if required)",IF(G11=0,"Basis missing",IF(G11=11,"Not priced (at cost)",IF(NOT(ISNUMBER(H11)),"Rate missing",IF(AND(G11=9,NOT(ISNUMBER(Audit!$I$63))),"Base amount missing",IF(NOT(ISNUMBER(J11)),"Exchange rate missing",IF(NOT(ISNUMBER(P11)),"Calculated — Not Independently Verified",IF(ABS(R11)<=Lists!$B$44,"Verified","Error - differs by "&TEXT(R11,"#,##0.00")&" "&I11)))))))))))) | R11: =IF(AND(O11=1,ISNUMBER(P11)),IF(ABS(P11-L11)<=ABS(P11-M11),P11-L11,P11-M11),"") | S11: =IF(AND(O11=1,ISNUMBER(Audit!$M$63),ISNUMBER(J11)),IF(H11-Audit!$M$63>0.005,ROUND((H11-Audit!$M$63)*K11*(1+Y11)*J11,2),0),0) -> 0 | T11: =Audit!$N$63&"" | U11: =IF(B11="",0,IF(COUNTIFS($B$2:$B$51,B11,$D$2:$D$51,D11)>1,1,0)) -> 0 | V11: =IF(D11="","",IFERROR(INDEX(Audit!$C$43:$C$49,MATCH(D11,Lists!$A$30:$A$36,0)),"")) | W11: =IF(AND(B11<>"",OR(F11="At cost",F11="TBC",AND(F11<>"If required",G11=11))),1,0) -> 0 | X11: =IF(B11="","",IF(T11<>"","flag",IF(F11="","status",IF(AND(G11=0,OR(F11="Firm",F11="Estimate",AND(F11="If required",ISNUMBER(H11)))),"basis",IF(AND(OR(F11="Firm",F11="Estimate"),G11<>11,NOT(ISNUMBER(H11))),"rate",IF(AND(O11=0,G11=9,OR(F11="Firm",F11="Estimate"),ISNUMBER(H11)),"base",IF(OR(C11="",C11="Unclassified"),"unclass",IF(U11=1,"dup",IF(AND(Audit!$C$19="Yes",O11=1,NOT(ISNUMBER(Audit!$M$63))),"noagree",""))))))))) | Y11: =IF(ISNUMBER(Audit!$K$63),Audit!$K$63,0) -> 0 | Z11: =IF(AND(F11="Firm",O11=1,ISNUMBER(J11)),L11*J11,0) -> 0 | AE11: Estimates | AF11: =SUMIFS($N$2:$N$51,$F$2:$F$51,"Estimate") -> 0 | AH11: 10 | AI11: =IFERROR(SMALL($J$70:$J$470,AH11),"") | AJ11: =IF(AI11="","",MATCH(AI11,$J$70:$J$470,0)) | AL11: 10 | AM11: =IFERROR(SMALL($K$70:$K$470,AL11),"") | AN11: =IF(AM11="","",MATCH(AM11,$K$70:$K$470,0))
A12: 11 | B12: =TRIM(Audit!$B$64) | C12: =Audit!$C$64&"" | D12: =IF(B12="","",IF(C12="","Other",IFERROR(INDEX(Lists!$C$4:$C$16,MATCH(C12,Lists!$A$4:$A$16,0)),"Other"))) | E12: =IF(B12="","",IF(C12="","Other",IFERROR(INDEX(Lists!$B$4:$B$16,MATCH(C12,Lists!$A$4:$A$16,0)),"Other"))) | F12: =Audit!$G$64&"" | G12: =IFERROR(MATCH(Audit!$D$64,Lists!$E$4:$E$14,0),0) -> 0 | H12: =IF(ISNUMBER(Audit!$E$64),Audit!$E$64,"") | I12: =IF(TRIM(Audit!$F$64)="",Audit!$C$25,TRIM(Audit!$F$64)) -> 0 | J12: =IF(OR(I12=Audit!$C$25,I12=""),1,IF(AND(I12=Audit!$C$31,ISNUMBER(Audit!$J$31)),Audit!$J$31,IF(AND(I12=Audit!$C$32,ISNUMBER(Audit!$J$32)),Audit!$J$32,""))) -> 1 | K12: =IF(B12="","",IF(ISNUMBER(Audit!$I$64),Audit!$I$64,IF(G12=0,"",CHOOSE(G12,IF(ISNUMBER(Audit!$C$26),Audit!$C$26,1),1,1,1,$AF$33,$AF$30,$AF$31,1,"",1,0)))) | L12: =IF(O12=1,ROUND(MAX(H12*K12,IF(ISNUMBER(Audit!$J$64),Audit!$J$64,0)),2),"") | M12: =IF(O12=1,ROUND(L12*(1+Y12),2),"") | N12: =IF(O12=1,IF(ISNUMBER(J12),ROUND(M12*J12,2),""),"") | O12: =IF(AND(B12<>"",OR(F12="Firm",F12="Estimate",F12="If required"),ISNUMBER(H12),G12>0,G12<>11,ISNUMBER(K12)),1,0) -> 0 | P12: =IF(ISNUMBER(Audit!$L$64),Audit!$L$64,"") | Q12: =IF(B12="","",IF(OR(F12="At cost",F12="TBC"),"Not priced ("&F12&")",IF(OR(F12="Included",F12="Excluded",F12="Not applicable"),F12,IF(F12="","Status missing",IF(AND(F12="If required",NOT(ISNUMBER(H12))),"Not priced (if required)",IF(G12=0,"Basis missing",IF(G12=11,"Not priced (at cost)",IF(NOT(ISNUMBER(H12)),"Rate missing",IF(AND(G12=9,NOT(ISNUMBER(Audit!$I$64))),"Base amount missing",IF(NOT(ISNUMBER(J12)),"Exchange rate missing",IF(NOT(ISNUMBER(P12)),"Calculated — Not Independently Verified",IF(ABS(R12)<=Lists!$B$44,"Verified","Error - differs by "&TEXT(R12,"#,##0.00")&" "&I12)))))))))))) | R12: =IF(AND(O12=1,ISNUMBER(P12)),IF(ABS(P12-L12)<=ABS(P12-M12),P12-L12,P12-M12),"") | S12: =IF(AND(O12=1,ISNUMBER(Audit!$M$64),ISNUMBER(J12)),IF(H12-Audit!$M$64>0.005,ROUND((H12-Audit!$M$64)*K12*(1+Y12)*J12,2),0),0) -> 0 | T12: =Audit!$N$64&"" | U12: =IF(B12="",0,IF(COUNTIFS($B$2:$B$51,B12,$D$2:$D$51,D12)>1,1,0)) -> 0 | V12: =IF(D12="","",IFERROR(INDEX(Audit!$C$43:$C$49,MATCH(D12,Lists!$A$30:$A$36,0)),"")) | W12: =IF(AND(B12<>"",OR(F12="At cost",F12="TBC",AND(F12<>"If required",G12=11))),1,0) -> 0 | X12: =IF(B12="","",IF(T12<>"","flag",IF(F12="","status",IF(AND(G12=0,OR(F12="Firm",F12="Estimate",AND(F12="If required",ISNUMBER(H12)))),"basis",IF(AND(OR(F12="Firm",F12="Estimate"),G12<>11,NOT(ISNUMBER(H12))),"rate",IF(AND(O12=0,G12=9,OR(F12="Firm",F12="Estimate"),ISNUMBER(H12)),"base",IF(OR(C12="",C12="Unclassified"),"unclass",IF(U12=1,"dup",IF(AND(Audit!$C$19="Yes",O12=1,NOT(ISNUMBER(Audit!$M$64))),"noagree",""))))))))) | Y12: =IF(ISNUMBER(Audit!$K$64),Audit!$K$64,0) -> 0 | Z12: =IF(AND(F12="Firm",O12=1,ISNUMBER(J12)),L12*J12,0) -> 0 | AE12: Estimate lines | AF12: =COUNTIFS($F$2:$F$51,"Estimate") -> 0 | AH12: 11 | AI12: =IFERROR(SMALL($J$70:$J$470,AH12),"") | AJ12: =IF(AI12="","",MATCH(AI12,$J$70:$J$470,0)) | AL12: 11 | AM12: =IFERROR(SMALL($K$70:$K$470,AL12),"") | AN12: =IF(AM12="","",MATCH(AM12,$K$70:$K$470,0))
A13: 12 | B13: =TRIM(Audit!$B$65) | C13: =Audit!$C$65&"" | D13: =IF(B13="","",IF(C13="","Other",IFERROR(INDEX(Lists!$C$4:$C$16,MATCH(C13,Lists!$A$4:$A$16,0)),"Other"))) | E13: =IF(B13="","",IF(C13="","Other",IFERROR(INDEX(Lists!$B$4:$B$16,MATCH(C13,Lists!$A$4:$A$16,0)),"Other"))) | F13: =Audit!$G$65&"" | G13: =IFERROR(MATCH(Audit!$D$65,Lists!$E$4:$E$14,0),0) -> 0 | H13: =IF(ISNUMBER(Audit!$E$65),Audit!$E$65,"") | I13: =IF(TRIM(Audit!$F$65)="",Audit!$C$25,TRIM(Audit!$F$65)) -> 0 | J13: =IF(OR(I13=Audit!$C$25,I13=""),1,IF(AND(I13=Audit!$C$31,ISNUMBER(Audit!$J$31)),Audit!$J$31,IF(AND(I13=Audit!$C$32,ISNUMBER(Audit!$J$32)),Audit!$J$32,""))) -> 1 | K13: =IF(B13="","",IF(ISNUMBER(Audit!$I$65),Audit!$I$65,IF(G13=0,"",CHOOSE(G13,IF(ISNUMBER(Audit!$C$26),Audit!$C$26,1),1,1,1,$AF$33,$AF$30,$AF$31,1,"",1,0)))) | L13: =IF(O13=1,ROUND(MAX(H13*K13,IF(ISNUMBER(Audit!$J$65),Audit!$J$65,0)),2),"") | M13: =IF(O13=1,ROUND(L13*(1+Y13),2),"") | N13: =IF(O13=1,IF(ISNUMBER(J13),ROUND(M13*J13,2),""),"") | O13: =IF(AND(B13<>"",OR(F13="Firm",F13="Estimate",F13="If required"),ISNUMBER(H13),G13>0,G13<>11,ISNUMBER(K13)),1,0) -> 0 | P13: =IF(ISNUMBER(Audit!$L$65),Audit!$L$65,"") | Q13: =IF(B13="","",IF(OR(F13="At cost",F13="TBC"),"Not priced ("&F13&")",IF(OR(F13="Included",F13="Excluded",F13="Not applicable"),F13,IF(F13="","Status missing",IF(AND(F13="If required",NOT(ISNUMBER(H13))),"Not priced (if required)",IF(G13=0,"Basis missing",IF(G13=11,"Not priced (at cost)",IF(NOT(ISNUMBER(H13)),"Rate missing",IF(AND(G13=9,NOT(ISNUMBER(Audit!$I$65))),"Base amount missing",IF(NOT(ISNUMBER(J13)),"Exchange rate missing",IF(NOT(ISNUMBER(P13)),"Calculated — Not Independently Verified",IF(ABS(R13)<=Lists!$B$44,"Verified","Error - differs by "&TEXT(R13,"#,##0.00")&" "&I13)))))))))))) | R13: =IF(AND(O13=1,ISNUMBER(P13)),IF(ABS(P13-L13)<=ABS(P13-M13),P13-L13,P13-M13),"") | S13: =IF(AND(O13=1,ISNUMBER(Audit!$M$65),ISNUMBER(J13)),IF(H13-Audit!$M$65>0.005,ROUND((H13-Audit!$M$65)*K13*(1+Y13)*J13,2),0),0) -> 0 | T13: =Audit!$N$65&"" | U13: =IF(B13="",0,IF(COUNTIFS($B$2:$B$51,B13,$D$2:$D$51,D13)>1,1,0)) -> 0 | V13: =IF(D13="","",IFERROR(INDEX(Audit!$C$43:$C$49,MATCH(D13,Lists!$A$30:$A$36,0)),"")) | W13: =IF(AND(B13<>"",OR(F13="At cost",F13="TBC",AND(F13<>"If required",G13=11))),1,0) -> 0 | X13: =IF(B13="","",IF(T13<>"","flag",IF(F13="","status",IF(AND(G13=0,OR(F13="Firm",F13="Estimate",AND(F13="If required",ISNUMBER(H13)))),"basis",IF(AND(OR(F13="Firm",F13="Estimate"),G13<>11,NOT(ISNUMBER(H13))),"rate",IF(AND(O13=0,G13=9,OR(F13="Firm",F13="Estimate"),ISNUMBER(H13)),"base",IF(OR(C13="",C13="Unclassified"),"unclass",IF(U13=1,"dup",IF(AND(Audit!$C$19="Yes",O13=1,NOT(ISNUMBER(Audit!$M$65))),"noagree",""))))))))) | Y13: =IF(ISNUMBER(Audit!$K$65),Audit!$K$65,0) -> 0 | Z13: =IF(AND(F13="Firm",O13=1,ISNUMBER(J13)),L13*J13,0) -> 0 | AE13: Conditional priced | AF13: =SUMIFS($N$2:$N$51,$F$2:$F$51,"If required") -> 0 | AH13: 12 | AI13: =IFERROR(SMALL($J$70:$J$470,AH13),"") | AJ13: =IF(AI13="","",MATCH(AI13,$J$70:$J$470,0)) | AL13: 12 | AM13: =IFERROR(SMALL($K$70:$K$470,AL13),"") | AN13: =IF(AM13="","",MATCH(AM13,$K$70:$K$470,0))
A14: 13 | B14: =TRIM(Audit!$B$66) | C14: =Audit!$C$66&"" | D14: =IF(B14="","",IF(C14="","Other",IFERROR(INDEX(Lists!$C$4:$C$16,MATCH(C14,Lists!$A$4:$A$16,0)),"Other"))) | E14: =IF(B14="","",IF(C14="","Other",IFERROR(INDEX(Lists!$B$4:$B$16,MATCH(C14,Lists!$A$4:$A$16,0)),"Other"))) | F14: =Audit!$G$66&"" | G14: =IFERROR(MATCH(Audit!$D$66,Lists!$E$4:$E$14,0),0) -> 0 | H14: =IF(ISNUMBER(Audit!$E$66),Audit!$E$66,"") | I14: =IF(TRIM(Audit!$F$66)="",Audit!$C$25,TRIM(Audit!$F$66)) -> 0 | J14: =IF(OR(I14=Audit!$C$25,I14=""),1,IF(AND(I14=Audit!$C$31,ISNUMBER(Audit!$J$31)),Audit!$J$31,IF(AND(I14=Audit!$C$32,ISNUMBER(Audit!$J$32)),Audit!$J$32,""))) -> 1 | K14: =IF(B14="","",IF(ISNUMBER(Audit!$I$66),Audit!$I$66,IF(G14=0,"",CHOOSE(G14,IF(ISNUMBER(Audit!$C$26),Audit!$C$26,1),1,1,1,$AF$33,$AF$30,$AF$31,1,"",1,0)))) | L14: =IF(O14=1,ROUND(MAX(H14*K14,IF(ISNUMBER(Audit!$J$66),Audit!$J$66,0)),2),"") | M14: =IF(O14=1,ROUND(L14*(1+Y14),2),"") | N14: =IF(O14=1,IF(ISNUMBER(J14),ROUND(M14*J14,2),""),"") | O14: =IF(AND(B14<>"",OR(F14="Firm",F14="Estimate",F14="If required"),ISNUMBER(H14),G14>0,G14<>11,ISNUMBER(K14)),1,0) -> 0 | P14: =IF(ISNUMBER(Audit!$L$66),Audit!$L$66,"") | Q14: =IF(B14="","",IF(OR(F14="At cost",F14="TBC"),"Not priced ("&F14&")",IF(OR(F14="Included",F14="Excluded",F14="Not applicable"),F14,IF(F14="","Status missing",IF(AND(F14="If required",NOT(ISNUMBER(H14))),"Not priced (if required)",IF(G14=0,"Basis missing",IF(G14=11,"Not priced (at cost)",IF(NOT(ISNUMBER(H14)),"Rate missing",IF(AND(G14=9,NOT(ISNUMBER(Audit!$I$66))),"Base amount missing",IF(NOT(ISNUMBER(J14)),"Exchange rate missing",IF(NOT(ISNUMBER(P14)),"Calculated — Not Independently Verified",IF(ABS(R14)<=Lists!$B$44,"Verified","Error - differs by "&TEXT(R14,"#,##0.00")&" "&I14)))))))))))) | R14: =IF(AND(O14=1,ISNUMBER(P14)),IF(ABS(P14-L14)<=ABS(P14-M14),P14-L14,P14-M14),"") | S14: =IF(AND(O14=1,ISNUMBER(Audit!$M$66),ISNUMBER(J14)),IF(H14-Audit!$M$66>0.005,ROUND((H14-Audit!$M$66)*K14*(1+Y14)*J14,2),0),0) -> 0 | T14: =Audit!$N$66&"" | U14: =IF(B14="",0,IF(COUNTIFS($B$2:$B$51,B14,$D$2:$D$51,D14)>1,1,0)) -> 0 | V14: =IF(D14="","",IFERROR(INDEX(Audit!$C$43:$C$49,MATCH(D14,Lists!$A$30:$A$36,0)),"")) | W14: =IF(AND(B14<>"",OR(F14="At cost",F14="TBC",AND(F14<>"If required",G14=11))),1,0) -> 0 | X14: =IF(B14="","",IF(T14<>"","flag",IF(F14="","status",IF(AND(G14=0,OR(F14="Firm",F14="Estimate",AND(F14="If required",ISNUMBER(H14)))),"basis",IF(AND(OR(F14="Firm",F14="Estimate"),G14<>11,NOT(ISNUMBER(H14))),"rate",IF(AND(O14=0,G14=9,OR(F14="Firm",F14="Estimate"),ISNUMBER(H14)),"base",IF(OR(C14="",C14="Unclassified"),"unclass",IF(U14=1,"dup",IF(AND(Audit!$C$19="Yes",O14=1,NOT(ISNUMBER(Audit!$M$66))),"noagree",""))))))))) | Y14: =IF(ISNUMBER(Audit!$K$66),Audit!$K$66,0) -> 0 | Z14: =IF(AND(F14="Firm",O14=1,ISNUMBER(J14)),L14*J14,0) -> 0 | AE14: Conditional unpriced count | AF14: =COUNTIFS($F$2:$F$51,"If required",$O$2:$O$51,0) -> 0 | AH14: 13 | AI14: =IFERROR(SMALL($J$70:$J$470,AH14),"") | AJ14: =IF(AI14="","",MATCH(AI14,$J$70:$J$470,0)) | AL14: 13 | AM14: =IFERROR(SMALL($K$70:$K$470,AL14),"") | AN14: =IF(AM14="","",MATCH(AM14,$K$70:$K$470,0))
A15: 14 | B15: =TRIM(Audit!$B$67) | C15: =Audit!$C$67&"" | D15: =IF(B15="","",IF(C15="","Other",IFERROR(INDEX(Lists!$C$4:$C$16,MATCH(C15,Lists!$A$4:$A$16,0)),"Other"))) | E15: =IF(B15="","",IF(C15="","Other",IFERROR(INDEX(Lists!$B$4:$B$16,MATCH(C15,Lists!$A$4:$A$16,0)),"Other"))) | F15: =Audit!$G$67&"" | G15: =IFERROR(MATCH(Audit!$D$67,Lists!$E$4:$E$14,0),0) -> 0 | H15: =IF(ISNUMBER(Audit!$E$67),Audit!$E$67,"") | I15: =IF(TRIM(Audit!$F$67)="",Audit!$C$25,TRIM(Audit!$F$67)) -> 0 | J15: =IF(OR(I15=Audit!$C$25,I15=""),1,IF(AND(I15=Audit!$C$31,ISNUMBER(Audit!$J$31)),Audit!$J$31,IF(AND(I15=Audit!$C$32,ISNUMBER(Audit!$J$32)),Audit!$J$32,""))) -> 1 | K15: =IF(B15="","",IF(ISNUMBER(Audit!$I$67),Audit!$I$67,IF(G15=0,"",CHOOSE(G15,IF(ISNUMBER(Audit!$C$26),Audit!$C$26,1),1,1,1,$AF$33,$AF$30,$AF$31,1,"",1,0)))) | L15: =IF(O15=1,ROUND(MAX(H15*K15,IF(ISNUMBER(Audit!$J$67),Audit!$J$67,0)),2),"") | M15: =IF(O15=1,ROUND(L15*(1+Y15),2),"") | N15: =IF(O15=1,IF(ISNUMBER(J15),ROUND(M15*J15,2),""),"") | O15: =IF(AND(B15<>"",OR(F15="Firm",F15="Estimate",F15="If required"),ISNUMBER(H15),G15>0,G15<>11,ISNUMBER(K15)),1,0) -> 0 | P15: =IF(ISNUMBER(Audit!$L$67),Audit!$L$67,"") | Q15: =IF(B15="","",IF(OR(F15="At cost",F15="TBC"),"Not priced ("&F15&")",IF(OR(F15="Included",F15="Excluded",F15="Not applicable"),F15,IF(F15="","Status missing",IF(AND(F15="If required",NOT(ISNUMBER(H15))),"Not priced (if required)",IF(G15=0,"Basis missing",IF(G15=11,"Not priced (at cost)",IF(NOT(ISNUMBER(H15)),"Rate missing",IF(AND(G15=9,NOT(ISNUMBER(Audit!$I$67))),"Base amount missing",IF(NOT(ISNUMBER(J15)),"Exchange rate missing",IF(NOT(ISNUMBER(P15)),"Calculated — Not Independently Verified",IF(ABS(R15)<=Lists!$B$44,"Verified","Error - differs by "&TEXT(R15,"#,##0.00")&" "&I15)))))))))))) | R15: =IF(AND(O15=1,ISNUMBER(P15)),IF(ABS(P15-L15)<=ABS(P15-M15),P15-L15,P15-M15),"") | S15: =IF(AND(O15=1,ISNUMBER(Audit!$M$67),ISNUMBER(J15)),IF(H15-Audit!$M$67>0.005,ROUND((H15-Audit!$M$67)*K15*(1+Y15)*J15,2),0),0) -> 0 | T15: =Audit!$N$67&"" | U15: =IF(B15="",0,IF(COUNTIFS($B$2:$B$51,B15,$D$2:$D$51,D15)>1,1,0)) -> 0 | V15: =IF(D15="","",IFERROR(INDEX(Audit!$C$43:$C$49,MATCH(D15,Lists!$A$30:$A$36,0)),"")) | W15: =IF(AND(B15<>"",OR(F15="At cost",F15="TBC",AND(F15<>"If required",G15=11))),1,0) -> 0 | X15: =IF(B15="","",IF(T15<>"","flag",IF(F15="","status",IF(AND(G15=0,OR(F15="Firm",F15="Estimate",AND(F15="If required",ISNUMBER(H15)))),"basis",IF(AND(OR(F15="Firm",F15="Estimate"),G15<>11,NOT(ISNUMBER(H15))),"rate",IF(AND(O15=0,G15=9,OR(F15="Firm",F15="Estimate"),ISNUMBER(H15)),"base",IF(OR(C15="",C15="Unclassified"),"unclass",IF(U15=1,"dup",IF(AND(Audit!$C$19="Yes",O15=1,NOT(ISNUMBER(Audit!$M$67))),"noagree",""))))))))) | Y15: =IF(ISNUMBER(Audit!$K$67),Audit!$K$67,0) -> 0 | Z15: =IF(AND(F15="Firm",O15=1,ISNUMBER(J15)),L15*J15,0) -> 0 | AE15: Unpriced count | AF15: =SUM($W$2:$W$51) -> 0 | AH15: 14 | AI15: =IFERROR(SMALL($J$70:$J$470,AH15),"") | AJ15: =IF(AI15="","",MATCH(AI15,$J$70:$J$470,0)) | AL15: 14 | AM15: =IFERROR(SMALL($K$70:$K$470,AL15),"") | AN15: =IF(AM15="","",MATCH(AM15,$K$70:$K$470,0))
A16: 15 | B16: =TRIM(Audit!$B$68) | C16: =Audit!$C$68&"" | D16: =IF(B16="","",IF(C16="","Other",IFERROR(INDEX(Lists!$C$4:$C$16,MATCH(C16,Lists!$A$4:$A$16,0)),"Other"))) | E16: =IF(B16="","",IF(C16="","Other",IFERROR(INDEX(Lists!$B$4:$B$16,MATCH(C16,Lists!$A$4:$A$16,0)),"Other"))) | F16: =Audit!$G$68&"" | G16: =IFERROR(MATCH(Audit!$D$68,Lists!$E$4:$E$14,0),0) -> 0 | H16: =IF(ISNUMBER(Audit!$E$68),Audit!$E$68,"") | I16: =IF(TRIM(Audit!$F$68)="",Audit!$C$25,TRIM(Audit!$F$68)) -> 0 | J16: =IF(OR(I16=Audit!$C$25,I16=""),1,IF(AND(I16=Audit!$C$31,ISNUMBER(Audit!$J$31)),Audit!$J$31,IF(AND(I16=Audit!$C$32,ISNUMBER(Audit!$J$32)),Audit!$J$32,""))) -> 1 | K16: =IF(B16="","",IF(ISNUMBER(Audit!$I$68),Audit!$I$68,IF(G16=0,"",CHOOSE(G16,IF(ISNUMBER(Audit!$C$26),Audit!$C$26,1),1,1,1,$AF$33,$AF$30,$AF$31,1,"",1,0)))) | L16: =IF(O16=1,ROUND(MAX(H16*K16,IF(ISNUMBER(Audit!$J$68),Audit!$J$68,0)),2),"") | M16: =IF(O16=1,ROUND(L16*(1+Y16),2),"") | N16: =IF(O16=1,IF(ISNUMBER(J16),ROUND(M16*J16,2),""),"") | O16: =IF(AND(B16<>"",OR(F16="Firm",F16="Estimate",F16="If required"),ISNUMBER(H16),G16>0,G16<>11,ISNUMBER(K16)),1,0) -> 0 | P16: =IF(ISNUMBER(Audit!$L$68),Audit!$L$68,"") | Q16: =IF(B16="","",IF(OR(F16="At cost",F16="TBC"),"Not priced ("&F16&")",IF(OR(F16="Included",F16="Excluded",F16="Not applicable"),F16,IF(F16="","Status missing",IF(AND(F16="If required",NOT(ISNUMBER(H16))),"Not priced (if required)",IF(G16=0,"Basis missing",IF(G16=11,"Not priced (at cost)",IF(NOT(ISNUMBER(H16)),"Rate missing",IF(AND(G16=9,NOT(ISNUMBER(Audit!$I$68))),"Base amount missing",IF(NOT(ISNUMBER(J16)),"Exchange rate missing",IF(NOT(ISNUMBER(P16)),"Calculated — Not Independently Verified",IF(ABS(R16)<=Lists!$B$44,"Verified","Error - differs by "&TEXT(R16,"#,##0.00")&" "&I16)))))))))))) | R16: =IF(AND(O16=1,ISNUMBER(P16)),IF(ABS(P16-L16)<=ABS(P16-M16),P16-L16,P16-M16),"") | S16: =IF(AND(O16=1,ISNUMBER(Audit!$M$68),ISNUMBER(J16)),IF(H16-Audit!$M$68>0.005,ROUND((H16-Audit!$M$68)*K16*(1+Y16)*J16,2),0),0) -> 0 | T16: =Audit!$N$68&"" | U16: =IF(B16="",0,IF(COUNTIFS($B$2:$B$51,B16,$D$2:$D$51,D16)>1,1,0)) -> 0 | V16: =IF(D16="","",IFERROR(INDEX(Audit!$C$43:$C$49,MATCH(D16,Lists!$A$30:$A$36,0)),"")) | W16: =IF(AND(B16<>"",OR(F16="At cost",F16="TBC",AND(F16<>"If required",G16=11))),1,0) -> 0 | X16: =IF(B16="","",IF(T16<>"","flag",IF(F16="","status",IF(AND(G16=0,OR(F16="Firm",F16="Estimate",AND(F16="If required",ISNUMBER(H16)))),"basis",IF(AND(OR(F16="Firm",F16="Estimate"),G16<>11,NOT(ISNUMBER(H16))),"rate",IF(AND(O16=0,G16=9,OR(F16="Firm",F16="Estimate"),ISNUMBER(H16)),"base",IF(OR(C16="",C16="Unclassified"),"unclass",IF(U16=1,"dup",IF(AND(Audit!$C$19="Yes",O16=1,NOT(ISNUMBER(Audit!$M$68))),"noagree",""))))))))) | Y16: =IF(ISNUMBER(Audit!$K$68),Audit!$K$68,0) -> 0 | Z16: =IF(AND(F16="Firm",O16=1,ISNUMBER(J16)),L16*J16,0) -> 0 | AE16: Confirmed discrepancies | AF16: =SUMIFS($I$70:$I$470,$B$70:$B$470,1,$C$70:$C$470,"Error") -> 0 | AH16: 15 | AI16: =IFERROR(SMALL($J$70:$J$470,AH16),"") | AJ16: =IF(AI16="","",MATCH(AI16,$J$70:$J$470,0)) | AL16: 15 | AM16: =IFERROR(SMALL($K$70:$K$470,AL16),"") | AN16: =IF(AM16="","",MATCH(AM16,$K$70:$K$470,0))
A17: 16 | B17: =TRIM(Audit!$B$69) | C17: =Audit!$C$69&"" | D17: =IF(B17="","",IF(C17="","Other",IFERROR(INDEX(Lists!$C$4:$C$16,MATCH(C17,Lists!$A$4:$A$16,0)),"Other"))) | E17: =IF(B17="","",IF(C17="","Other",IFERROR(INDEX(Lists!$B$4:$B$16,MATCH(C17,Lists!$A$4:$A$16,0)),"Other"))) | F17: =Audit!$G$69&"" | G17: =IFERROR(MATCH(Audit!$D$69,Lists!$E$4:$E$14,0),0) -> 0 | H17: =IF(ISNUMBER(Audit!$E$69),Audit!$E$69,"") | I17: =IF(TRIM(Audit!$F$69)="",Audit!$C$25,TRIM(Audit!$F$69)) -> 0 | J17: =IF(OR(I17=Audit!$C$25,I17=""),1,IF(AND(I17=Audit!$C$31,ISNUMBER(Audit!$J$31)),Audit!$J$31,IF(AND(I17=Audit!$C$32,ISNUMBER(Audit!$J$32)),Audit!$J$32,""))) -> 1 | K17: =IF(B17="","",IF(ISNUMBER(Audit!$I$69),Audit!$I$69,IF(G17=0,"",CHOOSE(G17,IF(ISNUMBER(Audit!$C$26),Audit!$C$26,1),1,1,1,$AF$33,$AF$30,$AF$31,1,"",1,0)))) | L17: =IF(O17=1,ROUND(MAX(H17*K17,IF(ISNUMBER(Audit!$J$69),Audit!$J$69,0)),2),"") | M17: =IF(O17=1,ROUND(L17*(1+Y17),2),"") | N17: =IF(O17=1,IF(ISNUMBER(J17),ROUND(M17*J17,2),""),"") | O17: =IF(AND(B17<>"",OR(F17="Firm",F17="Estimate",F17="If required"),ISNUMBER(H17),G17>0,G17<>11,ISNUMBER(K17)),1,0) -> 0 | P17: =IF(ISNUMBER(Audit!$L$69),Audit!$L$69,"") | Q17: =IF(B17="","",IF(OR(F17="At cost",F17="TBC"),"Not priced ("&F17&")",IF(OR(F17="Included",F17="Excluded",F17="Not applicable"),F17,IF(F17="","Status missing",IF(AND(F17="If required",NOT(ISNUMBER(H17))),"Not priced (if required)",IF(G17=0,"Basis missing",IF(G17=11,"Not priced (at cost)",IF(NOT(ISNUMBER(H17)),"Rate missing",IF(AND(G17=9,NOT(ISNUMBER(Audit!$I$69))),"Base amount missing",IF(NOT(ISNUMBER(J17)),"Exchange rate missing",IF(NOT(ISNUMBER(P17)),"Calculated — Not Independently Verified",IF(ABS(R17)<=Lists!$B$44,"Verified","Error - differs by "&TEXT(R17,"#,##0.00")&" "&I17)))))))))))) | R17: =IF(AND(O17=1,ISNUMBER(P17)),IF(ABS(P17-L17)<=ABS(P17-M17),P17-L17,P17-M17),"") | S17: =IF(AND(O17=1,ISNUMBER(Audit!$M$69),ISNUMBER(J17)),IF(H17-Audit!$M$69>0.005,ROUND((H17-Audit!$M$69)*K17*(1+Y17)*J17,2),0),0) -> 0 | T17: =Audit!$N$69&"" | U17: =IF(B17="",0,IF(COUNTIFS($B$2:$B$51,B17,$D$2:$D$51,D17)>1,1,0)) -> 0 | V17: =IF(D17="","",IFERROR(INDEX(Audit!$C$43:$C$49,MATCH(D17,Lists!$A$30:$A$36,0)),"")) | W17: =IF(AND(B17<>"",OR(F17="At cost",F17="TBC",AND(F17<>"If required",G17=11))),1,0) -> 0 | X17: =IF(B17="","",IF(T17<>"","flag",IF(F17="","status",IF(AND(G17=0,OR(F17="Firm",F17="Estimate",AND(F17="If required",ISNUMBER(H17)))),"basis",IF(AND(OR(F17="Firm",F17="Estimate"),G17<>11,NOT(ISNUMBER(H17))),"rate",IF(AND(O17=0,G17=9,OR(F17="Firm",F17="Estimate"),ISNUMBER(H17)),"base",IF(OR(C17="",C17="Unclassified"),"unclass",IF(U17=1,"dup",IF(AND(Audit!$C$19="Yes",O17=1,NOT(ISNUMBER(Audit!$M$69))),"noagree",""))))))))) | Y17: =IF(ISNUMBER(Audit!$K$69),Audit!$K$69,0) -> 0 | Z17: =IF(AND(F17="Firm",O17=1,ISNUMBER(J17)),L17*J17,0) -> 0 | AE17: Under question | AF17: =SUMIFS($I$70:$I$470,$B$70:$B$470,1,$C$70:$C$470,"Question") -> 0 | AH17: 16 | AI17: =IFERROR(SMALL($J$70:$J$470,AH17),"") | AJ17: =IF(AI17="","",MATCH(AI17,$J$70:$J$470,0))
A18: 17 | B18: =TRIM(Audit!$B$70) | C18: =Audit!$C$70&"" | D18: =IF(B18="","",IF(C18="","Other",IFERROR(INDEX(Lists!$C$4:$C$16,MATCH(C18,Lists!$A$4:$A$16,0)),"Other"))) | E18: =IF(B18="","",IF(C18="","Other",IFERROR(INDEX(Lists!$B$4:$B$16,MATCH(C18,Lists!$A$4:$A$16,0)),"Other"))) | F18: =Audit!$G$70&"" | G18: =IFERROR(MATCH(Audit!$D$70,Lists!$E$4:$E$14,0),0) -> 0 | H18: =IF(ISNUMBER(Audit!$E$70),Audit!$E$70,"") | I18: =IF(TRIM(Audit!$F$70)="",Audit!$C$25,TRIM(Audit!$F$70)) -> 0 | J18: =IF(OR(I18=Audit!$C$25,I18=""),1,IF(AND(I18=Audit!$C$31,ISNUMBER(Audit!$J$31)),Audit!$J$31,IF(AND(I18=Audit!$C$32,ISNUMBER(Audit!$J$32)),Audit!$J$32,""))) -> 1 | K18: =IF(B18="","",IF(ISNUMBER(Audit!$I$70),Audit!$I$70,IF(G18=0,"",CHOOSE(G18,IF(ISNUMBER(Audit!$C$26),Audit!$C$26,1),1,1,1,$AF$33,$AF$30,$AF$31,1,"",1,0)))) | L18: =IF(O18=1,ROUND(MAX(H18*K18,IF(ISNUMBER(Audit!$J$70),Audit!$J$70,0)),2),"") | M18: =IF(O18=1,ROUND(L18*(1+Y18),2),"") | N18: =IF(O18=1,IF(ISNUMBER(J18),ROUND(M18*J18,2),""),"") | O18: =IF(AND(B18<>"",OR(F18="Firm",F18="Estimate",F18="If required"),ISNUMBER(H18),G18>0,G18<>11,ISNUMBER(K18)),1,0) -> 0 | P18: =IF(ISNUMBER(Audit!$L$70),Audit!$L$70,"") | Q18: =IF(B18="","",IF(OR(F18="At cost",F18="TBC"),"Not priced ("&F18&")",IF(OR(F18="Included",F18="Excluded",F18="Not applicable"),F18,IF(F18="","Status missing",IF(AND(F18="If required",NOT(ISNUMBER(H18))),"Not priced (if required)",IF(G18=0,"Basis missing",IF(G18=11,"Not priced (at cost)",IF(NOT(ISNUMBER(H18)),"Rate missing",IF(AND(G18=9,NOT(ISNUMBER(Audit!$I$70))),"Base amount missing",IF(NOT(ISNUMBER(J18)),"Exchange rate missing",IF(NOT(ISNUMBER(P18)),"Calculated — Not Independently Verified",IF(ABS(R18)<=Lists!$B$44,"Verified","Error - differs by "&TEXT(R18,"#,##0.00")&" "&I18)))))))))))) | R18: =IF(AND(O18=1,ISNUMBER(P18)),IF(ABS(P18-L18)<=ABS(P18-M18),P18-L18,P18-M18),"") | S18: =IF(AND(O18=1,ISNUMBER(Audit!$M$70),ISNUMBER(J18)),IF(H18-Audit!$M$70>0.005,ROUND((H18-Audit!$M$70)*K18*(1+Y18)*J18,2),0),0) -> 0 | T18: =Audit!$N$70&"" | U18: =IF(B18="",0,IF(COUNTIFS($B$2:$B$51,B18,$D$2:$D$51,D18)>1,1,0)) -> 0 | V18: =IF(D18="","",IFERROR(INDEX(Audit!$C$43:$C$49,MATCH(D18,Lists!$A$30:$A$36,0)),"")) | W18: =IF(AND(B18<>"",OR(F18="At cost",F18="TBC",AND(F18<>"If required",G18=11))),1,0) -> 0 | X18: =IF(B18="","",IF(T18<>"","flag",IF(F18="","status",IF(AND(G18=0,OR(F18="Firm",F18="Estimate",AND(F18="If required",ISNUMBER(H18)))),"basis",IF(AND(OR(F18="Firm",F18="Estimate"),G18<>11,NOT(ISNUMBER(H18))),"rate",IF(AND(O18=0,G18=9,OR(F18="Firm",F18="Estimate"),ISNUMBER(H18)),"base",IF(OR(C18="",C18="Unclassified"),"unclass",IF(U18=1,"dup",IF(AND(Audit!$C$19="Yes",O18=1,NOT(ISNUMBER(Audit!$M$70))),"noagree",""))))))))) | Y18: =IF(ISNUMBER(Audit!$K$70),Audit!$K$70,0) -> 0 | Z18: =IF(AND(F18="Firm",O18=1,ISNUMBER(J18)),L18*J18,0) -> 0 | AE18: Services not all-in | AF18: =COUNTIFS($B$55:$B$61,"Yes",$J$55:$J$61,"Not addressed")+COUNTIFS($B$55:$B$61,"Yes",$J$55:$J$61,"Excluded")+COUNTIFS($B$55:$B$61,"Yes",$J$55:$J$61,"Unpriced") -> 0 | AH18: 17 | AI18: =IFERROR(SMALL($J$70:$J$470,AH18),"") | AJ18: =IF(AI18="","",MATCH(AI18,$J$70:$J$470,0))
A19: 18 | B19: =TRIM(Audit!$B$71) | C19: =Audit!$C$71&"" | D19: =IF(B19="","",IF(C19="","Other",IFERROR(INDEX(Lists!$C$4:$C$16,MATCH(C19,Lists!$A$4:$A$16,0)),"Other"))) | E19: =IF(B19="","",IF(C19="","Other",IFERROR(INDEX(Lists!$B$4:$B$16,MATCH(C19,Lists!$A$4:$A$16,0)),"Other"))) | F19: =Audit!$G$71&"" | G19: =IFERROR(MATCH(Audit!$D$71,Lists!$E$4:$E$14,0),0) -> 0 | H19: =IF(ISNUMBER(Audit!$E$71),Audit!$E$71,"") | I19: =IF(TRIM(Audit!$F$71)="",Audit!$C$25,TRIM(Audit!$F$71)) -> 0 | J19: =IF(OR(I19=Audit!$C$25,I19=""),1,IF(AND(I19=Audit!$C$31,ISNUMBER(Audit!$J$31)),Audit!$J$31,IF(AND(I19=Audit!$C$32,ISNUMBER(Audit!$J$32)),Audit!$J$32,""))) -> 1 | K19: =IF(B19="","",IF(ISNUMBER(Audit!$I$71),Audit!$I$71,IF(G19=0,"",CHOOSE(G19,IF(ISNUMBER(Audit!$C$26),Audit!$C$26,1),1,1,1,$AF$33,$AF$30,$AF$31,1,"",1,0)))) | L19: =IF(O19=1,ROUND(MAX(H19*K19,IF(ISNUMBER(Audit!$J$71),Audit!$J$71,0)),2),"") | M19: =IF(O19=1,ROUND(L19*(1+Y19),2),"") | N19: =IF(O19=1,IF(ISNUMBER(J19),ROUND(M19*J19,2),""),"") | O19: =IF(AND(B19<>"",OR(F19="Firm",F19="Estimate",F19="If required"),ISNUMBER(H19),G19>0,G19<>11,ISNUMBER(K19)),1,0) -> 0 | P19: =IF(ISNUMBER(Audit!$L$71),Audit!$L$71,"") | Q19: =IF(B19="","",IF(OR(F19="At cost",F19="TBC"),"Not priced ("&F19&")",IF(OR(F19="Included",F19="Excluded",F19="Not applicable"),F19,IF(F19="","Status missing",IF(AND(F19="If required",NOT(ISNUMBER(H19))),"Not priced (if required)",IF(G19=0,"Basis missing",IF(G19=11,"Not priced (at cost)",IF(NOT(ISNUMBER(H19)),"Rate missing",IF(AND(G19=9,NOT(ISNUMBER(Audit!$I$71))),"Base amount missing",IF(NOT(ISNUMBER(J19)),"Exchange rate missing",IF(NOT(ISNUMBER(P19)),"Calculated — Not Independently Verified",IF(ABS(R19)<=Lists!$B$44,"Verified","Error - differs by "&TEXT(R19,"#,##0.00")&" "&I19)))))))))))) | R19: =IF(AND(O19=1,ISNUMBER(P19)),IF(ABS(P19-L19)<=ABS(P19-M19),P19-L19,P19-M19),"") | S19: =IF(AND(O19=1,ISNUMBER(Audit!$M$71),ISNUMBER(J19)),IF(H19-Audit!$M$71>0.005,ROUND((H19-Audit!$M$71)*K19*(1+Y19)*J19,2),0),0) -> 0 | T19: =Audit!$N$71&"" | U19: =IF(B19="",0,IF(COUNTIFS($B$2:$B$51,B19,$D$2:$D$51,D19)>1,1,0)) -> 0 | V19: =IF(D19="","",IFERROR(INDEX(Audit!$C$43:$C$49,MATCH(D19,Lists!$A$30:$A$36,0)),"")) | W19: =IF(AND(B19<>"",OR(F19="At cost",F19="TBC",AND(F19<>"If required",G19=11))),1,0) -> 0 | X19: =IF(B19="","",IF(T19<>"","flag",IF(F19="","status",IF(AND(G19=0,OR(F19="Firm",F19="Estimate",AND(F19="If required",ISNUMBER(H19)))),"basis",IF(AND(OR(F19="Firm",F19="Estimate"),G19<>11,NOT(ISNUMBER(H19))),"rate",IF(AND(O19=0,G19=9,OR(F19="Firm",F19="Estimate"),ISNUMBER(H19)),"base",IF(OR(C19="",C19="Unclassified"),"unclass",IF(U19=1,"dup",IF(AND(Audit!$C$19="Yes",O19=1,NOT(ISNUMBER(Audit!$M$71))),"noagree",""))))))))) | Y19: =IF(ISNUMBER(Audit!$K$71),Audit!$K$71,0) -> 0 | Z19: =IF(AND(F19="Firm",O19=1,ISNUMBER(J19)),L19*J19,0) -> 0 | AE19: All-in? | AF19: =IF(AND(AF7>0,AF18=0,AF12=0,COUNTIFS($F$2:$F$51,"If required")=0,AF15=0,AF9=0),1,0) -> 0 | AH19: 18 | AI19: =IFERROR(SMALL($J$70:$J$470,AH19),"") | AJ19: =IF(AI19="","",MATCH(AI19,$J$70:$J$470,0))
A20: 19 | B20: =TRIM(Audit!$B$72) | C20: =Audit!$C$72&"" | D20: =IF(B20="","",IF(C20="","Other",IFERROR(INDEX(Lists!$C$4:$C$16,MATCH(C20,Lists!$A$4:$A$16,0)),"Other"))) | E20: =IF(B20="","",IF(C20="","Other",IFERROR(INDEX(Lists!$B$4:$B$16,MATCH(C20,Lists!$A$4:$A$16,0)),"Other"))) | F20: =Audit!$G$72&"" | G20: =IFERROR(MATCH(Audit!$D$72,Lists!$E$4:$E$14,0),0) -> 0 | H20: =IF(ISNUMBER(Audit!$E$72),Audit!$E$72,"") | I20: =IF(TRIM(Audit!$F$72)="",Audit!$C$25,TRIM(Audit!$F$72)) -> 0 | J20: =IF(OR(I20=Audit!$C$25,I20=""),1,IF(AND(I20=Audit!$C$31,ISNUMBER(Audit!$J$31)),Audit!$J$31,IF(AND(I20=Audit!$C$32,ISNUMBER(Audit!$J$32)),Audit!$J$32,""))) -> 1 | K20: =IF(B20="","",IF(ISNUMBER(Audit!$I$72),Audit!$I$72,IF(G20=0,"",CHOOSE(G20,IF(ISNUMBER(Audit!$C$26),Audit!$C$26,1),1,1,1,$AF$33,$AF$30,$AF$31,1,"",1,0)))) | L20: =IF(O20=1,ROUND(MAX(H20*K20,IF(ISNUMBER(Audit!$J$72),Audit!$J$72,0)),2),"") | M20: =IF(O20=1,ROUND(L20*(1+Y20),2),"") | N20: =IF(O20=1,IF(ISNUMBER(J20),ROUND(M20*J20,2),""),"") | O20: =IF(AND(B20<>"",OR(F20="Firm",F20="Estimate",F20="If required"),ISNUMBER(H20),G20>0,G20<>11,ISNUMBER(K20)),1,0) -> 0 | P20: =IF(ISNUMBER(Audit!$L$72),Audit!$L$72,"") | Q20: =IF(B20="","",IF(OR(F20="At cost",F20="TBC"),"Not priced ("&F20&")",IF(OR(F20="Included",F20="Excluded",F20="Not applicable"),F20,IF(F20="","Status missing",IF(AND(F20="If required",NOT(ISNUMBER(H20))),"Not priced (if required)",IF(G20=0,"Basis missing",IF(G20=11,"Not priced (at cost)",IF(NOT(ISNUMBER(H20)),"Rate missing",IF(AND(G20=9,NOT(ISNUMBER(Audit!$I$72))),"Base amount missing",IF(NOT(ISNUMBER(J20)),"Exchange rate missing",IF(NOT(ISNUMBER(P20)),"Calculated — Not Independently Verified",IF(ABS(R20)<=Lists!$B$44,"Verified","Error - differs by "&TEXT(R20,"#,##0.00")&" "&I20)))))))))))) | R20: =IF(AND(O20=1,ISNUMBER(P20)),IF(ABS(P20-L20)<=ABS(P20-M20),P20-L20,P20-M20),"") | S20: =IF(AND(O20=1,ISNUMBER(Audit!$M$72),ISNUMBER(J20)),IF(H20-Audit!$M$72>0.005,ROUND((H20-Audit!$M$72)*K20*(1+Y20)*J20,2),0),0) -> 0 | T20: =Audit!$N$72&"" | U20: =IF(B20="",0,IF(COUNTIFS($B$2:$B$51,B20,$D$2:$D$51,D20)>1,1,0)) -> 0 | V20: =IF(D20="","",IFERROR(INDEX(Audit!$C$43:$C$49,MATCH(D20,Lists!$A$30:$A$36,0)),"")) | W20: =IF(AND(B20<>"",OR(F20="At cost",F20="TBC",AND(F20<>"If required",G20=11))),1,0) -> 0 | X20: =IF(B20="","",IF(T20<>"","flag",IF(F20="","status",IF(AND(G20=0,OR(F20="Firm",F20="Estimate",AND(F20="If required",ISNUMBER(H20)))),"basis",IF(AND(OR(F20="Firm",F20="Estimate"),G20<>11,NOT(ISNUMBER(H20))),"rate",IF(AND(O20=0,G20=9,OR(F20="Firm",F20="Estimate"),ISNUMBER(H20)),"base",IF(OR(C20="",C20="Unclassified"),"unclass",IF(U20=1,"dup",IF(AND(Audit!$C$19="Yes",O20=1,NOT(ISNUMBER(Audit!$M$72))),"noagree",""))))))))) | Y20: =IF(ISNUMBER(Audit!$K$72),Audit!$K$72,0) -> 0 | Z20: =IF(AND(F20="Firm",O20=1,ISNUMBER(J20)),L20*J20,0) -> 0 | AE20: Total label | AF20: =IF(AF19=1,"All-In Firm Total (as quoted)","Known Firm Charges — Not All-In")&IF(AF3>0," — Subject to Correction","") -> Known Firm Charges — Not All-In | AH20: 19 | AI20: =IFERROR(SMALL($J$70:$J$470,AH20),"") | AJ20: =IF(AI20="","",MATCH(AI20,$J$70:$J$470,0))
A21: 20 | B21: =TRIM(Audit!$B$73) | C21: =Audit!$C$73&"" | D21: =IF(B21="","",IF(C21="","Other",IFERROR(INDEX(Lists!$C$4:$C$16,MATCH(C21,Lists!$A$4:$A$16,0)),"Other"))) | E21: =IF(B21="","",IF(C21="","Other",IFERROR(INDEX(Lists!$B$4:$B$16,MATCH(C21,Lists!$A$4:$A$16,0)),"Other"))) | F21: =Audit!$G$73&"" | G21: =IFERROR(MATCH(Audit!$D$73,Lists!$E$4:$E$14,0),0) -> 0 | H21: =IF(ISNUMBER(Audit!$E$73),Audit!$E$73,"") | I21: =IF(TRIM(Audit!$F$73)="",Audit!$C$25,TRIM(Audit!$F$73)) -> 0 | J21: =IF(OR(I21=Audit!$C$25,I21=""),1,IF(AND(I21=Audit!$C$31,ISNUMBER(Audit!$J$31)),Audit!$J$31,IF(AND(I21=Audit!$C$32,ISNUMBER(Audit!$J$32)),Audit!$J$32,""))) -> 1 | K21: =IF(B21="","",IF(ISNUMBER(Audit!$I$73),Audit!$I$73,IF(G21=0,"",CHOOSE(G21,IF(ISNUMBER(Audit!$C$26),Audit!$C$26,1),1,1,1,$AF$33,$AF$30,$AF$31,1,"",1,0)))) | L21: =IF(O21=1,ROUND(MAX(H21*K21,IF(ISNUMBER(Audit!$J$73),Audit!$J$73,0)),2),"") | M21: =IF(O21=1,ROUND(L21*(1+Y21),2),"") | N21: =IF(O21=1,IF(ISNUMBER(J21),ROUND(M21*J21,2),""),"") | O21: =IF(AND(B21<>"",OR(F21="Firm",F21="Estimate",F21="If required"),ISNUMBER(H21),G21>0,G21<>11,ISNUMBER(K21)),1,0) -> 0 | P21: =IF(ISNUMBER(Audit!$L$73),Audit!$L$73,"") | Q21: =IF(B21="","",IF(OR(F21="At cost",F21="TBC"),"Not priced ("&F21&")",IF(OR(F21="Included",F21="Excluded",F21="Not applicable"),F21,IF(F21="","Status missing",IF(AND(F21="If required",NOT(ISNUMBER(H21))),"Not priced (if required)",IF(G21=0,"Basis missing",IF(G21=11,"Not priced (at cost)",IF(NOT(ISNUMBER(H21)),"Rate missing",IF(AND(G21=9,NOT(ISNUMBER(Audit!$I$73))),"Base amount missing",IF(NOT(ISNUMBER(J21)),"Exchange rate missing",IF(NOT(ISNUMBER(P21)),"Calculated — Not Independently Verified",IF(ABS(R21)<=Lists!$B$44,"Verified","Error - differs by "&TEXT(R21,"#,##0.00")&" "&I21)))))))))))) | R21: =IF(AND(O21=1,ISNUMBER(P21)),IF(ABS(P21-L21)<=ABS(P21-M21),P21-L21,P21-M21),"") | S21: =IF(AND(O21=1,ISNUMBER(Audit!$M$73),ISNUMBER(J21)),IF(H21-Audit!$M$73>0.005,ROUND((H21-Audit!$M$73)*K21*(1+Y21)*J21,2),0),0) -> 0 | T21: =Audit!$N$73&"" | U21: =IF(B21="",0,IF(COUNTIFS($B$2:$B$51,B21,$D$2:$D$51,D21)>1,1,0)) -> 0 | V21: =IF(D21="","",IFERROR(INDEX(Audit!$C$43:$C$49,MATCH(D21,Lists!$A$30:$A$36,0)),"")) | W21: =IF(AND(B21<>"",OR(F21="At cost",F21="TBC",AND(F21<>"If required",G21=11))),1,0) -> 0 | X21: =IF(B21="","",IF(T21<>"","flag",IF(F21="","status",IF(AND(G21=0,OR(F21="Firm",F21="Estimate",AND(F21="If required",ISNUMBER(H21)))),"basis",IF(AND(OR(F21="Firm",F21="Estimate"),G21<>11,NOT(ISNUMBER(H21))),"rate",IF(AND(O21=0,G21=9,OR(F21="Firm",F21="Estimate"),ISNUMBER(H21)),"base",IF(OR(C21="",C21="Unclassified"),"unclass",IF(U21=1,"dup",IF(AND(Audit!$C$19="Yes",O21=1,NOT(ISNUMBER(Audit!$M$73))),"noagree",""))))))))) | Y21: =IF(ISNUMBER(Audit!$K$73),Audit!$K$73,0) -> 0 | Z21: =IF(AND(F21="Firm",O21=1,ISNUMBER(J21)),L21*J21,0) -> 0 | AE21: Status sentence | AF21: =IF(AF2="Not started","Enter shipment, quotation and charge details to start the audit.",IF(AF2="Insufficient Information","The quotation cannot be audited properly yet: see the questions about missing documents or breakdown.",IF(AF2="Corrections Required",AF3&" confirmed error(s) must be corrected by the forwarder"&IF(AF4>0," and "&AF4&" question(s) answered","")&" before the client proceeds.",IF(AF2="Needs Clarification","No confirmed errors, but "&AF4&" question(s) and "&AF5&" risk(s) remain open before the client proceeds.","All checks passed on the information provided. No unpriced, estimated or excluded requested costs remain.")))) -> Enter shipment, quotation and charge details to start the audit. | AH21: 20 | AI21: =IFERROR(SMALL($J$70:$J$470,AH21),"") | AJ21: =IF(AI21="","",MATCH(AI21,$J$70:$J$470,0))
A22: 21 | B22: =TRIM(Audit!$B$74) | C22: =Audit!$C$74&"" | D22: =IF(B22="","",IF(C22="","Other",IFERROR(INDEX(Lists!$C$4:$C$16,MATCH(C22,Lists!$A$4:$A$16,0)),"Other"))) | E22: =IF(B22="","",IF(C22="","Other",IFERROR(INDEX(Lists!$B$4:$B$16,MATCH(C22,Lists!$A$4:$A$16,0)),"Other"))) | F22: =Audit!$G$74&"" | G22: =IFERROR(MATCH(Audit!$D$74,Lists!$E$4:$E$14,0),0) -> 0 | H22: =IF(ISNUMBER(Audit!$E$74),Audit!$E$74,"") | I22: =IF(TRIM(Audit!$F$74)="",Audit!$C$25,TRIM(Audit!$F$74)) -> 0 | J22: =IF(OR(I22=Audit!$C$25,I22=""),1,IF(AND(I22=Audit!$C$31,ISNUMBER(Audit!$J$31)),Audit!$J$31,IF(AND(I22=Audit!$C$32,ISNUMBER(Audit!$J$32)),Audit!$J$32,""))) -> 1 | K22: =IF(B22="","",IF(ISNUMBER(Audit!$I$74),Audit!$I$74,IF(G22=0,"",CHOOSE(G22,IF(ISNUMBER(Audit!$C$26),Audit!$C$26,1),1,1,1,$AF$33,$AF$30,$AF$31,1,"",1,0)))) | L22: =IF(O22=1,ROUND(MAX(H22*K22,IF(ISNUMBER(Audit!$J$74),Audit!$J$74,0)),2),"") | M22: =IF(O22=1,ROUND(L22*(1+Y22),2),"") | N22: =IF(O22=1,IF(ISNUMBER(J22),ROUND(M22*J22,2),""),"") | O22: =IF(AND(B22<>"",OR(F22="Firm",F22="Estimate",F22="If required"),ISNUMBER(H22),G22>0,G22<>11,ISNUMBER(K22)),1,0) -> 0 | P22: =IF(ISNUMBER(Audit!$L$74),Audit!$L$74,"") | Q22: =IF(B22="","",IF(OR(F22="At cost",F22="TBC"),"Not priced ("&F22&")",IF(OR(F22="Included",F22="Excluded",F22="Not applicable"),F22,IF(F22="","Status missing",IF(AND(F22="If required",NOT(ISNUMBER(H22))),"Not priced (if required)",IF(G22=0,"Basis missing",IF(G22=11,"Not priced (at cost)",IF(NOT(ISNUMBER(H22)),"Rate missing",IF(AND(G22=9,NOT(ISNUMBER(Audit!$I$74))),"Base amount missing",IF(NOT(ISNUMBER(J22)),"Exchange rate missing",IF(NOT(ISNUMBER(P22)),"Calculated — Not Independently Verified",IF(ABS(R22)<=Lists!$B$44,"Verified","Error - differs by "&TEXT(R22,"#,##0.00")&" "&I22)))))))))))) | R22: =IF(AND(O22=1,ISNUMBER(P22)),IF(ABS(P22-L22)<=ABS(P22-M22),P22-L22,P22-M22),"") | S22: =IF(AND(O22=1,ISNUMBER(Audit!$M$74),ISNUMBER(J22)),IF(H22-Audit!$M$74>0.005,ROUND((H22-Audit!$M$74)*K22*(1+Y22)*J22,2),0),0) -> 0 | T22: =Audit!$N$74&"" | U22: =IF(B22="",0,IF(COUNTIFS($B$2:$B$51,B22,$D$2:$D$51,D22)>1,1,0)) -> 0 | V22: =IF(D22="","",IFERROR(INDEX(Audit!$C$43:$C$49,MATCH(D22,Lists!$A$30:$A$36,0)),"")) | W22: =IF(AND(B22<>"",OR(F22="At cost",F22="TBC",AND(F22<>"If required",G22=11))),1,0) -> 0 | X22: =IF(B22="","",IF(T22<>"","flag",IF(F22="","status",IF(AND(G22=0,OR(F22="Firm",F22="Estimate",AND(F22="If required",ISNUMBER(H22)))),"basis",IF(AND(OR(F22="Firm",F22="Estimate"),G22<>11,NOT(ISNUMBER(H22))),"rate",IF(AND(O22=0,G22=9,OR(F22="Firm",F22="Estimate"),ISNUMBER(H22)),"base",IF(OR(C22="",C22="Unclassified"),"unclass",IF(U22=1,"dup",IF(AND(Audit!$C$19="Yes",O22=1,NOT(ISNUMBER(Audit!$M$74))),"noagree",""))))))))) | Y22: =IF(ISNUMBER(Audit!$K$74),Audit!$K$74,0) -> 0 | Z22: =IF(AND(F22="Firm",O22=1,ISNUMBER(J22)),L22*J22,0) -> 0 | AE22: Firm note | AF22: =IF(AF3>0,"Subject to correction: "&AF3&" confirmed error(s) open; this figure is the quotation as submitted, not a corrected amount. ","")&IF(AF19=1,"Every requested service is firmly priced.","Not all-in: "&IF(AF18>0,AF18&" requested service(s) excluded, unpriced or not addressed; ","")&IF(AF12>0,"estimates; ","")&IF(COUNTIFS($F$2:$F$51,"If required")>0,"conditional charges; ","")&IF(AF15>0,"at-cost/TBC items; ","")&IF(AF9>0,"missing exchange rates; ","")) -> Not all-in: | AH22: 21 | AI22: =IFERROR(SMALL($J$70:$J$470,AH22),"") | AJ22: =IF(AI22="","",MATCH(AI22,$J$70:$J$470,0))
A23: 22 | B23: =TRIM(Audit!$B$75) | C23: =Audit!$C$75&"" | D23: =IF(B23="","",IF(C23="","Other",IFERROR(INDEX(Lists!$C$4:$C$16,MATCH(C23,Lists!$A$4:$A$16,0)),"Other"))) | E23: =IF(B23="","",IF(C23="","Other",IFERROR(INDEX(Lists!$B$4:$B$16,MATCH(C23,Lists!$A$4:$A$16,0)),"Other"))) | F23: =Audit!$G$75&"" | G23: =IFERROR(MATCH(Audit!$D$75,Lists!$E$4:$E$14,0),0) -> 0 | H23: =IF(ISNUMBER(Audit!$E$75),Audit!$E$75,"") | I23: =IF(TRIM(Audit!$F$75)="",Audit!$C$25,TRIM(Audit!$F$75)) -> 0 | J23: =IF(OR(I23=Audit!$C$25,I23=""),1,IF(AND(I23=Audit!$C$31,ISNUMBER(Audit!$J$31)),Audit!$J$31,IF(AND(I23=Audit!$C$32,ISNUMBER(Audit!$J$32)),Audit!$J$32,""))) -> 1 | K23: =IF(B23="","",IF(ISNUMBER(Audit!$I$75),Audit!$I$75,IF(G23=0,"",CHOOSE(G23,IF(ISNUMBER(Audit!$C$26),Audit!$C$26,1),1,1,1,$AF$33,$AF$30,$AF$31,1,"",1,0)))) | L23: =IF(O23=1,ROUND(MAX(H23*K23,IF(ISNUMBER(Audit!$J$75),Audit!$J$75,0)),2),"") | M23: =IF(O23=1,ROUND(L23*(1+Y23),2),"") | N23: =IF(O23=1,IF(ISNUMBER(J23),ROUND(M23*J23,2),""),"") | O23: =IF(AND(B23<>"",OR(F23="Firm",F23="Estimate",F23="If required"),ISNUMBER(H23),G23>0,G23<>11,ISNUMBER(K23)),1,0) -> 0 | P23: =IF(ISNUMBER(Audit!$L$75),Audit!$L$75,"") | Q23: =IF(B23="","",IF(OR(F23="At cost",F23="TBC"),"Not priced ("&F23&")",IF(OR(F23="Included",F23="Excluded",F23="Not applicable"),F23,IF(F23="","Status missing",IF(AND(F23="If required",NOT(ISNUMBER(H23))),"Not priced (if required)",IF(G23=0,"Basis missing",IF(G23=11,"Not priced (at cost)",IF(NOT(ISNUMBER(H23)),"Rate missing",IF(AND(G23=9,NOT(ISNUMBER(Audit!$I$75))),"Base amount missing",IF(NOT(ISNUMBER(J23)),"Exchange rate missing",IF(NOT(ISNUMBER(P23)),"Calculated — Not Independently Verified",IF(ABS(R23)<=Lists!$B$44,"Verified","Error - differs by "&TEXT(R23,"#,##0.00")&" "&I23)))))))))))) | R23: =IF(AND(O23=1,ISNUMBER(P23)),IF(ABS(P23-L23)<=ABS(P23-M23),P23-L23,P23-M23),"") | S23: =IF(AND(O23=1,ISNUMBER(Audit!$M$75),ISNUMBER(J23)),IF(H23-Audit!$M$75>0.005,ROUND((H23-Audit!$M$75)*K23*(1+Y23)*J23,2),0),0) -> 0 | T23: =Audit!$N$75&"" | U23: =IF(B23="",0,IF(COUNTIFS($B$2:$B$51,B23,$D$2:$D$51,D23)>1,1,0)) -> 0 | V23: =IF(D23="","",IFERROR(INDEX(Audit!$C$43:$C$49,MATCH(D23,Lists!$A$30:$A$36,0)),"")) | W23: =IF(AND(B23<>"",OR(F23="At cost",F23="TBC",AND(F23<>"If required",G23=11))),1,0) -> 0 | X23: =IF(B23="","",IF(T23<>"","flag",IF(F23="","status",IF(AND(G23=0,OR(F23="Firm",F23="Estimate",AND(F23="If required",ISNUMBER(H23)))),"basis",IF(AND(OR(F23="Firm",F23="Estimate"),G23<>11,NOT(ISNUMBER(H23))),"rate",IF(AND(O23=0,G23=9,OR(F23="Firm",F23="Estimate"),ISNUMBER(H23)),"base",IF(OR(C23="",C23="Unclassified"),"unclass",IF(U23=1,"dup",IF(AND(Audit!$C$19="Yes",O23=1,NOT(ISNUMBER(Audit!$M$75))),"noagree",""))))))))) | Y23: =IF(ISNUMBER(Audit!$K$75),Audit!$K$75,0) -> 0 | Z23: =IF(AND(F23="Firm",O23=1,ISNUMBER(J23)),L23*J23,0) -> 0 | AE23: Verification text | AF23: =AF25&" verified · "&AF26&" calculated, not independently verified · "&AF27&" with errors" -> 0 verified · 0 calculated, not independently verified · 0 with errors | AH23: 22 | AI23: =IFERROR(SMALL($J$70:$J$470,AH23),"") | AJ23: =IF(AI23="","",MATCH(AI23,$J$70:$J$470,0))
A24: 23 | B24: =TRIM(Audit!$B$76) | C24: =Audit!$C$76&"" | D24: =IF(B24="","",IF(C24="","Other",IFERROR(INDEX(Lists!$C$4:$C$16,MATCH(C24,Lists!$A$4:$A$16,0)),"Other"))) | E24: =IF(B24="","",IF(C24="","Other",IFERROR(INDEX(Lists!$B$4:$B$16,MATCH(C24,Lists!$A$4:$A$16,0)),"Other"))) | F24: =Audit!$G$76&"" | G24: =IFERROR(MATCH(Audit!$D$76,Lists!$E$4:$E$14,0),0) -> 0 | H24: =IF(ISNUMBER(Audit!$E$76),Audit!$E$76,"") | I24: =IF(TRIM(Audit!$F$76)="",Audit!$C$25,TRIM(Audit!$F$76)) -> 0 | J24: =IF(OR(I24=Audit!$C$25,I24=""),1,IF(AND(I24=Audit!$C$31,ISNUMBER(Audit!$J$31)),Audit!$J$31,IF(AND(I24=Audit!$C$32,ISNUMBER(Audit!$J$32)),Audit!$J$32,""))) -> 1 | K24: =IF(B24="","",IF(ISNUMBER(Audit!$I$76),Audit!$I$76,IF(G24=0,"",CHOOSE(G24,IF(ISNUMBER(Audit!$C$26),Audit!$C$26,1),1,1,1,$AF$33,$AF$30,$AF$31,1,"",1,0)))) | L24: =IF(O24=1,ROUND(MAX(H24*K24,IF(ISNUMBER(Audit!$J$76),Audit!$J$76,0)),2),"") | M24: =IF(O24=1,ROUND(L24*(1+Y24),2),"") | N24: =IF(O24=1,IF(ISNUMBER(J24),ROUND(M24*J24,2),""),"") | O24: =IF(AND(B24<>"",OR(F24="Firm",F24="Estimate",F24="If required"),ISNUMBER(H24),G24>0,G24<>11,ISNUMBER(K24)),1,0) -> 0 | P24: =IF(ISNUMBER(Audit!$L$76),Audit!$L$76,"") | Q24: =IF(B24="","",IF(OR(F24="At cost",F24="TBC"),"Not priced ("&F24&")",IF(OR(F24="Included",F24="Excluded",F24="Not applicable"),F24,IF(F24="","Status missing",IF(AND(F24="If required",NOT(ISNUMBER(H24))),"Not priced (if required)",IF(G24=0,"Basis missing",IF(G24=11,"Not priced (at cost)",IF(NOT(ISNUMBER(H24)),"Rate missing",IF(AND(G24=9,NOT(ISNUMBER(Audit!$I$76))),"Base amount missing",IF(NOT(ISNUMBER(J24)),"Exchange rate missing",IF(NOT(ISNUMBER(P24)),"Calculated — Not Independently Verified",IF(ABS(R24)<=Lists!$B$44,"Verified","Error - differs by "&TEXT(R24,"#,##0.00")&" "&I24)))))))))))) | R24: =IF(AND(O24=1,ISNUMBER(P24)),IF(ABS(P24-L24)<=ABS(P24-M24),P24-L24,P24-M24),"") | S24: =IF(AND(O24=1,ISNUMBER(Audit!$M$76),ISNUMBER(J24)),IF(H24-Audit!$M$76>0.005,ROUND((H24-Audit!$M$76)*K24*(1+Y24)*J24,2),0),0) -> 0 | T24: =Audit!$N$76&"" | U24: =IF(B24="",0,IF(COUNTIFS($B$2:$B$51,B24,$D$2:$D$51,D24)>1,1,0)) -> 0 | V24: =IF(D24="","",IFERROR(INDEX(Audit!$C$43:$C$49,MATCH(D24,Lists!$A$30:$A$36,0)),"")) | W24: =IF(AND(B24<>"",OR(F24="At cost",F24="TBC",AND(F24<>"If required",G24=11))),1,0) -> 0 | X24: =IF(B24="","",IF(T24<>"","flag",IF(F24="","status",IF(AND(G24=0,OR(F24="Firm",F24="Estimate",AND(F24="If required",ISNUMBER(H24)))),"basis",IF(AND(OR(F24="Firm",F24="Estimate"),G24<>11,NOT(ISNUMBER(H24))),"rate",IF(AND(O24=0,G24=9,OR(F24="Firm",F24="Estimate"),ISNUMBER(H24)),"base",IF(OR(C24="",C24="Unclassified"),"unclass",IF(U24=1,"dup",IF(AND(Audit!$C$19="Yes",O24=1,NOT(ISNUMBER(Audit!$M$76))),"noagree",""))))))))) | Y24: =IF(ISNUMBER(Audit!$K$76),Audit!$K$76,0) -> 0 | Z24: =IF(AND(F24="Firm",O24=1,ISNUMBER(J24)),L24*J24,0) -> 0 | AE24: Not checked | AF24: =IF(Audit!$C$19="Yes","","Agreed rates (no rate agreement provided); ")&"market price levels (no benchmark used); duty and tax rates (to be confirmed by a licensed customs broker)." -> Agreed rates (no rate agreement provided); market price levels (no benchmark used); duty and tax rates (to be confirmed by a licensed customs broker). | AH24: 23 | AI24: =IFERROR(SMALL($J$70:$J$470,AH24),"") | AJ24: =IF(AI24="","",MATCH(AI24,$J$70:$J$470,0))
A25: 24 | B25: =TRIM(Audit!$B$77) | C25: =Audit!$C$77&"" | D25: =IF(B25="","",IF(C25="","Other",IFERROR(INDEX(Lists!$C$4:$C$16,MATCH(C25,Lists!$A$4:$A$16,0)),"Other"))) | E25: =IF(B25="","",IF(C25="","Other",IFERROR(INDEX(Lists!$B$4:$B$16,MATCH(C25,Lists!$A$4:$A$16,0)),"Other"))) | F25: =Audit!$G$77&"" | G25: =IFERROR(MATCH(Audit!$D$77,Lists!$E$4:$E$14,0),0) -> 0 | H25: =IF(ISNUMBER(Audit!$E$77),Audit!$E$77,"") | I25: =IF(TRIM(Audit!$F$77)="",Audit!$C$25,TRIM(Audit!$F$77)) -> 0 | J25: =IF(OR(I25=Audit!$C$25,I25=""),1,IF(AND(I25=Audit!$C$31,ISNUMBER(Audit!$J$31)),Audit!$J$31,IF(AND(I25=Audit!$C$32,ISNUMBER(Audit!$J$32)),Audit!$J$32,""))) -> 1 | K25: =IF(B25="","",IF(ISNUMBER(Audit!$I$77),Audit!$I$77,IF(G25=0,"",CHOOSE(G25,IF(ISNUMBER(Audit!$C$26),Audit!$C$26,1),1,1,1,$AF$33,$AF$30,$AF$31,1,"",1,0)))) | L25: =IF(O25=1,ROUND(MAX(H25*K25,IF(ISNUMBER(Audit!$J$77),Audit!$J$77,0)),2),"") | M25: =IF(O25=1,ROUND(L25*(1+Y25),2),"") | N25: =IF(O25=1,IF(ISNUMBER(J25),ROUND(M25*J25,2),""),"") | O25: =IF(AND(B25<>"",OR(F25="Firm",F25="Estimate",F25="If required"),ISNUMBER(H25),G25>0,G25<>11,ISNUMBER(K25)),1,0) -> 0 | P25: =IF(ISNUMBER(Audit!$L$77),Audit!$L$77,"") | Q25: =IF(B25="","",IF(OR(F25="At cost",F25="TBC"),"Not priced ("&F25&")",IF(OR(F25="Included",F25="Excluded",F25="Not applicable"),F25,IF(F25="","Status missing",IF(AND(F25="If required",NOT(ISNUMBER(H25))),"Not priced (if required)",IF(G25=0,"Basis missing",IF(G25=11,"Not priced (at cost)",IF(NOT(ISNUMBER(H25)),"Rate missing",IF(AND(G25=9,NOT(ISNUMBER(Audit!$I$77))),"Base amount missing",IF(NOT(ISNUMBER(J25)),"Exchange rate missing",IF(NOT(ISNUMBER(P25)),"Calculated — Not Independently Verified",IF(ABS(R25)<=Lists!$B$44,"Verified","Error - differs by "&TEXT(R25,"#,##0.00")&" "&I25)))))))))))) | R25: =IF(AND(O25=1,ISNUMBER(P25)),IF(ABS(P25-L25)<=ABS(P25-M25),P25-L25,P25-M25),"") | S25: =IF(AND(O25=1,ISNUMBER(Audit!$M$77),ISNUMBER(J25)),IF(H25-Audit!$M$77>0.005,ROUND((H25-Audit!$M$77)*K25*(1+Y25)*J25,2),0),0) -> 0 | T25: =Audit!$N$77&"" | U25: =IF(B25="",0,IF(COUNTIFS($B$2:$B$51,B25,$D$2:$D$51,D25)>1,1,0)) -> 0 | V25: =IF(D25="","",IFERROR(INDEX(Audit!$C$43:$C$49,MATCH(D25,Lists!$A$30:$A$36,0)),"")) | W25: =IF(AND(B25<>"",OR(F25="At cost",F25="TBC",AND(F25<>"If required",G25=11))),1,0) -> 0 | X25: =IF(B25="","",IF(T25<>"","flag",IF(F25="","status",IF(AND(G25=0,OR(F25="Firm",F25="Estimate",AND(F25="If required",ISNUMBER(H25)))),"basis",IF(AND(OR(F25="Firm",F25="Estimate"),G25<>11,NOT(ISNUMBER(H25))),"rate",IF(AND(O25=0,G25=9,OR(F25="Firm",F25="Estimate"),ISNUMBER(H25)),"base",IF(OR(C25="",C25="Unclassified"),"unclass",IF(U25=1,"dup",IF(AND(Audit!$C$19="Yes",O25=1,NOT(ISNUMBER(Audit!$M$77))),"noagree",""))))))))) | Y25: =IF(ISNUMBER(Audit!$K$77),Audit!$K$77,0) -> 0 | Z25: =IF(AND(F25="Firm",O25=1,ISNUMBER(J25)),L25*J25,0) -> 0 | AE25: Verified count | AF25: =COUNTIFS($Q$2:$Q$51,"Verified") -> 0 | AH25: 24 | AI25: =IFERROR(SMALL($J$70:$J$470,AH25),"") | AJ25: =IF(AI25="","",MATCH(AI25,$J$70:$J$470,0))
A26: 25 | B26: =TRIM(Audit!$B$78) | C26: =Audit!$C$78&"" | D26: =IF(B26="","",IF(C26="","Other",IFERROR(INDEX(Lists!$C$4:$C$16,MATCH(C26,Lists!$A$4:$A$16,0)),"Other"))) | E26: =IF(B26="","",IF(C26="","Other",IFERROR(INDEX(Lists!$B$4:$B$16,MATCH(C26,Lists!$A$4:$A$16,0)),"Other"))) | F26: =Audit!$G$78&"" | G26: =IFERROR(MATCH(Audit!$D$78,Lists!$E$4:$E$14,0),0) -> 0 | H26: =IF(ISNUMBER(Audit!$E$78),Audit!$E$78,"") | I26: =IF(TRIM(Audit!$F$78)="",Audit!$C$25,TRIM(Audit!$F$78)) -> 0 | J26: =IF(OR(I26=Audit!$C$25,I26=""),1,IF(AND(I26=Audit!$C$31,ISNUMBER(Audit!$J$31)),Audit!$J$31,IF(AND(I26=Audit!$C$32,ISNUMBER(Audit!$J$32)),Audit!$J$32,""))) -> 1 | K26: =IF(B26="","",IF(ISNUMBER(Audit!$I$78),Audit!$I$78,IF(G26=0,"",CHOOSE(G26,IF(ISNUMBER(Audit!$C$26),Audit!$C$26,1),1,1,1,$AF$33,$AF$30,$AF$31,1,"",1,0)))) | L26: =IF(O26=1,ROUND(MAX(H26*K26,IF(ISNUMBER(Audit!$J$78),Audit!$J$78,0)),2),"") | M26: =IF(O26=1,ROUND(L26*(1+Y26),2),"") | N26: =IF(O26=1,IF(ISNUMBER(J26),ROUND(M26*J26,2),""),"") | O26: =IF(AND(B26<>"",OR(F26="Firm",F26="Estimate",F26="If required"),ISNUMBER(H26),G26>0,G26<>11,ISNUMBER(K26)),1,0) -> 0 | P26: =IF(ISNUMBER(Audit!$L$78),Audit!$L$78,"") | Q26: =IF(B26="","",IF(OR(F26="At cost",F26="TBC"),"Not priced ("&F26&")",IF(OR(F26="Included",F26="Excluded",F26="Not applicable"),F26,IF(F26="","Status missing",IF(AND(F26="If required",NOT(ISNUMBER(H26))),"Not priced (if required)",IF(G26=0,"Basis missing",IF(G26=11,"Not priced (at cost)",IF(NOT(ISNUMBER(H26)),"Rate missing",IF(AND(G26=9,NOT(ISNUMBER(Audit!$I$78))),"Base amount missing",IF(NOT(ISNUMBER(J26)),"Exchange rate missing",IF(NOT(ISNUMBER(P26)),"Calculated — Not Independently Verified",IF(ABS(R26)<=Lists!$B$44,"Verified","Error - differs by "&TEXT(R26,"#,##0.00")&" "&I26)))))))))))) | R26: =IF(AND(O26=1,ISNUMBER(P26)),IF(ABS(P26-L26)<=ABS(P26-M26),P26-L26,P26-M26),"") | S26: =IF(AND(O26=1,ISNUMBER(Audit!$M$78),ISNUMBER(J26)),IF(H26-Audit!$M$78>0.005,ROUND((H26-Audit!$M$78)*K26*(1+Y26)*J26,2),0),0) -> 0 | T26: =Audit!$N$78&"" | U26: =IF(B26="",0,IF(COUNTIFS($B$2:$B$51,B26,$D$2:$D$51,D26)>1,1,0)) -> 0 | V26: =IF(D26="","",IFERROR(INDEX(Audit!$C$43:$C$49,MATCH(D26,Lists!$A$30:$A$36,0)),"")) | W26: =IF(AND(B26<>"",OR(F26="At cost",F26="TBC",AND(F26<>"If required",G26=11))),1,0) -> 0 | X26: =IF(B26="","",IF(T26<>"","flag",IF(F26="","status",IF(AND(G26=0,OR(F26="Firm",F26="Estimate",AND(F26="If required",ISNUMBER(H26)))),"basis",IF(AND(OR(F26="Firm",F26="Estimate"),G26<>11,NOT(ISNUMBER(H26))),"rate",IF(AND(O26=0,G26=9,OR(F26="Firm",F26="Estimate"),ISNUMBER(H26)),"base",IF(OR(C26="",C26="Unclassified"),"unclass",IF(U26=1,"dup",IF(AND(Audit!$C$19="Yes",O26=1,NOT(ISNUMBER(Audit!$M$78))),"noagree",""))))))))) | Y26: =IF(ISNUMBER(Audit!$K$78),Audit!$K$78,0) -> 0 | Z26: =IF(AND(F26="Firm",O26=1,ISNUMBER(J26)),L26*J26,0) -> 0 | AE26: Calc-only count | AF26: =COUNTIFS($Q$2:$Q$51,"Calculated — Not Independently Verified") -> 0 | AH26: 25 | AI26: =IFERROR(SMALL($J$70:$J$470,AH26),"") | AJ26: =IF(AI26="","",MATCH(AI26,$J$70:$J$470,0))
A27: 26 | B27: =TRIM(Audit!$B$79) | C27: =Audit!$C$79&"" | D27: =IF(B27="","",IF(C27="","Other",IFERROR(INDEX(Lists!$C$4:$C$16,MATCH(C27,Lists!$A$4:$A$16,0)),"Other"))) | E27: =IF(B27="","",IF(C27="","Other",IFERROR(INDEX(Lists!$B$4:$B$16,MATCH(C27,Lists!$A$4:$A$16,0)),"Other"))) | F27: =Audit!$G$79&"" | G27: =IFERROR(MATCH(Audit!$D$79,Lists!$E$4:$E$14,0),0) -> 0 | H27: =IF(ISNUMBER(Audit!$E$79),Audit!$E$79,"") | I27: =IF(TRIM(Audit!$F$79)="",Audit!$C$25,TRIM(Audit!$F$79)) -> 0 | J27: =IF(OR(I27=Audit!$C$25,I27=""),1,IF(AND(I27=Audit!$C$31,ISNUMBER(Audit!$J$31)),Audit!$J$31,IF(AND(I27=Audit!$C$32,ISNUMBER(Audit!$J$32)),Audit!$J$32,""))) -> 1 | K27: =IF(B27="","",IF(ISNUMBER(Audit!$I$79),Audit!$I$79,IF(G27=0,"",CHOOSE(G27,IF(ISNUMBER(Audit!$C$26),Audit!$C$26,1),1,1,1,$AF$33,$AF$30,$AF$31,1,"",1,0)))) | L27: =IF(O27=1,ROUND(MAX(H27*K27,IF(ISNUMBER(Audit!$J$79),Audit!$J$79,0)),2),"") | M27: =IF(O27=1,ROUND(L27*(1+Y27),2),"") | N27: =IF(O27=1,IF(ISNUMBER(J27),ROUND(M27*J27,2),""),"") | O27: =IF(AND(B27<>"",OR(F27="Firm",F27="Estimate",F27="If required"),ISNUMBER(H27),G27>0,G27<>11,ISNUMBER(K27)),1,0) -> 0 | P27: =IF(ISNUMBER(Audit!$L$79),Audit!$L$79,"") | Q27: =IF(B27="","",IF(OR(F27="At cost",F27="TBC"),"Not priced ("&F27&")",IF(OR(F27="Included",F27="Excluded",F27="Not applicable"),F27,IF(F27="","Status missing",IF(AND(F27="If required",NOT(ISNUMBER(H27))),"Not priced (if required)",IF(G27=0,"Basis missing",IF(G27=11,"Not priced (at cost)",IF(NOT(ISNUMBER(H27)),"Rate missing",IF(AND(G27=9,NOT(ISNUMBER(Audit!$I$79))),"Base amount missing",IF(NOT(ISNUMBER(J27)),"Exchange rate missing",IF(NOT(ISNUMBER(P27)),"Calculated — Not Independently Verified",IF(ABS(R27)<=Lists!$B$44,"Verified","Error - differs by "&TEXT(R27,"#,##0.00")&" "&I27)))))))))))) | R27: =IF(AND(O27=1,ISNUMBER(P27)),IF(ABS(P27-L27)<=ABS(P27-M27),P27-L27,P27-M27),"") | S27: =IF(AND(O27=1,ISNUMBER(Audit!$M$79),ISNUMBER(J27)),IF(H27-Audit!$M$79>0.005,ROUND((H27-Audit!$M$79)*K27*(1+Y27)*J27,2),0),0) -> 0 | T27: =Audit!$N$79&"" | U27: =IF(B27="",0,IF(COUNTIFS($B$2:$B$51,B27,$D$2:$D$51,D27)>1,1,0)) -> 0 | V27: =IF(D27="","",IFERROR(INDEX(Audit!$C$43:$C$49,MATCH(D27,Lists!$A$30:$A$36,0)),"")) | W27: =IF(AND(B27<>"",OR(F27="At cost",F27="TBC",AND(F27<>"If required",G27=11))),1,0) -> 0 | X27: =IF(B27="","",IF(T27<>"","flag",IF(F27="","status",IF(AND(G27=0,OR(F27="Firm",F27="Estimate",AND(F27="If required",ISNUMBER(H27)))),"basis",IF(AND(OR(F27="Firm",F27="Estimate"),G27<>11,NOT(ISNUMBER(H27))),"rate",IF(AND(O27=0,G27=9,OR(F27="Firm",F27="Estimate"),ISNUMBER(H27)),"base",IF(OR(C27="",C27="Unclassified"),"unclass",IF(U27=1,"dup",IF(AND(Audit!$C$19="Yes",O27=1,NOT(ISNUMBER(Audit!$M$79))),"noagree",""))))))))) | Y27: =IF(ISNUMBER(Audit!$K$79),Audit!$K$79,0) -> 0 | Z27: =IF(AND(F27="Firm",O27=1,ISNUMBER(J27)),L27*J27,0) -> 0 | AE27: Error lines | AF27: =COUNTIFS($Q$2:$Q$51,"Error*") -> 0 | AH27: 26 | AI27: =IFERROR(SMALL($J$70:$J$470,AH27),"") | AJ27: =IF(AI27="","",MATCH(AI27,$J$70:$J$470,0))
A28: 27 | B28: =TRIM(Audit!$B$80) | C28: =Audit!$C$80&"" | D28: =IF(B28="","",IF(C28="","Other",IFERROR(INDEX(Lists!$C$4:$C$16,MATCH(C28,Lists!$A$4:$A$16,0)),"Other"))) | E28: =IF(B28="","",IF(C28="","Other",IFERROR(INDEX(Lists!$B$4:$B$16,MATCH(C28,Lists!$A$4:$A$16,0)),"Other"))) | F28: =Audit!$G$80&"" | G28: =IFERROR(MATCH(Audit!$D$80,Lists!$E$4:$E$14,0),0) -> 0 | H28: =IF(ISNUMBER(Audit!$E$80),Audit!$E$80,"") | I28: =IF(TRIM(Audit!$F$80)="",Audit!$C$25,TRIM(Audit!$F$80)) -> 0 | J28: =IF(OR(I28=Audit!$C$25,I28=""),1,IF(AND(I28=Audit!$C$31,ISNUMBER(Audit!$J$31)),Audit!$J$31,IF(AND(I28=Audit!$C$32,ISNUMBER(Audit!$J$32)),Audit!$J$32,""))) -> 1 | K28: =IF(B28="","",IF(ISNUMBER(Audit!$I$80),Audit!$I$80,IF(G28=0,"",CHOOSE(G28,IF(ISNUMBER(Audit!$C$26),Audit!$C$26,1),1,1,1,$AF$33,$AF$30,$AF$31,1,"",1,0)))) | L28: =IF(O28=1,ROUND(MAX(H28*K28,IF(ISNUMBER(Audit!$J$80),Audit!$J$80,0)),2),"") | M28: =IF(O28=1,ROUND(L28*(1+Y28),2),"") | N28: =IF(O28=1,IF(ISNUMBER(J28),ROUND(M28*J28,2),""),"") | O28: =IF(AND(B28<>"",OR(F28="Firm",F28="Estimate",F28="If required"),ISNUMBER(H28),G28>0,G28<>11,ISNUMBER(K28)),1,0) -> 0 | P28: =IF(ISNUMBER(Audit!$L$80),Audit!$L$80,"") | Q28: =IF(B28="","",IF(OR(F28="At cost",F28="TBC"),"Not priced ("&F28&")",IF(OR(F28="Included",F28="Excluded",F28="Not applicable"),F28,IF(F28="","Status missing",IF(AND(F28="If required",NOT(ISNUMBER(H28))),"Not priced (if required)",IF(G28=0,"Basis missing",IF(G28=11,"Not priced (at cost)",IF(NOT(ISNUMBER(H28)),"Rate missing",IF(AND(G28=9,NOT(ISNUMBER(Audit!$I$80))),"Base amount missing",IF(NOT(ISNUMBER(J28)),"Exchange rate missing",IF(NOT(ISNUMBER(P28)),"Calculated — Not Independently Verified",IF(ABS(R28)<=Lists!$B$44,"Verified","Error - differs by "&TEXT(R28,"#,##0.00")&" "&I28)))))))))))) | R28: =IF(AND(O28=1,ISNUMBER(P28)),IF(ABS(P28-L28)<=ABS(P28-M28),P28-L28,P28-M28),"") | S28: =IF(AND(O28=1,ISNUMBER(Audit!$M$80),ISNUMBER(J28)),IF(H28-Audit!$M$80>0.005,ROUND((H28-Audit!$M$80)*K28*(1+Y28)*J28,2),0),0) -> 0 | T28: =Audit!$N$80&"" | U28: =IF(B28="",0,IF(COUNTIFS($B$2:$B$51,B28,$D$2:$D$51,D28)>1,1,0)) -> 0 | V28: =IF(D28="","",IFERROR(INDEX(Audit!$C$43:$C$49,MATCH(D28,Lists!$A$30:$A$36,0)),"")) | W28: =IF(AND(B28<>"",OR(F28="At cost",F28="TBC",AND(F28<>"If required",G28=11))),1,0) -> 0 | X28: =IF(B28="","",IF(T28<>"","flag",IF(F28="","status",IF(AND(G28=0,OR(F28="Firm",F28="Estimate",AND(F28="If required",ISNUMBER(H28)))),"basis",IF(AND(OR(F28="Firm",F28="Estimate"),G28<>11,NOT(ISNUMBER(H28))),"rate",IF(AND(O28=0,G28=9,OR(F28="Firm",F28="Estimate"),ISNUMBER(H28)),"base",IF(OR(C28="",C28="Unclassified"),"unclass",IF(U28=1,"dup",IF(AND(Audit!$C$19="Yes",O28=1,NOT(ISNUMBER(Audit!$M$80))),"noagree",""))))))))) | Y28: =IF(ISNUMBER(Audit!$K$80),Audit!$K$80,0) -> 0 | Z28: =IF(AND(F28="Firm",O28=1,ISNUMBER(J28)),L28*J28,0) -> 0 | AE28: Firm pre-tax (quote cur) | AF28: =SUM($Z$2:$Z$51) -> 0 | AH28: 27 | AI28: =IFERROR(SMALL($J$70:$J$470,AH28),"") | AJ28: =IF(AI28="","",MATCH(AI28,$J$70:$J$470,0))
A29: 28 | B29: =TRIM(Audit!$B$81) | C29: =Audit!$C$81&"" | D29: =IF(B29="","",IF(C29="","Other",IFERROR(INDEX(Lists!$C$4:$C$16,MATCH(C29,Lists!$A$4:$A$16,0)),"Other"))) | E29: =IF(B29="","",IF(C29="","Other",IFERROR(INDEX(Lists!$B$4:$B$16,MATCH(C29,Lists!$A$4:$A$16,0)),"Other"))) | F29: =Audit!$G$81&"" | G29: =IFERROR(MATCH(Audit!$D$81,Lists!$E$4:$E$14,0),0) -> 0 | H29: =IF(ISNUMBER(Audit!$E$81),Audit!$E$81,"") | I29: =IF(TRIM(Audit!$F$81)="",Audit!$C$25,TRIM(Audit!$F$81)) -> 0 | J29: =IF(OR(I29=Audit!$C$25,I29=""),1,IF(AND(I29=Audit!$C$31,ISNUMBER(Audit!$J$31)),Audit!$J$31,IF(AND(I29=Audit!$C$32,ISNUMBER(Audit!$J$32)),Audit!$J$32,""))) -> 1 | K29: =IF(B29="","",IF(ISNUMBER(Audit!$I$81),Audit!$I$81,IF(G29=0,"",CHOOSE(G29,IF(ISNUMBER(Audit!$C$26),Audit!$C$26,1),1,1,1,$AF$33,$AF$30,$AF$31,1,"",1,0)))) | L29: =IF(O29=1,ROUND(MAX(H29*K29,IF(ISNUMBER(Audit!$J$81),Audit!$J$81,0)),2),"") | M29: =IF(O29=1,ROUND(L29*(1+Y29),2),"") | N29: =IF(O29=1,IF(ISNUMBER(J29),ROUND(M29*J29,2),""),"") | O29: =IF(AND(B29<>"",OR(F29="Firm",F29="Estimate",F29="If required"),ISNUMBER(H29),G29>0,G29<>11,ISNUMBER(K29)),1,0) -> 0 | P29: =IF(ISNUMBER(Audit!$L$81),Audit!$L$81,"") | Q29: =IF(B29="","",IF(OR(F29="At cost",F29="TBC"),"Not priced ("&F29&")",IF(OR(F29="Included",F29="Excluded",F29="Not applicable"),F29,IF(F29="","Status missing",IF(AND(F29="If required",NOT(ISNUMBER(H29))),"Not priced (if required)",IF(G29=0,"Basis missing",IF(G29=11,"Not priced (at cost)",IF(NOT(ISNUMBER(H29)),"Rate missing",IF(AND(G29=9,NOT(ISNUMBER(Audit!$I$81))),"Base amount missing",IF(NOT(ISNUMBER(J29)),"Exchange rate missing",IF(NOT(ISNUMBER(P29)),"Calculated — Not Independently Verified",IF(ABS(R29)<=Lists!$B$44,"Verified","Error - differs by "&TEXT(R29,"#,##0.00")&" "&I29)))))))))))) | R29: =IF(AND(O29=1,ISNUMBER(P29)),IF(ABS(P29-L29)<=ABS(P29-M29),P29-L29,P29-M29),"") | S29: =IF(AND(O29=1,ISNUMBER(Audit!$M$81),ISNUMBER(J29)),IF(H29-Audit!$M$81>0.005,ROUND((H29-Audit!$M$81)*K29*(1+Y29)*J29,2),0),0) -> 0 | T29: =Audit!$N$81&"" | U29: =IF(B29="",0,IF(COUNTIFS($B$2:$B$51,B29,$D$2:$D$51,D29)>1,1,0)) -> 0 | V29: =IF(D29="","",IFERROR(INDEX(Audit!$C$43:$C$49,MATCH(D29,Lists!$A$30:$A$36,0)),"")) | W29: =IF(AND(B29<>"",OR(F29="At cost",F29="TBC",AND(F29<>"If required",G29=11))),1,0) -> 0 | X29: =IF(B29="","",IF(T29<>"","flag",IF(F29="","status",IF(AND(G29=0,OR(F29="Firm",F29="Estimate",AND(F29="If required",ISNUMBER(H29)))),"basis",IF(AND(OR(F29="Firm",F29="Estimate"),G29<>11,NOT(ISNUMBER(H29))),"rate",IF(AND(O29=0,G29=9,OR(F29="Firm",F29="Estimate"),ISNUMBER(H29)),"base",IF(OR(C29="",C29="Unclassified"),"unclass",IF(U29=1,"dup",IF(AND(Audit!$C$19="Yes",O29=1,NOT(ISNUMBER(Audit!$M$81))),"noagree",""))))))))) | Y29: =IF(ISNUMBER(Audit!$K$81),Audit!$K$81,0) -> 0 | Z29: =IF(AND(F29="Firm",O29=1,ISNUMBER(J29)),L29*J29,0) -> 0 | AE29: Firm incl tax (quote cur) | AF29: =AF10 -> 0 | AH29: 28 | AI29: =IFERROR(SMALL($J$70:$J$470,AH29),"") | AJ29: =IF(AI29="","",MATCH(AI29,$J$70:$J$470,0))
A30: 29 | B30: =TRIM(Audit!$B$82) | C30: =Audit!$C$82&"" | D30: =IF(B30="","",IF(C30="","Other",IFERROR(INDEX(Lists!$C$4:$C$16,MATCH(C30,Lists!$A$4:$A$16,0)),"Other"))) | E30: =IF(B30="","",IF(C30="","Other",IFERROR(INDEX(Lists!$B$4:$B$16,MATCH(C30,Lists!$A$4:$A$16,0)),"Other"))) | F30: =Audit!$G$82&"" | G30: =IFERROR(MATCH(Audit!$D$82,Lists!$E$4:$E$14,0),0) -> 0 | H30: =IF(ISNUMBER(Audit!$E$82),Audit!$E$82,"") | I30: =IF(TRIM(Audit!$F$82)="",Audit!$C$25,TRIM(Audit!$F$82)) -> 0 | J30: =IF(OR(I30=Audit!$C$25,I30=""),1,IF(AND(I30=Audit!$C$31,ISNUMBER(Audit!$J$31)),Audit!$J$31,IF(AND(I30=Audit!$C$32,ISNUMBER(Audit!$J$32)),Audit!$J$32,""))) -> 1 | K30: =IF(B30="","",IF(ISNUMBER(Audit!$I$82),Audit!$I$82,IF(G30=0,"",CHOOSE(G30,IF(ISNUMBER(Audit!$C$26),Audit!$C$26,1),1,1,1,$AF$33,$AF$30,$AF$31,1,"",1,0)))) | L30: =IF(O30=1,ROUND(MAX(H30*K30,IF(ISNUMBER(Audit!$J$82),Audit!$J$82,0)),2),"") | M30: =IF(O30=1,ROUND(L30*(1+Y30),2),"") | N30: =IF(O30=1,IF(ISNUMBER(J30),ROUND(M30*J30,2),""),"") | O30: =IF(AND(B30<>"",OR(F30="Firm",F30="Estimate",F30="If required"),ISNUMBER(H30),G30>0,G30<>11,ISNUMBER(K30)),1,0) -> 0 | P30: =IF(ISNUMBER(Audit!$L$82),Audit!$L$82,"") | Q30: =IF(B30="","",IF(OR(F30="At cost",F30="TBC"),"Not priced ("&F30&")",IF(OR(F30="Included",F30="Excluded",F30="Not applicable"),F30,IF(F30="","Status missing",IF(AND(F30="If required",NOT(ISNUMBER(H30))),"Not priced (if required)",IF(G30=0,"Basis missing",IF(G30=11,"Not priced (at cost)",IF(NOT(ISNUMBER(H30)),"Rate missing",IF(AND(G30=9,NOT(ISNUMBER(Audit!$I$82))),"Base amount missing",IF(NOT(ISNUMBER(J30)),"Exchange rate missing",IF(NOT(ISNUMBER(P30)),"Calculated — Not Independently Verified",IF(ABS(R30)<=Lists!$B$44,"Verified","Error - differs by "&TEXT(R30,"#,##0.00")&" "&I30)))))))))))) | R30: =IF(AND(O30=1,ISNUMBER(P30)),IF(ABS(P30-L30)<=ABS(P30-M30),P30-L30,P30-M30),"") | S30: =IF(AND(O30=1,ISNUMBER(Audit!$M$82),ISNUMBER(J30)),IF(H30-Audit!$M$82>0.005,ROUND((H30-Audit!$M$82)*K30*(1+Y30)*J30,2),0),0) -> 0 | T30: =Audit!$N$82&"" | U30: =IF(B30="",0,IF(COUNTIFS($B$2:$B$51,B30,$D$2:$D$51,D30)>1,1,0)) -> 0 | V30: =IF(D30="","",IFERROR(INDEX(Audit!$C$43:$C$49,MATCH(D30,Lists!$A$30:$A$36,0)),"")) | W30: =IF(AND(B30<>"",OR(F30="At cost",F30="TBC",AND(F30<>"If required",G30=11))),1,0) -> 0 | X30: =IF(B30="","",IF(T30<>"","flag",IF(F30="","status",IF(AND(G30=0,OR(F30="Firm",F30="Estimate",AND(F30="If required",ISNUMBER(H30)))),"basis",IF(AND(OR(F30="Firm",F30="Estimate"),G30<>11,NOT(ISNUMBER(H30))),"rate",IF(AND(O30=0,G30=9,OR(F30="Firm",F30="Estimate"),ISNUMBER(H30)),"base",IF(OR(C30="",C30="Unclassified"),"unclass",IF(U30=1,"dup",IF(AND(Audit!$C$19="Yes",O30=1,NOT(ISNUMBER(Audit!$M$82))),"noagree",""))))))))) | Y30: =IF(ISNUMBER(Audit!$K$82),Audit!$K$82,0) -> 0 | Z30: =IF(AND(F30="Firm",O30=1,ISNUMBER(J30)),L30*J30,0) -> 0 | AE30: Revenue tonnes | AF30: =IF(AND(ISNUMBER(Audit!$J$15),ISNUMBER(Audit!$C$15)),MAX(Audit!$J$15,Audit!$C$15/1000),IF(ISNUMBER(Audit!$J$15),Audit!$J$15,"")) | AH30: 29 | AI30: =IFERROR(SMALL($J$70:$J$470,AH30),"") | AJ30: =IF(AI30="","",MATCH(AI30,$J$70:$J$470,0))
A31: 30 | B31: =TRIM(Audit!$B$83) | C31: =Audit!$C$83&"" | D31: =IF(B31="","",IF(C31="","Other",IFERROR(INDEX(Lists!$C$4:$C$16,MATCH(C31,Lists!$A$4:$A$16,0)),"Other"))) | E31: =IF(B31="","",IF(C31="","Other",IFERROR(INDEX(Lists!$B$4:$B$16,MATCH(C31,Lists!$A$4:$A$16,0)),"Other"))) | F31: =Audit!$G$83&"" | G31: =IFERROR(MATCH(Audit!$D$83,Lists!$E$4:$E$14,0),0) -> 0 | H31: =IF(ISNUMBER(Audit!$E$83),Audit!$E$83,"") | I31: =IF(TRIM(Audit!$F$83)="",Audit!$C$25,TRIM(Audit!$F$83)) -> 0 | J31: =IF(OR(I31=Audit!$C$25,I31=""),1,IF(AND(I31=Audit!$C$31,ISNUMBER(Audit!$J$31)),Audit!$J$31,IF(AND(I31=Audit!$C$32,ISNUMBER(Audit!$J$32)),Audit!$J$32,""))) -> 1 | K31: =IF(B31="","",IF(ISNUMBER(Audit!$I$83),Audit!$I$83,IF(G31=0,"",CHOOSE(G31,IF(ISNUMBER(Audit!$C$26),Audit!$C$26,1),1,1,1,$AF$33,$AF$30,$AF$31,1,"",1,0)))) | L31: =IF(O31=1,ROUND(MAX(H31*K31,IF(ISNUMBER(Audit!$J$83),Audit!$J$83,0)),2),"") | M31: =IF(O31=1,ROUND(L31*(1+Y31),2),"") | N31: =IF(O31=1,IF(ISNUMBER(J31),ROUND(M31*J31,2),""),"") | O31: =IF(AND(B31<>"",OR(F31="Firm",F31="Estimate",F31="If required"),ISNUMBER(H31),G31>0,G31<>11,ISNUMBER(K31)),1,0) -> 0 | P31: =IF(ISNUMBER(Audit!$L$83),Audit!$L$83,"") | Q31: =IF(B31="","",IF(OR(F31="At cost",F31="TBC"),"Not priced ("&F31&")",IF(OR(F31="Included",F31="Excluded",F31="Not applicable"),F31,IF(F31="","Status missing",IF(AND(F31="If required",NOT(ISNUMBER(H31))),"Not priced (if required)",IF(G31=0,"Basis missing",IF(G31=11,"Not priced (at cost)",IF(NOT(ISNUMBER(H31)),"Rate missing",IF(AND(G31=9,NOT(ISNUMBER(Audit!$I$83))),"Base amount missing",IF(NOT(ISNUMBER(J31)),"Exchange rate missing",IF(NOT(ISNUMBER(P31)),"Calculated — Not Independently Verified",IF(ABS(R31)<=Lists!$B$44,"Verified","Error - differs by "&TEXT(R31,"#,##0.00")&" "&I31)))))))))))) | R31: =IF(AND(O31=1,ISNUMBER(P31)),IF(ABS(P31-L31)<=ABS(P31-M31),P31-L31,P31-M31),"") | S31: =IF(AND(O31=1,ISNUMBER(Audit!$M$83),ISNUMBER(J31)),IF(H31-Audit!$M$83>0.005,ROUND((H31-Audit!$M$83)*K31*(1+Y31)*J31,2),0),0) -> 0 | T31: =Audit!$N$83&"" | U31: =IF(B31="",0,IF(COUNTIFS($B$2:$B$51,B31,$D$2:$D$51,D31)>1,1,0)) -> 0 | V31: =IF(D31="","",IFERROR(INDEX(Audit!$C$43:$C$49,MATCH(D31,Lists!$A$30:$A$36,0)),"")) | W31: =IF(AND(B31<>"",OR(F31="At cost",F31="TBC",AND(F31<>"If required",G31=11))),1,0) -> 0 | X31: =IF(B31="","",IF(T31<>"","flag",IF(F31="","status",IF(AND(G31=0,OR(F31="Firm",F31="Estimate",AND(F31="If required",ISNUMBER(H31)))),"basis",IF(AND(OR(F31="Firm",F31="Estimate"),G31<>11,NOT(ISNUMBER(H31))),"rate",IF(AND(O31=0,G31=9,OR(F31="Firm",F31="Estimate"),ISNUMBER(H31)),"base",IF(OR(C31="",C31="Unclassified"),"unclass",IF(U31=1,"dup",IF(AND(Audit!$C$19="Yes",O31=1,NOT(ISNUMBER(Audit!$M$83))),"noagree",""))))))))) | Y31: =IF(ISNUMBER(Audit!$K$83),Audit!$K$83,0) -> 0 | Z31: =IF(AND(F31="Firm",O31=1,ISNUMBER(J31)),L31*J31,0) -> 0 | AE31: Chargeable kg | AF31: =IF(NOT(ISNUMBER(Audit!$C$15)),"",IF(Audit!$J$25="Air",MAX(Audit!$C$15,IF(ISNUMBER(Audit!$J$15),Audit!$J$15*1000000/AF32,0)),Audit!$C$15)) | AH31: 30 | AI31: =IFERROR(SMALL($J$70:$J$470,AH31),"") | AJ31: =IF(AI31="","",MATCH(AI31,$J$70:$J$470,0))
A32: 31 | B32: =TRIM(Audit!$B$84) | C32: =Audit!$C$84&"" | D32: =IF(B32="","",IF(C32="","Other",IFERROR(INDEX(Lists!$C$4:$C$16,MATCH(C32,Lists!$A$4:$A$16,0)),"Other"))) | E32: =IF(B32="","",IF(C32="","Other",IFERROR(INDEX(Lists!$B$4:$B$16,MATCH(C32,Lists!$A$4:$A$16,0)),"Other"))) | F32: =Audit!$G$84&"" | G32: =IFERROR(MATCH(Audit!$D$84,Lists!$E$4:$E$14,0),0) -> 0 | H32: =IF(ISNUMBER(Audit!$E$84),Audit!$E$84,"") | I32: =IF(TRIM(Audit!$F$84)="",Audit!$C$25,TRIM(Audit!$F$84)) -> 0 | J32: =IF(OR(I32=Audit!$C$25,I32=""),1,IF(AND(I32=Audit!$C$31,ISNUMBER(Audit!$J$31)),Audit!$J$31,IF(AND(I32=Audit!$C$32,ISNUMBER(Audit!$J$32)),Audit!$J$32,""))) -> 1 | K32: =IF(B32="","",IF(ISNUMBER(Audit!$I$84),Audit!$I$84,IF(G32=0,"",CHOOSE(G32,IF(ISNUMBER(Audit!$C$26),Audit!$C$26,1),1,1,1,$AF$33,$AF$30,$AF$31,1,"",1,0)))) | L32: =IF(O32=1,ROUND(MAX(H32*K32,IF(ISNUMBER(Audit!$J$84),Audit!$J$84,0)),2),"") | M32: =IF(O32=1,ROUND(L32*(1+Y32),2),"") | N32: =IF(O32=1,IF(ISNUMBER(J32),ROUND(M32*J32,2),""),"") | O32: =IF(AND(B32<>"",OR(F32="Firm",F32="Estimate",F32="If required"),ISNUMBER(H32),G32>0,G32<>11,ISNUMBER(K32)),1,0) -> 0 | P32: =IF(ISNUMBER(Audit!$L$84),Audit!$L$84,"") | Q32: =IF(B32="","",IF(OR(F32="At cost",F32="TBC"),"Not priced ("&F32&")",IF(OR(F32="Included",F32="Excluded",F32="Not applicable"),F32,IF(F32="","Status missing",IF(AND(F32="If required",NOT(ISNUMBER(H32))),"Not priced (if required)",IF(G32=0,"Basis missing",IF(G32=11,"Not priced (at cost)",IF(NOT(ISNUMBER(H32)),"Rate missing",IF(AND(G32=9,NOT(ISNUMBER(Audit!$I$84))),"Base amount missing",IF(NOT(ISNUMBER(J32)),"Exchange rate missing",IF(NOT(ISNUMBER(P32)),"Calculated — Not Independently Verified",IF(ABS(R32)<=Lists!$B$44,"Verified","Error - differs by "&TEXT(R32,"#,##0.00")&" "&I32)))))))))))) | R32: =IF(AND(O32=1,ISNUMBER(P32)),IF(ABS(P32-L32)<=ABS(P32-M32),P32-L32,P32-M32),"") | S32: =IF(AND(O32=1,ISNUMBER(Audit!$M$84),ISNUMBER(J32)),IF(H32-Audit!$M$84>0.005,ROUND((H32-Audit!$M$84)*K32*(1+Y32)*J32,2),0),0) -> 0 | T32: =Audit!$N$84&"" | U32: =IF(B32="",0,IF(COUNTIFS($B$2:$B$51,B32,$D$2:$D$51,D32)>1,1,0)) -> 0 | V32: =IF(D32="","",IFERROR(INDEX(Audit!$C$43:$C$49,MATCH(D32,Lists!$A$30:$A$36,0)),"")) | W32: =IF(AND(B32<>"",OR(F32="At cost",F32="TBC",AND(F32<>"If required",G32=11))),1,0) -> 0 | X32: =IF(B32="","",IF(T32<>"","flag",IF(F32="","status",IF(AND(G32=0,OR(F32="Firm",F32="Estimate",AND(F32="If required",ISNUMBER(H32)))),"basis",IF(AND(OR(F32="Firm",F32="Estimate"),G32<>11,NOT(ISNUMBER(H32))),"rate",IF(AND(O32=0,G32=9,OR(F32="Firm",F32="Estimate"),ISNUMBER(H32)),"base",IF(OR(C32="",C32="Unclassified"),"unclass",IF(U32=1,"dup",IF(AND(Audit!$C$19="Yes",O32=1,NOT(ISNUMBER(Audit!$M$84))),"noagree",""))))))))) | Y32: =IF(ISNUMBER(Audit!$K$84),Audit!$K$84,0) -> 0 | Z32: =IF(AND(F32="Firm",O32=1,ISNUMBER(J32)),L32*J32,0) -> 0 | AE32: Divisor used | AF32: =IF(ISNUMBER(Audit!$C$30),Audit!$C$30,Lists!$B$41) -> 6000
A33: 32 | B33: =TRIM(Audit!$B$85) | C33: =Audit!$C$85&"" | D33: =IF(B33="","",IF(C33="","Other",IFERROR(INDEX(Lists!$C$4:$C$16,MATCH(C33,Lists!$A$4:$A$16,0)),"Other"))) | E33: =IF(B33="","",IF(C33="","Other",IFERROR(INDEX(Lists!$B$4:$B$16,MATCH(C33,Lists!$A$4:$A$16,0)),"Other"))) | F33: =Audit!$G$85&"" | G33: =IFERROR(MATCH(Audit!$D$85,Lists!$E$4:$E$14,0),0) -> 0 | H33: =IF(ISNUMBER(Audit!$E$85),Audit!$E$85,"") | I33: =IF(TRIM(Audit!$F$85)="",Audit!$C$25,TRIM(Audit!$F$85)) -> 0 | J33: =IF(OR(I33=Audit!$C$25,I33=""),1,IF(AND(I33=Audit!$C$31,ISNUMBER(Audit!$J$31)),Audit!$J$31,IF(AND(I33=Audit!$C$32,ISNUMBER(Audit!$J$32)),Audit!$J$32,""))) -> 1 | K33: =IF(B33="","",IF(ISNUMBER(Audit!$I$85),Audit!$I$85,IF(G33=0,"",CHOOSE(G33,IF(ISNUMBER(Audit!$C$26),Audit!$C$26,1),1,1,1,$AF$33,$AF$30,$AF$31,1,"",1,0)))) | L33: =IF(O33=1,ROUND(MAX(H33*K33,IF(ISNUMBER(Audit!$J$85),Audit!$J$85,0)),2),"") | M33: =IF(O33=1,ROUND(L33*(1+Y33),2),"") | N33: =IF(O33=1,IF(ISNUMBER(J33),ROUND(M33*J33,2),""),"") | O33: =IF(AND(B33<>"",OR(F33="Firm",F33="Estimate",F33="If required"),ISNUMBER(H33),G33>0,G33<>11,ISNUMBER(K33)),1,0) -> 0 | P33: =IF(ISNUMBER(Audit!$L$85),Audit!$L$85,"") | Q33: =IF(B33="","",IF(OR(F33="At cost",F33="TBC"),"Not priced ("&F33&")",IF(OR(F33="Included",F33="Excluded",F33="Not applicable"),F33,IF(F33="","Status missing",IF(AND(F33="If required",NOT(ISNUMBER(H33))),"Not priced (if required)",IF(G33=0,"Basis missing",IF(G33=11,"Not priced (at cost)",IF(NOT(ISNUMBER(H33)),"Rate missing",IF(AND(G33=9,NOT(ISNUMBER(Audit!$I$85))),"Base amount missing",IF(NOT(ISNUMBER(J33)),"Exchange rate missing",IF(NOT(ISNUMBER(P33)),"Calculated — Not Independently Verified",IF(ABS(R33)<=Lists!$B$44,"Verified","Error - differs by "&TEXT(R33,"#,##0.00")&" "&I33)))))))))))) | R33: =IF(AND(O33=1,ISNUMBER(P33)),IF(ABS(P33-L33)<=ABS(P33-M33),P33-L33,P33-M33),"") | S33: =IF(AND(O33=1,ISNUMBER(Audit!$M$85),ISNUMBER(J33)),IF(H33-Audit!$M$85>0.005,ROUND((H33-Audit!$M$85)*K33*(1+Y33)*J33,2),0),0) -> 0 | T33: =Audit!$N$85&"" | U33: =IF(B33="",0,IF(COUNTIFS($B$2:$B$51,B33,$D$2:$D$51,D33)>1,1,0)) -> 0 | V33: =IF(D33="","",IFERROR(INDEX(Audit!$C$43:$C$49,MATCH(D33,Lists!$A$30:$A$36,0)),"")) | W33: =IF(AND(B33<>"",OR(F33="At cost",F33="TBC",AND(F33<>"If required",G33=11))),1,0) -> 0 | X33: =IF(B33="","",IF(T33<>"","flag",IF(F33="","status",IF(AND(G33=0,OR(F33="Firm",F33="Estimate",AND(F33="If required",ISNUMBER(H33)))),"basis",IF(AND(OR(F33="Firm",F33="Estimate"),G33<>11,NOT(ISNUMBER(H33))),"rate",IF(AND(O33=0,G33=9,OR(F33="Firm",F33="Estimate"),ISNUMBER(H33)),"base",IF(OR(C33="",C33="Unclassified"),"unclass",IF(U33=1,"dup",IF(AND(Audit!$C$19="Yes",O33=1,NOT(ISNUMBER(Audit!$M$85))),"noagree",""))))))))) | Y33: =IF(ISNUMBER(Audit!$K$85),Audit!$K$85,0) -> 0 | Z33: =IF(AND(F33="Firm",O33=1,ISNUMBER(J33)),L33*J33,0) -> 0 | AE33: CBM | AF33: =IF(ISNUMBER(Audit!$J$15),Audit!$J$15,0) -> 0
A34: 33 | B34: =TRIM(Audit!$B$86) | C34: =Audit!$C$86&"" | D34: =IF(B34="","",IF(C34="","Other",IFERROR(INDEX(Lists!$C$4:$C$16,MATCH(C34,Lists!$A$4:$A$16,0)),"Other"))) | E34: =IF(B34="","",IF(C34="","Other",IFERROR(INDEX(Lists!$B$4:$B$16,MATCH(C34,Lists!$A$4:$A$16,0)),"Other"))) | F34: =Audit!$G$86&"" | G34: =IFERROR(MATCH(Audit!$D$86,Lists!$E$4:$E$14,0),0) -> 0 | H34: =IF(ISNUMBER(Audit!$E$86),Audit!$E$86,"") | I34: =IF(TRIM(Audit!$F$86)="",Audit!$C$25,TRIM(Audit!$F$86)) -> 0 | J34: =IF(OR(I34=Audit!$C$25,I34=""),1,IF(AND(I34=Audit!$C$31,ISNUMBER(Audit!$J$31)),Audit!$J$31,IF(AND(I34=Audit!$C$32,ISNUMBER(Audit!$J$32)),Audit!$J$32,""))) -> 1 | K34: =IF(B34="","",IF(ISNUMBER(Audit!$I$86),Audit!$I$86,IF(G34=0,"",CHOOSE(G34,IF(ISNUMBER(Audit!$C$26),Audit!$C$26,1),1,1,1,$AF$33,$AF$30,$AF$31,1,"",1,0)))) | L34: =IF(O34=1,ROUND(MAX(H34*K34,IF(ISNUMBER(Audit!$J$86),Audit!$J$86,0)),2),"") | M34: =IF(O34=1,ROUND(L34*(1+Y34),2),"") | N34: =IF(O34=1,IF(ISNUMBER(J34),ROUND(M34*J34,2),""),"") | O34: =IF(AND(B34<>"",OR(F34="Firm",F34="Estimate",F34="If required"),ISNUMBER(H34),G34>0,G34<>11,ISNUMBER(K34)),1,0) -> 0 | P34: =IF(ISNUMBER(Audit!$L$86),Audit!$L$86,"") | Q34: =IF(B34="","",IF(OR(F34="At cost",F34="TBC"),"Not priced ("&F34&")",IF(OR(F34="Included",F34="Excluded",F34="Not applicable"),F34,IF(F34="","Status missing",IF(AND(F34="If required",NOT(ISNUMBER(H34))),"Not priced (if required)",IF(G34=0,"Basis missing",IF(G34=11,"Not priced (at cost)",IF(NOT(ISNUMBER(H34)),"Rate missing",IF(AND(G34=9,NOT(ISNUMBER(Audit!$I$86))),"Base amount missing",IF(NOT(ISNUMBER(J34)),"Exchange rate missing",IF(NOT(ISNUMBER(P34)),"Calculated — Not Independently Verified",IF(ABS(R34)<=Lists!$B$44,"Verified","Error - differs by "&TEXT(R34,"#,##0.00")&" "&I34)))))))))))) | R34: =IF(AND(O34=1,ISNUMBER(P34)),IF(ABS(P34-L34)<=ABS(P34-M34),P34-L34,P34-M34),"") | S34: =IF(AND(O34=1,ISNUMBER(Audit!$M$86),ISNUMBER(J34)),IF(H34-Audit!$M$86>0.005,ROUND((H34-Audit!$M$86)*K34*(1+Y34)*J34,2),0),0) -> 0 | T34: =Audit!$N$86&"" | U34: =IF(B34="",0,IF(COUNTIFS($B$2:$B$51,B34,$D$2:$D$51,D34)>1,1,0)) -> 0 | V34: =IF(D34="","",IFERROR(INDEX(Audit!$C$43:$C$49,MATCH(D34,Lists!$A$30:$A$36,0)),"")) | W34: =IF(AND(B34<>"",OR(F34="At cost",F34="TBC",AND(F34<>"If required",G34=11))),1,0) -> 0 | X34: =IF(B34="","",IF(T34<>"","flag",IF(F34="","status",IF(AND(G34=0,OR(F34="Firm",F34="Estimate",AND(F34="If required",ISNUMBER(H34)))),"basis",IF(AND(OR(F34="Firm",F34="Estimate"),G34<>11,NOT(ISNUMBER(H34))),"rate",IF(AND(O34=0,G34=9,OR(F34="Firm",F34="Estimate"),ISNUMBER(H34)),"base",IF(OR(C34="",C34="Unclassified"),"unclass",IF(U34=1,"dup",IF(AND(Audit!$C$19="Yes",O34=1,NOT(ISNUMBER(Audit!$M$86))),"noagree",""))))))))) | Y34: =IF(ISNUMBER(Audit!$K$86),Audit!$K$86,0) -> 0 | Z34: =IF(AND(F34="Firm",O34=1,ISNUMBER(J34)),L34*J34,0) -> 0 | AE34: Not started | AF34: =IF(AND(Audit!$C$23="",AF7=0),1,0) -> 1
A35: 34 | B35: =TRIM(Audit!$B$87) | C35: =Audit!$C$87&"" | D35: =IF(B35="","",IF(C35="","Other",IFERROR(INDEX(Lists!$C$4:$C$16,MATCH(C35,Lists!$A$4:$A$16,0)),"Other"))) | E35: =IF(B35="","",IF(C35="","Other",IFERROR(INDEX(Lists!$B$4:$B$16,MATCH(C35,Lists!$A$4:$A$16,0)),"Other"))) | F35: =Audit!$G$87&"" | G35: =IFERROR(MATCH(Audit!$D$87,Lists!$E$4:$E$14,0),0) -> 0 | H35: =IF(ISNUMBER(Audit!$E$87),Audit!$E$87,"") | I35: =IF(TRIM(Audit!$F$87)="",Audit!$C$25,TRIM(Audit!$F$87)) -> 0 | J35: =IF(OR(I35=Audit!$C$25,I35=""),1,IF(AND(I35=Audit!$C$31,ISNUMBER(Audit!$J$31)),Audit!$J$31,IF(AND(I35=Audit!$C$32,ISNUMBER(Audit!$J$32)),Audit!$J$32,""))) -> 1 | K35: =IF(B35="","",IF(ISNUMBER(Audit!$I$87),Audit!$I$87,IF(G35=0,"",CHOOSE(G35,IF(ISNUMBER(Audit!$C$26),Audit!$C$26,1),1,1,1,$AF$33,$AF$30,$AF$31,1,"",1,0)))) | L35: =IF(O35=1,ROUND(MAX(H35*K35,IF(ISNUMBER(Audit!$J$87),Audit!$J$87,0)),2),"") | M35: =IF(O35=1,ROUND(L35*(1+Y35),2),"") | N35: =IF(O35=1,IF(ISNUMBER(J35),ROUND(M35*J35,2),""),"") | O35: =IF(AND(B35<>"",OR(F35="Firm",F35="Estimate",F35="If required"),ISNUMBER(H35),G35>0,G35<>11,ISNUMBER(K35)),1,0) -> 0 | P35: =IF(ISNUMBER(Audit!$L$87),Audit!$L$87,"") | Q35: =IF(B35="","",IF(OR(F35="At cost",F35="TBC"),"Not priced ("&F35&")",IF(OR(F35="Included",F35="Excluded",F35="Not applicable"),F35,IF(F35="","Status missing",IF(AND(F35="If required",NOT(ISNUMBER(H35))),"Not priced (if required)",IF(G35=0,"Basis missing",IF(G35=11,"Not priced (at cost)",IF(NOT(ISNUMBER(H35)),"Rate missing",IF(AND(G35=9,NOT(ISNUMBER(Audit!$I$87))),"Base amount missing",IF(NOT(ISNUMBER(J35)),"Exchange rate missing",IF(NOT(ISNUMBER(P35)),"Calculated — Not Independently Verified",IF(ABS(R35)<=Lists!$B$44,"Verified","Error - differs by "&TEXT(R35,"#,##0.00")&" "&I35)))))))))))) | R35: =IF(AND(O35=1,ISNUMBER(P35)),IF(ABS(P35-L35)<=ABS(P35-M35),P35-L35,P35-M35),"") | S35: =IF(AND(O35=1,ISNUMBER(Audit!$M$87),ISNUMBER(J35)),IF(H35-Audit!$M$87>0.005,ROUND((H35-Audit!$M$87)*K35*(1+Y35)*J35,2),0),0) -> 0 | T35: =Audit!$N$87&"" | U35: =IF(B35="",0,IF(COUNTIFS($B$2:$B$51,B35,$D$2:$D$51,D35)>1,1,0)) -> 0 | V35: =IF(D35="","",IFERROR(INDEX(Audit!$C$43:$C$49,MATCH(D35,Lists!$A$30:$A$36,0)),"")) | W35: =IF(AND(B35<>"",OR(F35="At cost",F35="TBC",AND(F35<>"If required",G35=11))),1,0) -> 0 | X35: =IF(B35="","",IF(T35<>"","flag",IF(F35="","status",IF(AND(G35=0,OR(F35="Firm",F35="Estimate",AND(F35="If required",ISNUMBER(H35)))),"basis",IF(AND(OR(F35="Firm",F35="Estimate"),G35<>11,NOT(ISNUMBER(H35))),"rate",IF(AND(O35=0,G35=9,OR(F35="Firm",F35="Estimate"),ISNUMBER(H35)),"base",IF(OR(C35="",C35="Unclassified"),"unclass",IF(U35=1,"dup",IF(AND(Audit!$C$19="Yes",O35=1,NOT(ISNUMBER(Audit!$M$87))),"noagree",""))))))))) | Y35: =IF(ISNUMBER(Audit!$K$87),Audit!$K$87,0) -> 0 | Z35: =IF(AND(F35="Firm",O35=1,ISNUMBER(J35)),L35*J35,0) -> 0
A36: 35 | B36: =TRIM(Audit!$B$88) | C36: =Audit!$C$88&"" | D36: =IF(B36="","",IF(C36="","Other",IFERROR(INDEX(Lists!$C$4:$C$16,MATCH(C36,Lists!$A$4:$A$16,0)),"Other"))) | E36: =IF(B36="","",IF(C36="","Other",IFERROR(INDEX(Lists!$B$4:$B$16,MATCH(C36,Lists!$A$4:$A$16,0)),"Other"))) | F36: =Audit!$G$88&"" | G36: =IFERROR(MATCH(Audit!$D$88,Lists!$E$4:$E$14,0),0) -> 0 | H36: =IF(ISNUMBER(Audit!$E$88),Audit!$E$88,"") | I36: =IF(TRIM(Audit!$F$88)="",Audit!$C$25,TRIM(Audit!$F$88)) -> 0 | J36: =IF(OR(I36=Audit!$C$25,I36=""),1,IF(AND(I36=Audit!$C$31,ISNUMBER(Audit!$J$31)),Audit!$J$31,IF(AND(I36=Audit!$C$32,ISNUMBER(Audit!$J$32)),Audit!$J$32,""))) -> 1 | K36: =IF(B36="","",IF(ISNUMBER(Audit!$I$88),Audit!$I$88,IF(G36=0,"",CHOOSE(G36,IF(ISNUMBER(Audit!$C$26),Audit!$C$26,1),1,1,1,$AF$33,$AF$30,$AF$31,1,"",1,0)))) | L36: =IF(O36=1,ROUND(MAX(H36*K36,IF(ISNUMBER(Audit!$J$88),Audit!$J$88,0)),2),"") | M36: =IF(O36=1,ROUND(L36*(1+Y36),2),"") | N36: =IF(O36=1,IF(ISNUMBER(J36),ROUND(M36*J36,2),""),"") | O36: =IF(AND(B36<>"",OR(F36="Firm",F36="Estimate",F36="If required"),ISNUMBER(H36),G36>0,G36<>11,ISNUMBER(K36)),1,0) -> 0 | P36: =IF(ISNUMBER(Audit!$L$88),Audit!$L$88,"") | Q36: =IF(B36="","",IF(OR(F36="At cost",F36="TBC"),"Not priced ("&F36&")",IF(OR(F36="Included",F36="Excluded",F36="Not applicable"),F36,IF(F36="","Status missing",IF(AND(F36="If required",NOT(ISNUMBER(H36))),"Not priced (if required)",IF(G36=0,"Basis missing",IF(G36=11,"Not priced (at cost)",IF(NOT(ISNUMBER(H36)),"Rate missing",IF(AND(G36=9,NOT(ISNUMBER(Audit!$I$88))),"Base amount missing",IF(NOT(ISNUMBER(J36)),"Exchange rate missing",IF(NOT(ISNUMBER(P36)),"Calculated — Not Independently Verified",IF(ABS(R36)<=Lists!$B$44,"Verified","Error - differs by "&TEXT(R36,"#,##0.00")&" "&I36)))))))))))) | R36: =IF(AND(O36=1,ISNUMBER(P36)),IF(ABS(P36-L36)<=ABS(P36-M36),P36-L36,P36-M36),"") | S36: =IF(AND(O36=1,ISNUMBER(Audit!$M$88),ISNUMBER(J36)),IF(H36-Audit!$M$88>0.005,ROUND((H36-Audit!$M$88)*K36*(1+Y36)*J36,2),0),0) -> 0 | T36: =Audit!$N$88&"" | U36: =IF(B36="",0,IF(COUNTIFS($B$2:$B$51,B36,$D$2:$D$51,D36)>1,1,0)) -> 0 | V36: =IF(D36="","",IFERROR(INDEX(Audit!$C$43:$C$49,MATCH(D36,Lists!$A$30:$A$36,0)),"")) | W36: =IF(AND(B36<>"",OR(F36="At cost",F36="TBC",AND(F36<>"If required",G36=11))),1,0) -> 0 | X36: =IF(B36="","",IF(T36<>"","flag",IF(F36="","status",IF(AND(G36=0,OR(F36="Firm",F36="Estimate",AND(F36="If required",ISNUMBER(H36)))),"basis",IF(AND(OR(F36="Firm",F36="Estimate"),G36<>11,NOT(ISNUMBER(H36))),"rate",IF(AND(O36=0,G36=9,OR(F36="Firm",F36="Estimate"),ISNUMBER(H36)),"base",IF(OR(C36="",C36="Unclassified"),"unclass",IF(U36=1,"dup",IF(AND(Audit!$C$19="Yes",O36=1,NOT(ISNUMBER(Audit!$M$88))),"noagree",""))))))))) | Y36: =IF(ISNUMBER(Audit!$K$88),Audit!$K$88,0) -> 0 | Z36: =IF(AND(F36="Firm",O36=1,ISNUMBER(J36)),L36*J36,0) -> 0
A37: 36 | B37: =TRIM(Audit!$B$89) | C37: =Audit!$C$89&"" | D37: =IF(B37="","",IF(C37="","Other",IFERROR(INDEX(Lists!$C$4:$C$16,MATCH(C37,Lists!$A$4:$A$16,0)),"Other"))) | E37: =IF(B37="","",IF(C37="","Other",IFERROR(INDEX(Lists!$B$4:$B$16,MATCH(C37,Lists!$A$4:$A$16,0)),"Other"))) | F37: =Audit!$G$89&"" | G37: =IFERROR(MATCH(Audit!$D$89,Lists!$E$4:$E$14,0),0) -> 0 | H37: =IF(ISNUMBER(Audit!$E$89),Audit!$E$89,"") | I37: =IF(TRIM(Audit!$F$89)="",Audit!$C$25,TRIM(Audit!$F$89)) -> 0 | J37: =IF(OR(I37=Audit!$C$25,I37=""),1,IF(AND(I37=Audit!$C$31,ISNUMBER(Audit!$J$31)),Audit!$J$31,IF(AND(I37=Audit!$C$32,ISNUMBER(Audit!$J$32)),Audit!$J$32,""))) -> 1 | K37: =IF(B37="","",IF(ISNUMBER(Audit!$I$89),Audit!$I$89,IF(G37=0,"",CHOOSE(G37,IF(ISNUMBER(Audit!$C$26),Audit!$C$26,1),1,1,1,$AF$33,$AF$30,$AF$31,1,"",1,0)))) | L37: =IF(O37=1,ROUND(MAX(H37*K37,IF(ISNUMBER(Audit!$J$89),Audit!$J$89,0)),2),"") | M37: =IF(O37=1,ROUND(L37*(1+Y37),2),"") | N37: =IF(O37=1,IF(ISNUMBER(J37),ROUND(M37*J37,2),""),"") | O37: =IF(AND(B37<>"",OR(F37="Firm",F37="Estimate",F37="If required"),ISNUMBER(H37),G37>0,G37<>11,ISNUMBER(K37)),1,0) -> 0 | P37: =IF(ISNUMBER(Audit!$L$89),Audit!$L$89,"") | Q37: =IF(B37="","",IF(OR(F37="At cost",F37="TBC"),"Not priced ("&F37&")",IF(OR(F37="Included",F37="Excluded",F37="Not applicable"),F37,IF(F37="","Status missing",IF(AND(F37="If required",NOT(ISNUMBER(H37))),"Not priced (if required)",IF(G37=0,"Basis missing",IF(G37=11,"Not priced (at cost)",IF(NOT(ISNUMBER(H37)),"Rate missing",IF(AND(G37=9,NOT(ISNUMBER(Audit!$I$89))),"Base amount missing",IF(NOT(ISNUMBER(J37)),"Exchange rate missing",IF(NOT(ISNUMBER(P37)),"Calculated — Not Independently Verified",IF(ABS(R37)<=Lists!$B$44,"Verified","Error - differs by "&TEXT(R37,"#,##0.00")&" "&I37)))))))))))) | R37: =IF(AND(O37=1,ISNUMBER(P37)),IF(ABS(P37-L37)<=ABS(P37-M37),P37-L37,P37-M37),"") | S37: =IF(AND(O37=1,ISNUMBER(Audit!$M$89),ISNUMBER(J37)),IF(H37-Audit!$M$89>0.005,ROUND((H37-Audit!$M$89)*K37*(1+Y37)*J37,2),0),0) -> 0 | T37: =Audit!$N$89&"" | U37: =IF(B37="",0,IF(COUNTIFS($B$2:$B$51,B37,$D$2:$D$51,D37)>1,1,0)) -> 0 | V37: =IF(D37="","",IFERROR(INDEX(Audit!$C$43:$C$49,MATCH(D37,Lists!$A$30:$A$36,0)),"")) | W37: =IF(AND(B37<>"",OR(F37="At cost",F37="TBC",AND(F37<>"If required",G37=11))),1,0) -> 0 | X37: =IF(B37="","",IF(T37<>"","flag",IF(F37="","status",IF(AND(G37=0,OR(F37="Firm",F37="Estimate",AND(F37="If required",ISNUMBER(H37)))),"basis",IF(AND(OR(F37="Firm",F37="Estimate"),G37<>11,NOT(ISNUMBER(H37))),"rate",IF(AND(O37=0,G37=9,OR(F37="Firm",F37="Estimate"),ISNUMBER(H37)),"base",IF(OR(C37="",C37="Unclassified"),"unclass",IF(U37=1,"dup",IF(AND(Audit!$C$19="Yes",O37=1,NOT(ISNUMBER(Audit!$M$89))),"noagree",""))))))))) | Y37: =IF(ISNUMBER(Audit!$K$89),Audit!$K$89,0) -> 0 | Z37: =IF(AND(F37="Firm",O37=1,ISNUMBER(J37)),L37*J37,0) -> 0
A38: 37 | B38: =TRIM(Audit!$B$90) | C38: =Audit!$C$90&"" | D38: =IF(B38="","",IF(C38="","Other",IFERROR(INDEX(Lists!$C$4:$C$16,MATCH(C38,Lists!$A$4:$A$16,0)),"Other"))) | E38: =IF(B38="","",IF(C38="","Other",IFERROR(INDEX(Lists!$B$4:$B$16,MATCH(C38,Lists!$A$4:$A$16,0)),"Other"))) | F38: =Audit!$G$90&"" | G38: =IFERROR(MATCH(Audit!$D$90,Lists!$E$4:$E$14,0),0) -> 0 | H38: =IF(ISNUMBER(Audit!$E$90),Audit!$E$90,"") | I38: =IF(TRIM(Audit!$F$90)="",Audit!$C$25,TRIM(Audit!$F$90)) -> 0 | J38: =IF(OR(I38=Audit!$C$25,I38=""),1,IF(AND(I38=Audit!$C$31,ISNUMBER(Audit!$J$31)),Audit!$J$31,IF(AND(I38=Audit!$C$32,ISNUMBER(Audit!$J$32)),Audit!$J$32,""))) -> 1 | K38: =IF(B38="","",IF(ISNUMBER(Audit!$I$90),Audit!$I$90,IF(G38=0,"",CHOOSE(G38,IF(ISNUMBER(Audit!$C$26),Audit!$C$26,1),1,1,1,$AF$33,$AF$30,$AF$31,1,"",1,0)))) | L38: =IF(O38=1,ROUND(MAX(H38*K38,IF(ISNUMBER(Audit!$J$90),Audit!$J$90,0)),2),"") | M38: =IF(O38=1,ROUND(L38*(1+Y38),2),"") | N38: =IF(O38=1,IF(ISNUMBER(J38),ROUND(M38*J38,2),""),"") | O38: =IF(AND(B38<>"",OR(F38="Firm",F38="Estimate",F38="If required"),ISNUMBER(H38),G38>0,G38<>11,ISNUMBER(K38)),1,0) -> 0 | P38: =IF(ISNUMBER(Audit!$L$90),Audit!$L$90,"") | Q38: =IF(B38="","",IF(OR(F38="At cost",F38="TBC"),"Not priced ("&F38&")",IF(OR(F38="Included",F38="Excluded",F38="Not applicable"),F38,IF(F38="","Status missing",IF(AND(F38="If required",NOT(ISNUMBER(H38))),"Not priced (if required)",IF(G38=0,"Basis missing",IF(G38=11,"Not priced (at cost)",IF(NOT(ISNUMBER(H38)),"Rate missing",IF(AND(G38=9,NOT(ISNUMBER(Audit!$I$90))),"Base amount missing",IF(NOT(ISNUMBER(J38)),"Exchange rate missing",IF(NOT(ISNUMBER(P38)),"Calculated — Not Independently Verified",IF(ABS(R38)<=Lists!$B$44,"Verified","Error - differs by "&TEXT(R38,"#,##0.00")&" "&I38)))))))))))) | R38: =IF(AND(O38=1,ISNUMBER(P38)),IF(ABS(P38-L38)<=ABS(P38-M38),P38-L38,P38-M38),"") | S38: =IF(AND(O38=1,ISNUMBER(Audit!$M$90),ISNUMBER(J38)),IF(H38-Audit!$M$90>0.005,ROUND((H38-Audit!$M$90)*K38*(1+Y38)*J38,2),0),0) -> 0 | T38: =Audit!$N$90&"" | U38: =IF(B38="",0,IF(COUNTIFS($B$2:$B$51,B38,$D$2:$D$51,D38)>1,1,0)) -> 0 | V38: =IF(D38="","",IFERROR(INDEX(Audit!$C$43:$C$49,MATCH(D38,Lists!$A$30:$A$36,0)),"")) | W38: =IF(AND(B38<>"",OR(F38="At cost",F38="TBC",AND(F38<>"If required",G38=11))),1,0) -> 0 | X38: =IF(B38="","",IF(T38<>"","flag",IF(F38="","status",IF(AND(G38=0,OR(F38="Firm",F38="Estimate",AND(F38="If required",ISNUMBER(H38)))),"basis",IF(AND(OR(F38="Firm",F38="Estimate"),G38<>11,NOT(ISNUMBER(H38))),"rate",IF(AND(O38=0,G38=9,OR(F38="Firm",F38="Estimate"),ISNUMBER(H38)),"base",IF(OR(C38="",C38="Unclassified"),"unclass",IF(U38=1,"dup",IF(AND(Audit!$C$19="Yes",O38=1,NOT(ISNUMBER(Audit!$M$90))),"noagree",""))))))))) | Y38: =IF(ISNUMBER(Audit!$K$90),Audit!$K$90,0) -> 0 | Z38: =IF(AND(F38="Firm",O38=1,ISNUMBER(J38)),L38*J38,0) -> 0
A39: 38 | B39: =TRIM(Audit!$B$91) | C39: =Audit!$C$91&"" | D39: =IF(B39="","",IF(C39="","Other",IFERROR(INDEX(Lists!$C$4:$C$16,MATCH(C39,Lists!$A$4:$A$16,0)),"Other"))) | E39: =IF(B39="","",IF(C39="","Other",IFERROR(INDEX(Lists!$B$4:$B$16,MATCH(C39,Lists!$A$4:$A$16,0)),"Other"))) | F39: =Audit!$G$91&"" | G39: =IFERROR(MATCH(Audit!$D$91,Lists!$E$4:$E$14,0),0) -> 0 | H39: =IF(ISNUMBER(Audit!$E$91),Audit!$E$91,"") | I39: =IF(TRIM(Audit!$F$91)="",Audit!$C$25,TRIM(Audit!$F$91)) -> 0 | J39: =IF(OR(I39=Audit!$C$25,I39=""),1,IF(AND(I39=Audit!$C$31,ISNUMBER(Audit!$J$31)),Audit!$J$31,IF(AND(I39=Audit!$C$32,ISNUMBER(Audit!$J$32)),Audit!$J$32,""))) -> 1 | K39: =IF(B39="","",IF(ISNUMBER(Audit!$I$91),Audit!$I$91,IF(G39=0,"",CHOOSE(G39,IF(ISNUMBER(Audit!$C$26),Audit!$C$26,1),1,1,1,$AF$33,$AF$30,$AF$31,1,"",1,0)))) | L39: =IF(O39=1,ROUND(MAX(H39*K39,IF(ISNUMBER(Audit!$J$91),Audit!$J$91,0)),2),"") | M39: =IF(O39=1,ROUND(L39*(1+Y39),2),"") | N39: =IF(O39=1,IF(ISNUMBER(J39),ROUND(M39*J39,2),""),"") | O39: =IF(AND(B39<>"",OR(F39="Firm",F39="Estimate",F39="If required"),ISNUMBER(H39),G39>0,G39<>11,ISNUMBER(K39)),1,0) -> 0 | P39: =IF(ISNUMBER(Audit!$L$91),Audit!$L$91,"") | Q39: =IF(B39="","",IF(OR(F39="At cost",F39="TBC"),"Not priced ("&F39&")",IF(OR(F39="Included",F39="Excluded",F39="Not applicable"),F39,IF(F39="","Status missing",IF(AND(F39="If required",NOT(ISNUMBER(H39))),"Not priced (if required)",IF(G39=0,"Basis missing",IF(G39=11,"Not priced (at cost)",IF(NOT(ISNUMBER(H39)),"Rate missing",IF(AND(G39=9,NOT(ISNUMBER(Audit!$I$91))),"Base amount missing",IF(NOT(ISNUMBER(J39)),"Exchange rate missing",IF(NOT(ISNUMBER(P39)),"Calculated — Not Independently Verified",IF(ABS(R39)<=Lists!$B$44,"Verified","Error - differs by "&TEXT(R39,"#,##0.00")&" "&I39)))))))))))) | R39: =IF(AND(O39=1,ISNUMBER(P39)),IF(ABS(P39-L39)<=ABS(P39-M39),P39-L39,P39-M39),"") | S39: =IF(AND(O39=1,ISNUMBER(Audit!$M$91),ISNUMBER(J39)),IF(H39-Audit!$M$91>0.005,ROUND((H39-Audit!$M$91)*K39*(1+Y39)*J39,2),0),0) -> 0 | T39: =Audit!$N$91&"" | U39: =IF(B39="",0,IF(COUNTIFS($B$2:$B$51,B39,$D$2:$D$51,D39)>1,1,0)) -> 0 | V39: =IF(D39="","",IFERROR(INDEX(Audit!$C$43:$C$49,MATCH(D39,Lists!$A$30:$A$36,0)),"")) | W39: =IF(AND(B39<>"",OR(F39="At cost",F39="TBC",AND(F39<>"If required",G39=11))),1,0) -> 0 | X39: =IF(B39="","",IF(T39<>"","flag",IF(F39="","status",IF(AND(G39=0,OR(F39="Firm",F39="Estimate",AND(F39="If required",ISNUMBER(H39)))),"basis",IF(AND(OR(F39="Firm",F39="Estimate"),G39<>11,NOT(ISNUMBER(H39))),"rate",IF(AND(O39=0,G39=9,OR(F39="Firm",F39="Estimate"),ISNUMBER(H39)),"base",IF(OR(C39="",C39="Unclassified"),"unclass",IF(U39=1,"dup",IF(AND(Audit!$C$19="Yes",O39=1,NOT(ISNUMBER(Audit!$M$91))),"noagree",""))))))))) | Y39: =IF(ISNUMBER(Audit!$K$91),Audit!$K$91,0) -> 0 | Z39: =IF(AND(F39="Firm",O39=1,ISNUMBER(J39)),L39*J39,0) -> 0
A40: 39 | B40: =TRIM(Audit!$B$92) | C40: =Audit!$C$92&"" | D40: =IF(B40="","",IF(C40="","Other",IFERROR(INDEX(Lists!$C$4:$C$16,MATCH(C40,Lists!$A$4:$A$16,0)),"Other"))) | E40: =IF(B40="","",IF(C40="","Other",IFERROR(INDEX(Lists!$B$4:$B$16,MATCH(C40,Lists!$A$4:$A$16,0)),"Other"))) | F40: =Audit!$G$92&"" | G40: =IFERROR(MATCH(Audit!$D$92,Lists!$E$4:$E$14,0),0) -> 0 | H40: =IF(ISNUMBER(Audit!$E$92),Audit!$E$92,"") | I40: =IF(TRIM(Audit!$F$92)="",Audit!$C$25,TRIM(Audit!$F$92)) -> 0 | J40: =IF(OR(I40=Audit!$C$25,I40=""),1,IF(AND(I40=Audit!$C$31,ISNUMBER(Audit!$J$31)),Audit!$J$31,IF(AND(I40=Audit!$C$32,ISNUMBER(Audit!$J$32)),Audit!$J$32,""))) -> 1 | K40: =IF(B40="","",IF(ISNUMBER(Audit!$I$92),Audit!$I$92,IF(G40=0,"",CHOOSE(G40,IF(ISNUMBER(Audit!$C$26),Audit!$C$26,1),1,1,1,$AF$33,$AF$30,$AF$31,1,"",1,0)))) | L40: =IF(O40=1,ROUND(MAX(H40*K40,IF(ISNUMBER(Audit!$J$92),Audit!$J$92,0)),2),"") | M40: =IF(O40=1,ROUND(L40*(1+Y40),2),"") | N40: =IF(O40=1,IF(ISNUMBER(J40),ROUND(M40*J40,2),""),"") | O40: =IF(AND(B40<>"",OR(F40="Firm",F40="Estimate",F40="If required"),ISNUMBER(H40),G40>0,G40<>11,ISNUMBER(K40)),1,0) -> 0 | P40: =IF(ISNUMBER(Audit!$L$92),Audit!$L$92,"") | Q40: =IF(B40="","",IF(OR(F40="At cost",F40="TBC"),"Not priced ("&F40&")",IF(OR(F40="Included",F40="Excluded",F40="Not applicable"),F40,IF(F40="","Status missing",IF(AND(F40="If required",NOT(ISNUMBER(H40))),"Not priced (if required)",IF(G40=0,"Basis missing",IF(G40=11,"Not priced (at cost)",IF(NOT(ISNUMBER(H40)),"Rate missing",IF(AND(G40=9,NOT(ISNUMBER(Audit!$I$92))),"Base amount missing",IF(NOT(ISNUMBER(J40)),"Exchange rate missing",IF(NOT(ISNUMBER(P40)),"Calculated — Not Independently Verified",IF(ABS(R40)<=Lists!$B$44,"Verified","Error - differs by "&TEXT(R40,"#,##0.00")&" "&I40)))))))))))) | R40: =IF(AND(O40=1,ISNUMBER(P40)),IF(ABS(P40-L40)<=ABS(P40-M40),P40-L40,P40-M40),"") | S40: =IF(AND(O40=1,ISNUMBER(Audit!$M$92),ISNUMBER(J40)),IF(H40-Audit!$M$92>0.005,ROUND((H40-Audit!$M$92)*K40*(1+Y40)*J40,2),0),0) -> 0 | T40: =Audit!$N$92&"" | U40: =IF(B40="",0,IF(COUNTIFS($B$2:$B$51,B40,$D$2:$D$51,D40)>1,1,0)) -> 0 | V40: =IF(D40="","",IFERROR(INDEX(Audit!$C$43:$C$49,MATCH(D40,Lists!$A$30:$A$36,0)),"")) | W40: =IF(AND(B40<>"",OR(F40="At cost",F40="TBC",AND(F40<>"If required",G40=11))),1,0) -> 0 | X40: =IF(B40="","",IF(T40<>"","flag",IF(F40="","status",IF(AND(G40=0,OR(F40="Firm",F40="Estimate",AND(F40="If required",ISNUMBER(H40)))),"basis",IF(AND(OR(F40="Firm",F40="Estimate"),G40<>11,NOT(ISNUMBER(H40))),"rate",IF(AND(O40=0,G40=9,OR(F40="Firm",F40="Estimate"),ISNUMBER(H40)),"base",IF(OR(C40="",C40="Unclassified"),"unclass",IF(U40=1,"dup",IF(AND(Audit!$C$19="Yes",O40=1,NOT(ISNUMBER(Audit!$M$92))),"noagree",""))))))))) | Y40: =IF(ISNUMBER(Audit!$K$92),Audit!$K$92,0) -> 0 | Z40: =IF(AND(F40="Firm",O40=1,ISNUMBER(J40)),L40*J40,0) -> 0
A41: 40 | B41: =TRIM(Audit!$B$93) | C41: =Audit!$C$93&"" | D41: =IF(B41="","",IF(C41="","Other",IFERROR(INDEX(Lists!$C$4:$C$16,MATCH(C41,Lists!$A$4:$A$16,0)),"Other"))) | E41: =IF(B41="","",IF(C41="","Other",IFERROR(INDEX(Lists!$B$4:$B$16,MATCH(C41,Lists!$A$4:$A$16,0)),"Other"))) | F41: =Audit!$G$93&"" | G41: =IFERROR(MATCH(Audit!$D$93,Lists!$E$4:$E$14,0),0) -> 0 | H41: =IF(ISNUMBER(Audit!$E$93),Audit!$E$93,"") | I41: =IF(TRIM(Audit!$F$93)="",Audit!$C$25,TRIM(Audit!$F$93)) -> 0 | J41: =IF(OR(I41=Audit!$C$25,I41=""),1,IF(AND(I41=Audit!$C$31,ISNUMBER(Audit!$J$31)),Audit!$J$31,IF(AND(I41=Audit!$C$32,ISNUMBER(Audit!$J$32)),Audit!$J$32,""))) -> 1 | K41: =IF(B41="","",IF(ISNUMBER(Audit!$I$93),Audit!$I$93,IF(G41=0,"",CHOOSE(G41,IF(ISNUMBER(Audit!$C$26),Audit!$C$26,1),1,1,1,$AF$33,$AF$30,$AF$31,1,"",1,0)))) | L41: =IF(O41=1,ROUND(MAX(H41*K41,IF(ISNUMBER(Audit!$J$93),Audit!$J$93,0)),2),"") | M41: =IF(O41=1,ROUND(L41*(1+Y41),2),"") | N41: =IF(O41=1,IF(ISNUMBER(J41),ROUND(M41*J41,2),""),"") | O41: =IF(AND(B41<>"",OR(F41="Firm",F41="Estimate",F41="If required"),ISNUMBER(H41),G41>0,G41<>11,ISNUMBER(K41)),1,0) -> 0 | P41: =IF(ISNUMBER(Audit!$L$93),Audit!$L$93,"") | Q41: =IF(B41="","",IF(OR(F41="At cost",F41="TBC"),"Not priced ("&F41&")",IF(OR(F41="Included",F41="Excluded",F41="Not applicable"),F41,IF(F41="","Status missing",IF(AND(F41="If required",NOT(ISNUMBER(H41))),"Not priced (if required)",IF(G41=0,"Basis missing",IF(G41=11,"Not priced (at cost)",IF(NOT(ISNUMBER(H41)),"Rate missing",IF(AND(G41=9,NOT(ISNUMBER(Audit!$I$93))),"Base amount missing",IF(NOT(ISNUMBER(J41)),"Exchange rate missing",IF(NOT(ISNUMBER(P41)),"Calculated — Not Independently Verified",IF(ABS(R41)<=Lists!$B$44,"Verified","Error - differs by "&TEXT(R41,"#,##0.00")&" "&I41)))))))))))) | R41: =IF(AND(O41=1,ISNUMBER(P41)),IF(ABS(P41-L41)<=ABS(P41-M41),P41-L41,P41-M41),"") | S41: =IF(AND(O41=1,ISNUMBER(Audit!$M$93),ISNUMBER(J41)),IF(H41-Audit!$M$93>0.005,ROUND((H41-Audit!$M$93)*K41*(1+Y41)*J41,2),0),0) -> 0 | T41: =Audit!$N$93&"" | U41: =IF(B41="",0,IF(COUNTIFS($B$2:$B$51,B41,$D$2:$D$51,D41)>1,1,0)) -> 0 | V41: =IF(D41="","",IFERROR(INDEX(Audit!$C$43:$C$49,MATCH(D41,Lists!$A$30:$A$36,0)),"")) | W41: =IF(AND(B41<>"",OR(F41="At cost",F41="TBC",AND(F41<>"If required",G41=11))),1,0) -> 0 | X41: =IF(B41="","",IF(T41<>"","flag",IF(F41="","status",IF(AND(G41=0,OR(F41="Firm",F41="Estimate",AND(F41="If required",ISNUMBER(H41)))),"basis",IF(AND(OR(F41="Firm",F41="Estimate"),G41<>11,NOT(ISNUMBER(H41))),"rate",IF(AND(O41=0,G41=9,OR(F41="Firm",F41="Estimate"),ISNUMBER(H41)),"base",IF(OR(C41="",C41="Unclassified"),"unclass",IF(U41=1,"dup",IF(AND(Audit!$C$19="Yes",O41=1,NOT(ISNUMBER(Audit!$M$93))),"noagree",""))))))))) | Y41: =IF(ISNUMBER(Audit!$K$93),Audit!$K$93,0) -> 0 | Z41: =IF(AND(F41="Firm",O41=1,ISNUMBER(J41)),L41*J41,0) -> 0
A42: 41 | B42: =TRIM(Audit!$B$94) | C42: =Audit!$C$94&"" | D42: =IF(B42="","",IF(C42="","Other",IFERROR(INDEX(Lists!$C$4:$C$16,MATCH(C42,Lists!$A$4:$A$16,0)),"Other"))) | E42: =IF(B42="","",IF(C42="","Other",IFERROR(INDEX(Lists!$B$4:$B$16,MATCH(C42,Lists!$A$4:$A$16,0)),"Other"))) | F42: =Audit!$G$94&"" | G42: =IFERROR(MATCH(Audit!$D$94,Lists!$E$4:$E$14,0),0) -> 0 | H42: =IF(ISNUMBER(Audit!$E$94),Audit!$E$94,"") | I42: =IF(TRIM(Audit!$F$94)="",Audit!$C$25,TRIM(Audit!$F$94)) -> 0 | J42: =IF(OR(I42=Audit!$C$25,I42=""),1,IF(AND(I42=Audit!$C$31,ISNUMBER(Audit!$J$31)),Audit!$J$31,IF(AND(I42=Audit!$C$32,ISNUMBER(Audit!$J$32)),Audit!$J$32,""))) -> 1 | K42: =IF(B42="","",IF(ISNUMBER(Audit!$I$94),Audit!$I$94,IF(G42=0,"",CHOOSE(G42,IF(ISNUMBER(Audit!$C$26),Audit!$C$26,1),1,1,1,$AF$33,$AF$30,$AF$31,1,"",1,0)))) | L42: =IF(O42=1,ROUND(MAX(H42*K42,IF(ISNUMBER(Audit!$J$94),Audit!$J$94,0)),2),"") | M42: =IF(O42=1,ROUND(L42*(1+Y42),2),"") | N42: =IF(O42=1,IF(ISNUMBER(J42),ROUND(M42*J42,2),""),"") | O42: =IF(AND(B42<>"",OR(F42="Firm",F42="Estimate",F42="If required"),ISNUMBER(H42),G42>0,G42<>11,ISNUMBER(K42)),1,0) -> 0 | P42: =IF(ISNUMBER(Audit!$L$94),Audit!$L$94,"") | Q42: =IF(B42="","",IF(OR(F42="At cost",F42="TBC"),"Not priced ("&F42&")",IF(OR(F42="Included",F42="Excluded",F42="Not applicable"),F42,IF(F42="","Status missing",IF(AND(F42="If required",NOT(ISNUMBER(H42))),"Not priced (if required)",IF(G42=0,"Basis missing",IF(G42=11,"Not priced (at cost)",IF(NOT(ISNUMBER(H42)),"Rate missing",IF(AND(G42=9,NOT(ISNUMBER(Audit!$I$94))),"Base amount missing",IF(NOT(ISNUMBER(J42)),"Exchange rate missing",IF(NOT(ISNUMBER(P42)),"Calculated — Not Independently Verified",IF(ABS(R42)<=Lists!$B$44,"Verified","Error - differs by "&TEXT(R42,"#,##0.00")&" "&I42)))))))))))) | R42: =IF(AND(O42=1,ISNUMBER(P42)),IF(ABS(P42-L42)<=ABS(P42-M42),P42-L42,P42-M42),"") | S42: =IF(AND(O42=1,ISNUMBER(Audit!$M$94),ISNUMBER(J42)),IF(H42-Audit!$M$94>0.005,ROUND((H42-Audit!$M$94)*K42*(1+Y42)*J42,2),0),0) -> 0 | T42: =Audit!$N$94&"" | U42: =IF(B42="",0,IF(COUNTIFS($B$2:$B$51,B42,$D$2:$D$51,D42)>1,1,0)) -> 0 | V42: =IF(D42="","",IFERROR(INDEX(Audit!$C$43:$C$49,MATCH(D42,Lists!$A$30:$A$36,0)),"")) | W42: =IF(AND(B42<>"",OR(F42="At cost",F42="TBC",AND(F42<>"If required",G42=11))),1,0) -> 0 | X42: =IF(B42="","",IF(T42<>"","flag",IF(F42="","status",IF(AND(G42=0,OR(F42="Firm",F42="Estimate",AND(F42="If required",ISNUMBER(H42)))),"basis",IF(AND(OR(F42="Firm",F42="Estimate"),G42<>11,NOT(ISNUMBER(H42))),"rate",IF(AND(O42=0,G42=9,OR(F42="Firm",F42="Estimate"),ISNUMBER(H42)),"base",IF(OR(C42="",C42="Unclassified"),"unclass",IF(U42=1,"dup",IF(AND(Audit!$C$19="Yes",O42=1,NOT(ISNUMBER(Audit!$M$94))),"noagree",""))))))))) | Y42: =IF(ISNUMBER(Audit!$K$94),Audit!$K$94,0) -> 0 | Z42: =IF(AND(F42="Firm",O42=1,ISNUMBER(J42)),L42*J42,0) -> 0
A43: 42 | B43: =TRIM(Audit!$B$95) | C43: =Audit!$C$95&"" | D43: =IF(B43="","",IF(C43="","Other",IFERROR(INDEX(Lists!$C$4:$C$16,MATCH(C43,Lists!$A$4:$A$16,0)),"Other"))) | E43: =IF(B43="","",IF(C43="","Other",IFERROR(INDEX(Lists!$B$4:$B$16,MATCH(C43,Lists!$A$4:$A$16,0)),"Other"))) | F43: =Audit!$G$95&"" | G43: =IFERROR(MATCH(Audit!$D$95,Lists!$E$4:$E$14,0),0) -> 0 | H43: =IF(ISNUMBER(Audit!$E$95),Audit!$E$95,"") | I43: =IF(TRIM(Audit!$F$95)="",Audit!$C$25,TRIM(Audit!$F$95)) -> 0 | J43: =IF(OR(I43=Audit!$C$25,I43=""),1,IF(AND(I43=Audit!$C$31,ISNUMBER(Audit!$J$31)),Audit!$J$31,IF(AND(I43=Audit!$C$32,ISNUMBER(Audit!$J$32)),Audit!$J$32,""))) -> 1 | K43: =IF(B43="","",IF(ISNUMBER(Audit!$I$95),Audit!$I$95,IF(G43=0,"",CHOOSE(G43,IF(ISNUMBER(Audit!$C$26),Audit!$C$26,1),1,1,1,$AF$33,$AF$30,$AF$31,1,"",1,0)))) | L43: =IF(O43=1,ROUND(MAX(H43*K43,IF(ISNUMBER(Audit!$J$95),Audit!$J$95,0)),2),"") | M43: =IF(O43=1,ROUND(L43*(1+Y43),2),"") | N43: =IF(O43=1,IF(ISNUMBER(J43),ROUND(M43*J43,2),""),"") | O43: =IF(AND(B43<>"",OR(F43="Firm",F43="Estimate",F43="If required"),ISNUMBER(H43),G43>0,G43<>11,ISNUMBER(K43)),1,0) -> 0 | P43: =IF(ISNUMBER(Audit!$L$95),Audit!$L$95,"") | Q43: =IF(B43="","",IF(OR(F43="At cost",F43="TBC"),"Not priced ("&F43&")",IF(OR(F43="Included",F43="Excluded",F43="Not applicable"),F43,IF(F43="","Status missing",IF(AND(F43="If required",NOT(ISNUMBER(H43))),"Not priced (if required)",IF(G43=0,"Basis missing",IF(G43=11,"Not priced (at cost)",IF(NOT(ISNUMBER(H43)),"Rate missing",IF(AND(G43=9,NOT(ISNUMBER(Audit!$I$95))),"Base amount missing",IF(NOT(ISNUMBER(J43)),"Exchange rate missing",IF(NOT(ISNUMBER(P43)),"Calculated — Not Independently Verified",IF(ABS(R43)<=Lists!$B$44,"Verified","Error - differs by "&TEXT(R43,"#,##0.00")&" "&I43)))))))))))) | R43: =IF(AND(O43=1,ISNUMBER(P43)),IF(ABS(P43-L43)<=ABS(P43-M43),P43-L43,P43-M43),"") | S43: =IF(AND(O43=1,ISNUMBER(Audit!$M$95),ISNUMBER(J43)),IF(H43-Audit!$M$95>0.005,ROUND((H43-Audit!$M$95)*K43*(1+Y43)*J43,2),0),0) -> 0 | T43: =Audit!$N$95&"" | U43: =IF(B43="",0,IF(COUNTIFS($B$2:$B$51,B43,$D$2:$D$51,D43)>1,1,0)) -> 0 | V43: =IF(D43="","",IFERROR(INDEX(Audit!$C$43:$C$49,MATCH(D43,Lists!$A$30:$A$36,0)),"")) | W43: =IF(AND(B43<>"",OR(F43="At cost",F43="TBC",AND(F43<>"If required",G43=11))),1,0) -> 0 | X43: =IF(B43="","",IF(T43<>"","flag",IF(F43="","status",IF(AND(G43=0,OR(F43="Firm",F43="Estimate",AND(F43="If required",ISNUMBER(H43)))),"basis",IF(AND(OR(F43="Firm",F43="Estimate"),G43<>11,NOT(ISNUMBER(H43))),"rate",IF(AND(O43=0,G43=9,OR(F43="Firm",F43="Estimate"),ISNUMBER(H43)),"base",IF(OR(C43="",C43="Unclassified"),"unclass",IF(U43=1,"dup",IF(AND(Audit!$C$19="Yes",O43=1,NOT(ISNUMBER(Audit!$M$95))),"noagree",""))))))))) | Y43: =IF(ISNUMBER(Audit!$K$95),Audit!$K$95,0) -> 0 | Z43: =IF(AND(F43="Firm",O43=1,ISNUMBER(J43)),L43*J43,0) -> 0
A44: 43 | B44: =TRIM(Audit!$B$96) | C44: =Audit!$C$96&"" | D44: =IF(B44="","",IF(C44="","Other",IFERROR(INDEX(Lists!$C$4:$C$16,MATCH(C44,Lists!$A$4:$A$16,0)),"Other"))) | E44: =IF(B44="","",IF(C44="","Other",IFERROR(INDEX(Lists!$B$4:$B$16,MATCH(C44,Lists!$A$4:$A$16,0)),"Other"))) | F44: =Audit!$G$96&"" | G44: =IFERROR(MATCH(Audit!$D$96,Lists!$E$4:$E$14,0),0) -> 0 | H44: =IF(ISNUMBER(Audit!$E$96),Audit!$E$96,"") | I44: =IF(TRIM(Audit!$F$96)="",Audit!$C$25,TRIM(Audit!$F$96)) -> 0 | J44: =IF(OR(I44=Audit!$C$25,I44=""),1,IF(AND(I44=Audit!$C$31,ISNUMBER(Audit!$J$31)),Audit!$J$31,IF(AND(I44=Audit!$C$32,ISNUMBER(Audit!$J$32)),Audit!$J$32,""))) -> 1 | K44: =IF(B44="","",IF(ISNUMBER(Audit!$I$96),Audit!$I$96,IF(G44=0,"",CHOOSE(G44,IF(ISNUMBER(Audit!$C$26),Audit!$C$26,1),1,1,1,$AF$33,$AF$30,$AF$31,1,"",1,0)))) | L44: =IF(O44=1,ROUND(MAX(H44*K44,IF(ISNUMBER(Audit!$J$96),Audit!$J$96,0)),2),"") | M44: =IF(O44=1,ROUND(L44*(1+Y44),2),"") | N44: =IF(O44=1,IF(ISNUMBER(J44),ROUND(M44*J44,2),""),"") | O44: =IF(AND(B44<>"",OR(F44="Firm",F44="Estimate",F44="If required"),ISNUMBER(H44),G44>0,G44<>11,ISNUMBER(K44)),1,0) -> 0 | P44: =IF(ISNUMBER(Audit!$L$96),Audit!$L$96,"") | Q44: =IF(B44="","",IF(OR(F44="At cost",F44="TBC"),"Not priced ("&F44&")",IF(OR(F44="Included",F44="Excluded",F44="Not applicable"),F44,IF(F44="","Status missing",IF(AND(F44="If required",NOT(ISNUMBER(H44))),"Not priced (if required)",IF(G44=0,"Basis missing",IF(G44=11,"Not priced (at cost)",IF(NOT(ISNUMBER(H44)),"Rate missing",IF(AND(G44=9,NOT(ISNUMBER(Audit!$I$96))),"Base amount missing",IF(NOT(ISNUMBER(J44)),"Exchange rate missing",IF(NOT(ISNUMBER(P44)),"Calculated — Not Independently Verified",IF(ABS(R44)<=Lists!$B$44,"Verified","Error - differs by "&TEXT(R44,"#,##0.00")&" "&I44)))))))))))) | R44: =IF(AND(O44=1,ISNUMBER(P44)),IF(ABS(P44-L44)<=ABS(P44-M44),P44-L44,P44-M44),"") | S44: =IF(AND(O44=1,ISNUMBER(Audit!$M$96),ISNUMBER(J44)),IF(H44-Audit!$M$96>0.005,ROUND((H44-Audit!$M$96)*K44*(1+Y44)*J44,2),0),0) -> 0 | T44: =Audit!$N$96&"" | U44: =IF(B44="",0,IF(COUNTIFS($B$2:$B$51,B44,$D$2:$D$51,D44)>1,1,0)) -> 0 | V44: =IF(D44="","",IFERROR(INDEX(Audit!$C$43:$C$49,MATCH(D44,Lists!$A$30:$A$36,0)),"")) | W44: =IF(AND(B44<>"",OR(F44="At cost",F44="TBC",AND(F44<>"If required",G44=11))),1,0) -> 0 | X44: =IF(B44="","",IF(T44<>"","flag",IF(F44="","status",IF(AND(G44=0,OR(F44="Firm",F44="Estimate",AND(F44="If required",ISNUMBER(H44)))),"basis",IF(AND(OR(F44="Firm",F44="Estimate"),G44<>11,NOT(ISNUMBER(H44))),"rate",IF(AND(O44=0,G44=9,OR(F44="Firm",F44="Estimate"),ISNUMBER(H44)),"base",IF(OR(C44="",C44="Unclassified"),"unclass",IF(U44=1,"dup",IF(AND(Audit!$C$19="Yes",O44=1,NOT(ISNUMBER(Audit!$M$96))),"noagree",""))))))))) | Y44: =IF(ISNUMBER(Audit!$K$96),Audit!$K$96,0) -> 0 | Z44: =IF(AND(F44="Firm",O44=1,ISNUMBER(J44)),L44*J44,0) -> 0
A45: 44 | B45: =TRIM(Audit!$B$97) | C45: =Audit!$C$97&"" | D45: =IF(B45="","",IF(C45="","Other",IFERROR(INDEX(Lists!$C$4:$C$16,MATCH(C45,Lists!$A$4:$A$16,0)),"Other"))) | E45: =IF(B45="","",IF(C45="","Other",IFERROR(INDEX(Lists!$B$4:$B$16,MATCH(C45,Lists!$A$4:$A$16,0)),"Other"))) | F45: =Audit!$G$97&"" | G45: =IFERROR(MATCH(Audit!$D$97,Lists!$E$4:$E$14,0),0) -> 0 | H45: =IF(ISNUMBER(Audit!$E$97),Audit!$E$97,"") | I45: =IF(TRIM(Audit!$F$97)="",Audit!$C$25,TRIM(Audit!$F$97)) -> 0 | J45: =IF(OR(I45=Audit!$C$25,I45=""),1,IF(AND(I45=Audit!$C$31,ISNUMBER(Audit!$J$31)),Audit!$J$31,IF(AND(I45=Audit!$C$32,ISNUMBER(Audit!$J$32)),Audit!$J$32,""))) -> 1 | K45: =IF(B45="","",IF(ISNUMBER(Audit!$I$97),Audit!$I$97,IF(G45=0,"",CHOOSE(G45,IF(ISNUMBER(Audit!$C$26),Audit!$C$26,1),1,1,1,$AF$33,$AF$30,$AF$31,1,"",1,0)))) | L45: =IF(O45=1,ROUND(MAX(H45*K45,IF(ISNUMBER(Audit!$J$97),Audit!$J$97,0)),2),"") | M45: =IF(O45=1,ROUND(L45*(1+Y45),2),"") | N45: =IF(O45=1,IF(ISNUMBER(J45),ROUND(M45*J45,2),""),"") | O45: =IF(AND(B45<>"",OR(F45="Firm",F45="Estimate",F45="If required"),ISNUMBER(H45),G45>0,G45<>11,ISNUMBER(K45)),1,0) -> 0 | P45: =IF(ISNUMBER(Audit!$L$97),Audit!$L$97,"") | Q45: =IF(B45="","",IF(OR(F45="At cost",F45="TBC"),"Not priced ("&F45&")",IF(OR(F45="Included",F45="Excluded",F45="Not applicable"),F45,IF(F45="","Status missing",IF(AND(F45="If required",NOT(ISNUMBER(H45))),"Not priced (if required)",IF(G45=0,"Basis missing",IF(G45=11,"Not priced (at cost)",IF(NOT(ISNUMBER(H45)),"Rate missing",IF(AND(G45=9,NOT(ISNUMBER(Audit!$I$97))),"Base amount missing",IF(NOT(ISNUMBER(J45)),"Exchange rate missing",IF(NOT(ISNUMBER(P45)),"Calculated — Not Independently Verified",IF(ABS(R45)<=Lists!$B$44,"Verified","Error - differs by "&TEXT(R45,"#,##0.00")&" "&I45)))))))))))) | R45: =IF(AND(O45=1,ISNUMBER(P45)),IF(ABS(P45-L45)<=ABS(P45-M45),P45-L45,P45-M45),"") | S45: =IF(AND(O45=1,ISNUMBER(Audit!$M$97),ISNUMBER(J45)),IF(H45-Audit!$M$97>0.005,ROUND((H45-Audit!$M$97)*K45*(1+Y45)*J45,2),0),0) -> 0 | T45: =Audit!$N$97&"" | U45: =IF(B45="",0,IF(COUNTIFS($B$2:$B$51,B45,$D$2:$D$51,D45)>1,1,0)) -> 0 | V45: =IF(D45="","",IFERROR(INDEX(Audit!$C$43:$C$49,MATCH(D45,Lists!$A$30:$A$36,0)),"")) | W45: =IF(AND(B45<>"",OR(F45="At cost",F45="TBC",AND(F45<>"If required",G45=11))),1,0) -> 0 | X45: =IF(B45="","",IF(T45<>"","flag",IF(F45="","status",IF(AND(G45=0,OR(F45="Firm",F45="Estimate",AND(F45="If required",ISNUMBER(H45)))),"basis",IF(AND(OR(F45="Firm",F45="Estimate"),G45<>11,NOT(ISNUMBER(H45))),"rate",IF(AND(O45=0,G45=9,OR(F45="Firm",F45="Estimate"),ISNUMBER(H45)),"base",IF(OR(C45="",C45="Unclassified"),"unclass",IF(U45=1,"dup",IF(AND(Audit!$C$19="Yes",O45=1,NOT(ISNUMBER(Audit!$M$97))),"noagree",""))))))))) | Y45: =IF(ISNUMBER(Audit!$K$97),Audit!$K$97,0) -> 0 | Z45: =IF(AND(F45="Firm",O45=1,ISNUMBER(J45)),L45*J45,0) -> 0
A46: 45 | B46: =TRIM(Audit!$B$98) | C46: =Audit!$C$98&"" | D46: =IF(B46="","",IF(C46="","Other",IFERROR(INDEX(Lists!$C$4:$C$16,MATCH(C46,Lists!$A$4:$A$16,0)),"Other"))) | E46: =IF(B46="","",IF(C46="","Other",IFERROR(INDEX(Lists!$B$4:$B$16,MATCH(C46,Lists!$A$4:$A$16,0)),"Other"))) | F46: =Audit!$G$98&"" | G46: =IFERROR(MATCH(Audit!$D$98,Lists!$E$4:$E$14,0),0) -> 0 | H46: =IF(ISNUMBER(Audit!$E$98),Audit!$E$98,"") | I46: =IF(TRIM(Audit!$F$98)="",Audit!$C$25,TRIM(Audit!$F$98)) -> 0 | J46: =IF(OR(I46=Audit!$C$25,I46=""),1,IF(AND(I46=Audit!$C$31,ISNUMBER(Audit!$J$31)),Audit!$J$31,IF(AND(I46=Audit!$C$32,ISNUMBER(Audit!$J$32)),Audit!$J$32,""))) -> 1 | K46: =IF(B46="","",IF(ISNUMBER(Audit!$I$98),Audit!$I$98,IF(G46=0,"",CHOOSE(G46,IF(ISNUMBER(Audit!$C$26),Audit!$C$26,1),1,1,1,$AF$33,$AF$30,$AF$31,1,"",1,0)))) | L46: =IF(O46=1,ROUND(MAX(H46*K46,IF(ISNUMBER(Audit!$J$98),Audit!$J$98,0)),2),"") | M46: =IF(O46=1,ROUND(L46*(1+Y46),2),"") | N46: =IF(O46=1,IF(ISNUMBER(J46),ROUND(M46*J46,2),""),"") | O46: =IF(AND(B46<>"",OR(F46="Firm",F46="Estimate",F46="If required"),ISNUMBER(H46),G46>0,G46<>11,ISNUMBER(K46)),1,0) -> 0 | P46: =IF(ISNUMBER(Audit!$L$98),Audit!$L$98,"") | Q46: =IF(B46="","",IF(OR(F46="At cost",F46="TBC"),"Not priced ("&F46&")",IF(OR(F46="Included",F46="Excluded",F46="Not applicable"),F46,IF(F46="","Status missing",IF(AND(F46="If required",NOT(ISNUMBER(H46))),"Not priced (if required)",IF(G46=0,"Basis missing",IF(G46=11,"Not priced (at cost)",IF(NOT(ISNUMBER(H46)),"Rate missing",IF(AND(G46=9,NOT(ISNUMBER(Audit!$I$98))),"Base amount missing",IF(NOT(ISNUMBER(J46)),"Exchange rate missing",IF(NOT(ISNUMBER(P46)),"Calculated — Not Independently Verified",IF(ABS(R46)<=Lists!$B$44,"Verified","Error - differs by "&TEXT(R46,"#,##0.00")&" "&I46)))))))))))) | R46: =IF(AND(O46=1,ISNUMBER(P46)),IF(ABS(P46-L46)<=ABS(P46-M46),P46-L46,P46-M46),"") | S46: =IF(AND(O46=1,ISNUMBER(Audit!$M$98),ISNUMBER(J46)),IF(H46-Audit!$M$98>0.005,ROUND((H46-Audit!$M$98)*K46*(1+Y46)*J46,2),0),0) -> 0 | T46: =Audit!$N$98&"" | U46: =IF(B46="",0,IF(COUNTIFS($B$2:$B$51,B46,$D$2:$D$51,D46)>1,1,0)) -> 0 | V46: =IF(D46="","",IFERROR(INDEX(Audit!$C$43:$C$49,MATCH(D46,Lists!$A$30:$A$36,0)),"")) | W46: =IF(AND(B46<>"",OR(F46="At cost",F46="TBC",AND(F46<>"If required",G46=11))),1,0) -> 0 | X46: =IF(B46="","",IF(T46<>"","flag",IF(F46="","status",IF(AND(G46=0,OR(F46="Firm",F46="Estimate",AND(F46="If required",ISNUMBER(H46)))),"basis",IF(AND(OR(F46="Firm",F46="Estimate"),G46<>11,NOT(ISNUMBER(H46))),"rate",IF(AND(O46=0,G46=9,OR(F46="Firm",F46="Estimate"),ISNUMBER(H46)),"base",IF(OR(C46="",C46="Unclassified"),"unclass",IF(U46=1,"dup",IF(AND(Audit!$C$19="Yes",O46=1,NOT(ISNUMBER(Audit!$M$98))),"noagree",""))))))))) | Y46: =IF(ISNUMBER(Audit!$K$98),Audit!$K$98,0) -> 0 | Z46: =IF(AND(F46="Firm",O46=1,ISNUMBER(J46)),L46*J46,0) -> 0
A47: 46 | B47: =TRIM(Audit!$B$99) | C47: =Audit!$C$99&"" | D47: =IF(B47="","",IF(C47="","Other",IFERROR(INDEX(Lists!$C$4:$C$16,MATCH(C47,Lists!$A$4:$A$16,0)),"Other"))) | E47: =IF(B47="","",IF(C47="","Other",IFERROR(INDEX(Lists!$B$4:$B$16,MATCH(C47,Lists!$A$4:$A$16,0)),"Other"))) | F47: =Audit!$G$99&"" | G47: =IFERROR(MATCH(Audit!$D$99,Lists!$E$4:$E$14,0),0) -> 0 | H47: =IF(ISNUMBER(Audit!$E$99),Audit!$E$99,"") | I47: =IF(TRIM(Audit!$F$99)="",Audit!$C$25,TRIM(Audit!$F$99)) -> 0 | J47: =IF(OR(I47=Audit!$C$25,I47=""),1,IF(AND(I47=Audit!$C$31,ISNUMBER(Audit!$J$31)),Audit!$J$31,IF(AND(I47=Audit!$C$32,ISNUMBER(Audit!$J$32)),Audit!$J$32,""))) -> 1 | K47: =IF(B47="","",IF(ISNUMBER(Audit!$I$99),Audit!$I$99,IF(G47=0,"",CHOOSE(G47,IF(ISNUMBER(Audit!$C$26),Audit!$C$26,1),1,1,1,$AF$33,$AF$30,$AF$31,1,"",1,0)))) | L47: =IF(O47=1,ROUND(MAX(H47*K47,IF(ISNUMBER(Audit!$J$99),Audit!$J$99,0)),2),"") | M47: =IF(O47=1,ROUND(L47*(1+Y47),2),"") | N47: =IF(O47=1,IF(ISNUMBER(J47),ROUND(M47*J47,2),""),"") | O47: =IF(AND(B47<>"",OR(F47="Firm",F47="Estimate",F47="If required"),ISNUMBER(H47),G47>0,G47<>11,ISNUMBER(K47)),1,0) -> 0 | P47: =IF(ISNUMBER(Audit!$L$99),Audit!$L$99,"") | Q47: =IF(B47="","",IF(OR(F47="At cost",F47="TBC"),"Not priced ("&F47&")",IF(OR(F47="Included",F47="Excluded",F47="Not applicable"),F47,IF(F47="","Status missing",IF(AND(F47="If required",NOT(ISNUMBER(H47))),"Not priced (if required)",IF(G47=0,"Basis missing",IF(G47=11,"Not priced (at cost)",IF(NOT(ISNUMBER(H47)),"Rate missing",IF(AND(G47=9,NOT(ISNUMBER(Audit!$I$99))),"Base amount missing",IF(NOT(ISNUMBER(J47)),"Exchange rate missing",IF(NOT(ISNUMBER(P47)),"Calculated — Not Independently Verified",IF(ABS(R47)<=Lists!$B$44,"Verified","Error - differs by "&TEXT(R47,"#,##0.00")&" "&I47)))))))))))) | R47: =IF(AND(O47=1,ISNUMBER(P47)),IF(ABS(P47-L47)<=ABS(P47-M47),P47-L47,P47-M47),"") | S47: =IF(AND(O47=1,ISNUMBER(Audit!$M$99),ISNUMBER(J47)),IF(H47-Audit!$M$99>0.005,ROUND((H47-Audit!$M$99)*K47*(1+Y47)*J47,2),0),0) -> 0 | T47: =Audit!$N$99&"" | U47: =IF(B47="",0,IF(COUNTIFS($B$2:$B$51,B47,$D$2:$D$51,D47)>1,1,0)) -> 0 | V47: =IF(D47="","",IFERROR(INDEX(Audit!$C$43:$C$49,MATCH(D47,Lists!$A$30:$A$36,0)),"")) | W47: =IF(AND(B47<>"",OR(F47="At cost",F47="TBC",AND(F47<>"If required",G47=11))),1,0) -> 0 | X47: =IF(B47="","",IF(T47<>"","flag",IF(F47="","status",IF(AND(G47=0,OR(F47="Firm",F47="Estimate",AND(F47="If required",ISNUMBER(H47)))),"basis",IF(AND(OR(F47="Firm",F47="Estimate"),G47<>11,NOT(ISNUMBER(H47))),"rate",IF(AND(O47=0,G47=9,OR(F47="Firm",F47="Estimate"),ISNUMBER(H47)),"base",IF(OR(C47="",C47="Unclassified"),"unclass",IF(U47=1,"dup",IF(AND(Audit!$C$19="Yes",O47=1,NOT(ISNUMBER(Audit!$M$99))),"noagree",""))))))))) | Y47: =IF(ISNUMBER(Audit!$K$99),Audit!$K$99,0) -> 0 | Z47: =IF(AND(F47="Firm",O47=1,ISNUMBER(J47)),L47*J47,0) -> 0
A48: 47 | B48: =TRIM(Audit!$B$100) | C48: =Audit!$C$100&"" | D48: =IF(B48="","",IF(C48="","Other",IFERROR(INDEX(Lists!$C$4:$C$16,MATCH(C48,Lists!$A$4:$A$16,0)),"Other"))) | E48: =IF(B48="","",IF(C48="","Other",IFERROR(INDEX(Lists!$B$4:$B$16,MATCH(C48,Lists!$A$4:$A$16,0)),"Other"))) | F48: =Audit!$G$100&"" | G48: =IFERROR(MATCH(Audit!$D$100,Lists!$E$4:$E$14,0),0) -> 0 | H48: =IF(ISNUMBER(Audit!$E$100),Audit!$E$100,"") | I48: =IF(TRIM(Audit!$F$100)="",Audit!$C$25,TRIM(Audit!$F$100)) -> 0 | J48: =IF(OR(I48=Audit!$C$25,I48=""),1,IF(AND(I48=Audit!$C$31,ISNUMBER(Audit!$J$31)),Audit!$J$31,IF(AND(I48=Audit!$C$32,ISNUMBER(Audit!$J$32)),Audit!$J$32,""))) -> 1 | K48: =IF(B48="","",IF(ISNUMBER(Audit!$I$100),Audit!$I$100,IF(G48=0,"",CHOOSE(G48,IF(ISNUMBER(Audit!$C$26),Audit!$C$26,1),1,1,1,$AF$33,$AF$30,$AF$31,1,"",1,0)))) | L48: =IF(O48=1,ROUND(MAX(H48*K48,IF(ISNUMBER(Audit!$J$100),Audit!$J$100,0)),2),"") | M48: =IF(O48=1,ROUND(L48*(1+Y48),2),"") | N48: =IF(O48=1,IF(ISNUMBER(J48),ROUND(M48*J48,2),""),"") | O48: =IF(AND(B48<>"",OR(F48="Firm",F48="Estimate",F48="If required"),ISNUMBER(H48),G48>0,G48<>11,ISNUMBER(K48)),1,0) -> 0 | P48: =IF(ISNUMBER(Audit!$L$100),Audit!$L$100,"") | Q48: =IF(B48="","",IF(OR(F48="At cost",F48="TBC"),"Not priced ("&F48&")",IF(OR(F48="Included",F48="Excluded",F48="Not applicable"),F48,IF(F48="","Status missing",IF(AND(F48="If required",NOT(ISNUMBER(H48))),"Not priced (if required)",IF(G48=0,"Basis missing",IF(G48=11,"Not priced (at cost)",IF(NOT(ISNUMBER(H48)),"Rate missing",IF(AND(G48=9,NOT(ISNUMBER(Audit!$I$100))),"Base amount missing",IF(NOT(ISNUMBER(J48)),"Exchange rate missing",IF(NOT(ISNUMBER(P48)),"Calculated — Not Independently Verified",IF(ABS(R48)<=Lists!$B$44,"Verified","Error - differs by "&TEXT(R48,"#,##0.00")&" "&I48)))))))))))) | R48: =IF(AND(O48=1,ISNUMBER(P48)),IF(ABS(P48-L48)<=ABS(P48-M48),P48-L48,P48-M48),"") | S48: =IF(AND(O48=1,ISNUMBER(Audit!$M$100),ISNUMBER(J48)),IF(H48-Audit!$M$100>0.005,ROUND((H48-Audit!$M$100)*K48*(1+Y48)*J48,2),0),0) -> 0 | T48: =Audit!$N$100&"" | U48: =IF(B48="",0,IF(COUNTIFS($B$2:$B$51,B48,$D$2:$D$51,D48)>1,1,0)) -> 0 | V48: =IF(D48="","",IFERROR(INDEX(Audit!$C$43:$C$49,MATCH(D48,Lists!$A$30:$A$36,0)),"")) | W48: =IF(AND(B48<>"",OR(F48="At cost",F48="TBC",AND(F48<>"If required",G48=11))),1,0) -> 0 | X48: =IF(B48="","",IF(T48<>"","flag",IF(F48="","status",IF(AND(G48=0,OR(F48="Firm",F48="Estimate",AND(F48="If required",ISNUMBER(H48)))),"basis",IF(AND(OR(F48="Firm",F48="Estimate"),G48<>11,NOT(ISNUMBER(H48))),"rate",IF(AND(O48=0,G48=9,OR(F48="Firm",F48="Estimate"),ISNUMBER(H48)),"base",IF(OR(C48="",C48="Unclassified"),"unclass",IF(U48=1,"dup",IF(AND(Audit!$C$19="Yes",O48=1,NOT(ISNUMBER(Audit!$M$100))),"noagree",""))))))))) | Y48: =IF(ISNUMBER(Audit!$K$100),Audit!$K$100,0) -> 0 | Z48: =IF(AND(F48="Firm",O48=1,ISNUMBER(J48)),L48*J48,0) -> 0
A49: 48 | B49: =TRIM(Audit!$B$101) | C49: =Audit!$C$101&"" | D49: =IF(B49="","",IF(C49="","Other",IFERROR(INDEX(Lists!$C$4:$C$16,MATCH(C49,Lists!$A$4:$A$16,0)),"Other"))) | E49: =IF(B49="","",IF(C49="","Other",IFERROR(INDEX(Lists!$B$4:$B$16,MATCH(C49,Lists!$A$4:$A$16,0)),"Other"))) | F49: =Audit!$G$101&"" | G49: =IFERROR(MATCH(Audit!$D$101,Lists!$E$4:$E$14,0),0) -> 0 | H49: =IF(ISNUMBER(Audit!$E$101),Audit!$E$101,"") | I49: =IF(TRIM(Audit!$F$101)="",Audit!$C$25,TRIM(Audit!$F$101)) -> 0 | J49: =IF(OR(I49=Audit!$C$25,I49=""),1,IF(AND(I49=Audit!$C$31,ISNUMBER(Audit!$J$31)),Audit!$J$31,IF(AND(I49=Audit!$C$32,ISNUMBER(Audit!$J$32)),Audit!$J$32,""))) -> 1 | K49: =IF(B49="","",IF(ISNUMBER(Audit!$I$101),Audit!$I$101,IF(G49=0,"",CHOOSE(G49,IF(ISNUMBER(Audit!$C$26),Audit!$C$26,1),1,1,1,$AF$33,$AF$30,$AF$31,1,"",1,0)))) | L49: =IF(O49=1,ROUND(MAX(H49*K49,IF(ISNUMBER(Audit!$J$101),Audit!$J$101,0)),2),"") | M49: =IF(O49=1,ROUND(L49*(1+Y49),2),"") | N49: =IF(O49=1,IF(ISNUMBER(J49),ROUND(M49*J49,2),""),"") | O49: =IF(AND(B49<>"",OR(F49="Firm",F49="Estimate",F49="If required"),ISNUMBER(H49),G49>0,G49<>11,ISNUMBER(K49)),1,0) -> 0 | P49: =IF(ISNUMBER(Audit!$L$101),Audit!$L$101,"") | Q49: =IF(B49="","",IF(OR(F49="At cost",F49="TBC"),"Not priced ("&F49&")",IF(OR(F49="Included",F49="Excluded",F49="Not applicable"),F49,IF(F49="","Status missing",IF(AND(F49="If required",NOT(ISNUMBER(H49))),"Not priced (if required)",IF(G49=0,"Basis missing",IF(G49=11,"Not priced (at cost)",IF(NOT(ISNUMBER(H49)),"Rate missing",IF(AND(G49=9,NOT(ISNUMBER(Audit!$I$101))),"Base amount missing",IF(NOT(ISNUMBER(J49)),"Exchange rate missing",IF(NOT(ISNUMBER(P49)),"Calculated — Not Independently Verified",IF(ABS(R49)<=Lists!$B$44,"Verified","Error - differs by "&TEXT(R49,"#,##0.00")&" "&I49)))))))))))) | R49: =IF(AND(O49=1,ISNUMBER(P49)),IF(ABS(P49-L49)<=ABS(P49-M49),P49-L49,P49-M49),"") | S49: =IF(AND(O49=1,ISNUMBER(Audit!$M$101),ISNUMBER(J49)),IF(H49-Audit!$M$101>0.005,ROUND((H49-Audit!$M$101)*K49*(1+Y49)*J49,2),0),0) -> 0 | T49: =Audit!$N$101&"" | U49: =IF(B49="",0,IF(COUNTIFS($B$2:$B$51,B49,$D$2:$D$51,D49)>1,1,0)) -> 0 | V49: =IF(D49="","",IFERROR(INDEX(Audit!$C$43:$C$49,MATCH(D49,Lists!$A$30:$A$36,0)),"")) | W49: =IF(AND(B49<>"",OR(F49="At cost",F49="TBC",AND(F49<>"If required",G49=11))),1,0) -> 0 | X49: =IF(B49="","",IF(T49<>"","flag",IF(F49="","status",IF(AND(G49=0,OR(F49="Firm",F49="Estimate",AND(F49="If required",ISNUMBER(H49)))),"basis",IF(AND(OR(F49="Firm",F49="Estimate"),G49<>11,NOT(ISNUMBER(H49))),"rate",IF(AND(O49=0,G49=9,OR(F49="Firm",F49="Estimate"),ISNUMBER(H49)),"base",IF(OR(C49="",C49="Unclassified"),"unclass",IF(U49=1,"dup",IF(AND(Audit!$C$19="Yes",O49=1,NOT(ISNUMBER(Audit!$M$101))),"noagree",""))))))))) | Y49: =IF(ISNUMBER(Audit!$K$101),Audit!$K$101,0) -> 0 | Z49: =IF(AND(F49="Firm",O49=1,ISNUMBER(J49)),L49*J49,0) -> 0
A50: 49 | B50: =TRIM(Audit!$B$102) | C50: =Audit!$C$102&"" | D50: =IF(B50="","",IF(C50="","Other",IFERROR(INDEX(Lists!$C$4:$C$16,MATCH(C50,Lists!$A$4:$A$16,0)),"Other"))) | E50: =IF(B50="","",IF(C50="","Other",IFERROR(INDEX(Lists!$B$4:$B$16,MATCH(C50,Lists!$A$4:$A$16,0)),"Other"))) | F50: =Audit!$G$102&"" | G50: =IFERROR(MATCH(Audit!$D$102,Lists!$E$4:$E$14,0),0) -> 0 | H50: =IF(ISNUMBER(Audit!$E$102),Audit!$E$102,"") | I50: =IF(TRIM(Audit!$F$102)="",Audit!$C$25,TRIM(Audit!$F$102)) -> 0 | J50: =IF(OR(I50=Audit!$C$25,I50=""),1,IF(AND(I50=Audit!$C$31,ISNUMBER(Audit!$J$31)),Audit!$J$31,IF(AND(I50=Audit!$C$32,ISNUMBER(Audit!$J$32)),Audit!$J$32,""))) -> 1 | K50: =IF(B50="","",IF(ISNUMBER(Audit!$I$102),Audit!$I$102,IF(G50=0,"",CHOOSE(G50,IF(ISNUMBER(Audit!$C$26),Audit!$C$26,1),1,1,1,$AF$33,$AF$30,$AF$31,1,"",1,0)))) | L50: =IF(O50=1,ROUND(MAX(H50*K50,IF(ISNUMBER(Audit!$J$102),Audit!$J$102,0)),2),"") | M50: =IF(O50=1,ROUND(L50*(1+Y50),2),"") | N50: =IF(O50=1,IF(ISNUMBER(J50),ROUND(M50*J50,2),""),"") | O50: =IF(AND(B50<>"",OR(F50="Firm",F50="Estimate",F50="If required"),ISNUMBER(H50),G50>0,G50<>11,ISNUMBER(K50)),1,0) -> 0 | P50: =IF(ISNUMBER(Audit!$L$102),Audit!$L$102,"") | Q50: =IF(B50="","",IF(OR(F50="At cost",F50="TBC"),"Not priced ("&F50&")",IF(OR(F50="Included",F50="Excluded",F50="Not applicable"),F50,IF(F50="","Status missing",IF(AND(F50="If required",NOT(ISNUMBER(H50))),"Not priced (if required)",IF(G50=0,"Basis missing",IF(G50=11,"Not priced (at cost)",IF(NOT(ISNUMBER(H50)),"Rate missing",IF(AND(G50=9,NOT(ISNUMBER(Audit!$I$102))),"Base amount missing",IF(NOT(ISNUMBER(J50)),"Exchange rate missing",IF(NOT(ISNUMBER(P50)),"Calculated — Not Independently Verified",IF(ABS(R50)<=Lists!$B$44,"Verified","Error - differs by "&TEXT(R50,"#,##0.00")&" "&I50)))))))))))) | R50: =IF(AND(O50=1,ISNUMBER(P50)),IF(ABS(P50-L50)<=ABS(P50-M50),P50-L50,P50-M50),"") | S50: =IF(AND(O50=1,ISNUMBER(Audit!$M$102),ISNUMBER(J50)),IF(H50-Audit!$M$102>0.005,ROUND((H50-Audit!$M$102)*K50*(1+Y50)*J50,2),0),0) -> 0 | T50: =Audit!$N$102&"" | U50: =IF(B50="",0,IF(COUNTIFS($B$2:$B$51,B50,$D$2:$D$51,D50)>1,1,0)) -> 0 | V50: =IF(D50="","",IFERROR(INDEX(Audit!$C$43:$C$49,MATCH(D50,Lists!$A$30:$A$36,0)),"")) | W50: =IF(AND(B50<>"",OR(F50="At cost",F50="TBC",AND(F50<>"If required",G50=11))),1,0) -> 0 | X50: =IF(B50="","",IF(T50<>"","flag",IF(F50="","status",IF(AND(G50=0,OR(F50="Firm",F50="Estimate",AND(F50="If required",ISNUMBER(H50)))),"basis",IF(AND(OR(F50="Firm",F50="Estimate"),G50<>11,NOT(ISNUMBER(H50))),"rate",IF(AND(O50=0,G50=9,OR(F50="Firm",F50="Estimate"),ISNUMBER(H50)),"base",IF(OR(C50="",C50="Unclassified"),"unclass",IF(U50=1,"dup",IF(AND(Audit!$C$19="Yes",O50=1,NOT(ISNUMBER(Audit!$M$102))),"noagree",""))))))))) | Y50: =IF(ISNUMBER(Audit!$K$102),Audit!$K$102,0) -> 0 | Z50: =IF(AND(F50="Firm",O50=1,ISNUMBER(J50)),L50*J50,0) -> 0
A51: 50 | B51: =TRIM(Audit!$B$103) | C51: =Audit!$C$103&"" | D51: =IF(B51="","",IF(C51="","Other",IFERROR(INDEX(Lists!$C$4:$C$16,MATCH(C51,Lists!$A$4:$A$16,0)),"Other"))) | E51: =IF(B51="","",IF(C51="","Other",IFERROR(INDEX(Lists!$B$4:$B$16,MATCH(C51,Lists!$A$4:$A$16,0)),"Other"))) | F51: =Audit!$G$103&"" | G51: =IFERROR(MATCH(Audit!$D$103,Lists!$E$4:$E$14,0),0) -> 0 | H51: =IF(ISNUMBER(Audit!$E$103),Audit!$E$103,"") | I51: =IF(TRIM(Audit!$F$103)="",Audit!$C$25,TRIM(Audit!$F$103)) -> 0 | J51: =IF(OR(I51=Audit!$C$25,I51=""),1,IF(AND(I51=Audit!$C$31,ISNUMBER(Audit!$J$31)),Audit!$J$31,IF(AND(I51=Audit!$C$32,ISNUMBER(Audit!$J$32)),Audit!$J$32,""))) -> 1 | K51: =IF(B51="","",IF(ISNUMBER(Audit!$I$103),Audit!$I$103,IF(G51=0,"",CHOOSE(G51,IF(ISNUMBER(Audit!$C$26),Audit!$C$26,1),1,1,1,$AF$33,$AF$30,$AF$31,1,"",1,0)))) | L51: =IF(O51=1,ROUND(MAX(H51*K51,IF(ISNUMBER(Audit!$J$103),Audit!$J$103,0)),2),"") | M51: =IF(O51=1,ROUND(L51*(1+Y51),2),"") | N51: =IF(O51=1,IF(ISNUMBER(J51),ROUND(M51*J51,2),""),"") | O51: =IF(AND(B51<>"",OR(F51="Firm",F51="Estimate",F51="If required"),ISNUMBER(H51),G51>0,G51<>11,ISNUMBER(K51)),1,0) -> 0 | P51: =IF(ISNUMBER(Audit!$L$103),Audit!$L$103,"") | Q51: =IF(B51="","",IF(OR(F51="At cost",F51="TBC"),"Not priced ("&F51&")",IF(OR(F51="Included",F51="Excluded",F51="Not applicable"),F51,IF(F51="","Status missing",IF(AND(F51="If required",NOT(ISNUMBER(H51))),"Not priced (if required)",IF(G51=0,"Basis missing",IF(G51=11,"Not priced (at cost)",IF(NOT(ISNUMBER(H51)),"Rate missing",IF(AND(G51=9,NOT(ISNUMBER(Audit!$I$103))),"Base amount missing",IF(NOT(ISNUMBER(J51)),"Exchange rate missing",IF(NOT(ISNUMBER(P51)),"Calculated — Not Independently Verified",IF(ABS(R51)<=Lists!$B$44,"Verified","Error - differs by "&TEXT(R51,"#,##0.00")&" "&I51)))))))))))) | R51: =IF(AND(O51=1,ISNUMBER(P51)),IF(ABS(P51-L51)<=ABS(P51-M51),P51-L51,P51-M51),"") | S51: =IF(AND(O51=1,ISNUMBER(Audit!$M$103),ISNUMBER(J51)),IF(H51-Audit!$M$103>0.005,ROUND((H51-Audit!$M$103)*K51*(1+Y51)*J51,2),0),0) -> 0 | T51: =Audit!$N$103&"" | U51: =IF(B51="",0,IF(COUNTIFS($B$2:$B$51,B51,$D$2:$D$51,D51)>1,1,0)) -> 0 | V51: =IF(D51="","",IFERROR(INDEX(Audit!$C$43:$C$49,MATCH(D51,Lists!$A$30:$A$36,0)),"")) | W51: =IF(AND(B51<>"",OR(F51="At cost",F51="TBC",AND(F51<>"If required",G51=11))),1,0) -> 0 | X51: =IF(B51="","",IF(T51<>"","flag",IF(F51="","status",IF(AND(G51=0,OR(F51="Firm",F51="Estimate",AND(F51="If required",ISNUMBER(H51)))),"basis",IF(AND(OR(F51="Firm",F51="Estimate"),G51<>11,NOT(ISNUMBER(H51))),"rate",IF(AND(O51=0,G51=9,OR(F51="Firm",F51="Estimate"),ISNUMBER(H51)),"base",IF(OR(C51="",C51="Unclassified"),"unclass",IF(U51=1,"dup",IF(AND(Audit!$C$19="Yes",O51=1,NOT(ISNUMBER(Audit!$M$103))),"noagree",""))))))))) | Y51: =IF(ISNUMBER(Audit!$K$103),Audit!$K$103,0) -> 0 | Z51: =IF(AND(F51="Firm",O51=1,ISNUMBER(J51)),L51*J51,0) -> 0
A54: Service | B54: Requested | C54: Priced lines | D54: Unpriced lines | E54: Included | F54: Excluded | G54: N/A | H54: Found | I54: Mark | J54: Coverage | K54: Firm amount | L54: Payer | M54: Firm lines | N54: Mismatch party
A55: Pickup | B55: =Audit!$C$43&"" | C55: =SUMIFS($O$2:$O$51,$D$2:$D$51,A55) -> 0 | D55: =SUMIFS($W$2:$W$51,$D$2:$D$51,A55) -> 0 | E55: =COUNTIFS($D$2:$D$51,A55,$F$2:$F$51,"Included") -> 0 | F55: =COUNTIFS($D$2:$D$51,A55,$F$2:$F$51,"Excluded") -> 0 | G55: =COUNTIFS($D$2:$D$51,A55,$F$2:$F$51,"Not applicable") -> 0 | H55: =IF(C55>0,"Priced",IF(D55>0,"Unpriced",IF(E55>0,"Included",IF(F55>0,"Excluded",IF(G55>0,"Not applicable","No lines"))))) -> No lines | I55: =Audit!$G$43&"" | J55: =IF(I55<>"",I55,IF(H55="No lines",IF(B55="Yes","Not addressed","-"),H55)) -> - | K55: =SUMIFS($N$2:$N$51,$D$2:$D$51,A55,$F$2:$F$51,"Firm") -> 0 | L55: =IFERROR(INDEX(Lists!$J$4:$P$14,MATCH(Audit!$C$8,Lists!$I$4:$I$14,0),1),"") | M55: =COUNTIFS($D$2:$D$51,A55,$F$2:$F$51,"Firm",$O$2:$O$51,1) -> 0 | N55: =IF(AND(Audit!$J$7="Buyer",L55="Seller"),"seller",IF(AND(Audit!$J$7="Seller",L55="Buyer"),"buyer",""))
A56: Export & origin | B56: =Audit!$C$44&"" | C56: =SUMIFS($O$2:$O$51,$D$2:$D$51,A56) -> 0 | D56: =SUMIFS($W$2:$W$51,$D$2:$D$51,A56) -> 0 | E56: =COUNTIFS($D$2:$D$51,A56,$F$2:$F$51,"Included") -> 0 | F56: =COUNTIFS($D$2:$D$51,A56,$F$2:$F$51,"Excluded") -> 0 | G56: =COUNTIFS($D$2:$D$51,A56,$F$2:$F$51,"Not applicable") -> 0 | H56: =IF(C56>0,"Priced",IF(D56>0,"Unpriced",IF(E56>0,"Included",IF(F56>0,"Excluded",IF(G56>0,"Not applicable","No lines"))))) -> No lines | I56: =Audit!$G$44&"" | J56: =IF(I56<>"",I56,IF(H56="No lines",IF(B56="Yes","Not addressed","-"),H56)) -> - | K56: =SUMIFS($N$2:$N$51,$D$2:$D$51,A56,$F$2:$F$51,"Firm") -> 0 | L56: =IFERROR(INDEX(Lists!$J$4:$P$14,MATCH(Audit!$C$8,Lists!$I$4:$I$14,0),2),"") | M56: =COUNTIFS($D$2:$D$51,A56,$F$2:$F$51,"Firm",$O$2:$O$51,1) -> 0 | N56: =IF(AND(Audit!$J$7="Buyer",L56="Seller"),"seller",IF(AND(Audit!$J$7="Seller",L56="Buyer"),"buyer",""))
A57: Main freight | B57: =Audit!$C$45&"" | C57: =SUMIFS($O$2:$O$51,$D$2:$D$51,A57) -> 0 | D57: =SUMIFS($W$2:$W$51,$D$2:$D$51,A57) -> 0 | E57: =COUNTIFS($D$2:$D$51,A57,$F$2:$F$51,"Included") -> 0 | F57: =COUNTIFS($D$2:$D$51,A57,$F$2:$F$51,"Excluded") -> 0 | G57: =COUNTIFS($D$2:$D$51,A57,$F$2:$F$51,"Not applicable") -> 0 | H57: =IF(C57>0,"Priced",IF(D57>0,"Unpriced",IF(E57>0,"Included",IF(F57>0,"Excluded",IF(G57>0,"Not applicable","No lines"))))) -> No lines | I57: =Audit!$G$45&"" | J57: =IF(I57<>"",I57,IF(H57="No lines",IF(B57="Yes","Not addressed","-"),H57)) -> - | K57: =SUMIFS($N$2:$N$51,$D$2:$D$51,A57,$F$2:$F$51,"Firm") -> 0 | L57: =IFERROR(INDEX(Lists!$J$4:$P$14,MATCH(Audit!$C$8,Lists!$I$4:$I$14,0),3),"") | M57: =COUNTIFS($D$2:$D$51,A57,$F$2:$F$51,"Firm",$O$2:$O$51,1) -> 0 | N57: =IF(AND(Audit!$J$7="Buyer",L57="Seller"),"seller",IF(AND(Audit!$J$7="Seller",L57="Buyer"),"buyer",""))
A58: Destination port & handling | B58: =Audit!$C$46&"" | C58: =SUMIFS($O$2:$O$51,$D$2:$D$51,A58) -> 0 | D58: =SUMIFS($W$2:$W$51,$D$2:$D$51,A58) -> 0 | E58: =COUNTIFS($D$2:$D$51,A58,$F$2:$F$51,"Included") -> 0 | F58: =COUNTIFS($D$2:$D$51,A58,$F$2:$F$51,"Excluded") -> 0 | G58: =COUNTIFS($D$2:$D$51,A58,$F$2:$F$51,"Not applicable") -> 0 | H58: =IF(C58>0,"Priced",IF(D58>0,"Unpriced",IF(E58>0,"Included",IF(F58>0,"Excluded",IF(G58>0,"Not applicable","No lines"))))) -> No lines | I58: =Audit!$G$46&"" | J58: =IF(I58<>"",I58,IF(H58="No lines",IF(B58="Yes","Not addressed","-"),H58)) -> - | K58: =SUMIFS($N$2:$N$51,$D$2:$D$51,A58,$F$2:$F$51,"Firm") -> 0 | L58: =IFERROR(INDEX(Lists!$J$4:$P$14,MATCH(Audit!$C$8,Lists!$I$4:$I$14,0),4),"") | M58: =COUNTIFS($D$2:$D$51,A58,$F$2:$F$51,"Firm",$O$2:$O$51,1) -> 0 | N58: =IF(AND(Audit!$J$7="Buyer",L58="Seller"),"seller",IF(AND(Audit!$J$7="Seller",L58="Buyer"),"buyer",""))
A59: Import clearance | B59: =Audit!$C$47&"" | C59: =SUMIFS($O$2:$O$51,$D$2:$D$51,A59) -> 0 | D59: =SUMIFS($W$2:$W$51,$D$2:$D$51,A59) -> 0 | E59: =COUNTIFS($D$2:$D$51,A59,$F$2:$F$51,"Included") -> 0 | F59: =COUNTIFS($D$2:$D$51,A59,$F$2:$F$51,"Excluded") -> 0 | G59: =COUNTIFS($D$2:$D$51,A59,$F$2:$F$51,"Not applicable") -> 0 | H59: =IF(C59>0,"Priced",IF(D59>0,"Unpriced",IF(E59>0,"Included",IF(F59>0,"Excluded",IF(G59>0,"Not applicable","No lines"))))) -> No lines | I59: =Audit!$G$47&"" | J59: =IF(I59<>"",I59,IF(H59="No lines",IF(B59="Yes","Not addressed","-"),H59)) -> - | K59: =SUMIFS($N$2:$N$51,$D$2:$D$51,A59,$F$2:$F$51,"Firm") -> 0 | L59: =IFERROR(INDEX(Lists!$J$4:$P$14,MATCH(Audit!$C$8,Lists!$I$4:$I$14,0),5),"") | M59: =COUNTIFS($D$2:$D$51,A59,$F$2:$F$51,"Firm",$O$2:$O$51,1) -> 0 | N59: =IF(AND(Audit!$J$7="Buyer",L59="Seller"),"seller",IF(AND(Audit!$J$7="Seller",L59="Buyer"),"buyer",""))
A60: Delivery | B60: =Audit!$C$48&"" | C60: =SUMIFS($O$2:$O$51,$D$2:$D$51,A60) -> 0 | D60: =SUMIFS($W$2:$W$51,$D$2:$D$51,A60) -> 0 | E60: =COUNTIFS($D$2:$D$51,A60,$F$2:$F$51,"Included") -> 0 | F60: =COUNTIFS($D$2:$D$51,A60,$F$2:$F$51,"Excluded") -> 0 | G60: =COUNTIFS($D$2:$D$51,A60,$F$2:$F$51,"Not applicable") -> 0 | H60: =IF(C60>0,"Priced",IF(D60>0,"Unpriced",IF(E60>0,"Included",IF(F60>0,"Excluded",IF(G60>0,"Not applicable","No lines"))))) -> No lines | I60: =Audit!$G$48&"" | J60: =IF(I60<>"",I60,IF(H60="No lines",IF(B60="Yes","Not addressed","-"),H60)) -> - | K60: =SUMIFS($N$2:$N$51,$D$2:$D$51,A60,$F$2:$F$51,"Firm") -> 0 | L60: =IFERROR(INDEX(Lists!$J$4:$P$14,MATCH(Audit!$C$8,Lists!$I$4:$I$14,0),6),"") | M60: =COUNTIFS($D$2:$D$51,A60,$F$2:$F$51,"Firm",$O$2:$O$51,1) -> 0 | N60: =IF(AND(Audit!$J$7="Buyer",L60="Seller"),"seller",IF(AND(Audit!$J$7="Seller",L60="Buyer"),"buyer",""))
A61: Duties & taxes | B61: =Audit!$C$49&"" | C61: =SUMIFS($O$2:$O$51,$D$2:$D$51,A61) -> 0 | D61: =SUMIFS($W$2:$W$51,$D$2:$D$51,A61) -> 0 | E61: =COUNTIFS($D$2:$D$51,A61,$F$2:$F$51,"Included") -> 0 | F61: =COUNTIFS($D$2:$D$51,A61,$F$2:$F$51,"Excluded") -> 0 | G61: =COUNTIFS($D$2:$D$51,A61,$F$2:$F$51,"Not applicable") -> 0 | H61: =IF(C61>0,"Priced",IF(D61>0,"Unpriced",IF(E61>0,"Included",IF(F61>0,"Excluded",IF(G61>0,"Not applicable","No lines"))))) -> No lines | I61: =Audit!$G$49&"" | J61: =IF(I61<>"",I61,IF(H61="No lines",IF(B61="Yes","Not addressed","-"),H61)) -> - | K61: =SUMIFS($N$2:$N$51,$D$2:$D$51,A61,$F$2:$F$51,"Firm") -> 0 | L61: =IFERROR(INDEX(Lists!$J$4:$P$14,MATCH(Audit!$C$8,Lists!$I$4:$I$14,0),7),"") | M61: =COUNTIFS($D$2:$D$51,A61,$F$2:$F$51,"Firm",$O$2:$O$51,1) -> 0 | N61: =IF(AND(Audit!$J$7="Buyer",L61="Seller"),"seller",IF(AND(Audit!$J$7="Seller",L61="Buyer"),"buyer",""))
A69: Key | B69: Active | C69: Type | D69: Order | E69: Charge | F69: Issue | G69: Explanation | H69: Action | I69: Amount | J69: Rank | K69: QRank
A70: CI | B70: =IFERROR(IF(Audit!$C$18="No",1,0),0) -> 0 | C70: ="Question" -> Question | D70: =IF(C70="Error",1,IF(C70="Question",2,3)) -> 2 | E70: =IF(B70=1,"Commercial invoice","") | F70: =IF(B70=1,"Not provided","") | G70: =IF(B70=1,"The quotation cannot be checked against the shipment without the commercial invoice.","") | H70: =IF(B70=1,"Obtain the commercial invoice from the client.","") | I70: =IF(B70=1,"","") | J70: =IF(B70=1,D70*1000+ROW(),"") | K70: =IF(AND(B70=1,C70="Question"),ROW(),"")
A71: PL | B71: =IFERROR(IF(Audit!$J$18="No",1,0),0) -> 0 | C71: ="Question" -> Question | D71: =IF(C71="Error",1,IF(C71="Question",2,3)) -> 2 | E71: =IF(B71=1,"Packing list","") | F71: =IF(B71=1,"Not provided","") | G71: =IF(B71=1,"Weights, volumes and packages cannot be checked without the packing list.","") | H71: =IF(B71=1,"Obtain the packing list from the client.","") | I71: =IF(B71=1,"","") | J71: =IF(B71=1,D71*1000+ROW(),"") | K71: =IF(AND(B71=1,C71="Question"),ROW(),"")
A72: ITEM | B72: =IFERROR(IF(Audit!$J$19="No",1,0),0) -> 0 | C72: ="Question" -> Question | D72: =IF(C72="Error",1,IF(C72="Question",2,3)) -> 2 | E72: =IF(B72=1,"Whole quotation","") | F72: =IF(B72=1,"Not itemised","") | G72: =IF(B72=1,"A lump-sum quotation cannot be audited charge by charge.","") | H72: =IF(B72=1,"Ask the forwarder for a line-by-line breakdown with units and quantities.","") | I72: =IF(B72=1,"","") | J72: =IF(B72=1,D72*1000+ROW(),"") | K72: =IF(AND(B72=1,C72="Question"),ROW(),"")
A73: NOPRICE | B73: =IFERROR(IF(AND($AF$7>0,$AF$8=0),1,0),0) -> 0 | C73: ="Question" -> Question | D73: =IF(C73="Error",1,IF(C73="Question",2,3)) -> 2 | E73: =IF(B73=1,"Charge lines","") | F73: =IF(B73=1,"No line has a usable rate","") | G73: =IF(B73=1,"None of the entered lines can be calculated.","") | H73: =IF(B73=1,"Check that rates, bases and statuses are entered; ask the forwarder for unit rates.","") | I73: =IF(B73=1,"","") | J73: =IF(B73=1,D73*1000+ROW(),"") | K73: =IF(AND(B73=1,C73="Question"),ROW(),"")
A74: VMISS | B74: =IFERROR(IF(AND($AF$34=0,Audit!$J$24=""),1,0),0) -> 0 | C74: ="Question" -> Question | D74: =IF(C74="Error",1,IF(C74="Question",2,3)) -> 2 | E74: =IF(B74=1,"Freight validity","") | F74: =IF(B74=1,"Validity date not stated","") | G74: =IF(B74=1,"Without a validity date the client cannot tell whether the rates still apply.","") | H74: =IF(B74=1,"Ask the forwarder for the validity date of all rates, including local charges.","") | I74: =IF(B74=1,"","") | J74: =IF(B74=1,D74*1000+ROW(),"") | K74: =IF(AND(B74=1,C74="Question"),ROW(),"")
A75: VEXP | B75: =IFERROR(IF(AND(ISNUMBER(Audit!$J$24),OR(AND(ISNUMBER(Audit!$J$6),Audit!$J$24<Audit!$J$6),AND(ISNUMBER(Audit!$C$11),Audit!$J$24<Audit!$C$11))),1,0),0) -> 0 | C75: ="Question" -> Question | D75: =IF(C75="Error",1,IF(C75="Question",2,3)) -> 2 | E75: =IF(B75=1,"Freight validity","") | F75: =IF(B75=1,"Freight rates expired / expire on "&TEXT(Audit!$J$24,"d mmm yyyy"),"") | G75: =IF(B75=1,"The rates are no longer valid for this shipment date.","") | H75: =IF(B75=1,"Request revalidated rates before the client proceeds.","") | I75: =IF(B75=1,"","") | J75: =IF(B75=1,D75*1000+ROW(),"") | K75: =IF(AND(B75=1,C75="Question"),ROW(),"")
A76: VSOON | B76: =IFERROR(IF(IF(AND(ISNUMBER(Audit!$J$24),ISNUMBER(Audit!$J$6)),AND(Audit!$J$24>=Audit!$J$6,Audit!$J$24-Audit!$J$6<=Lists!$B$42,NOT(AND(ISNUMBER(Audit!$C$11),Audit!$J$24<Audit!$C$11))),FALSE()),1,0),0) -> 0 | C76: ="Risk" -> Risk | D76: =IF(C76="Error",1,IF(C76="Question",2,3)) -> 3 | E76: =IF(B76=1,"Freight validity","") | F76: =IF(B76=1,"Freight rates expire on "&TEXT(Audit!$J$24,"d mmm yyyy"),"") | G76: =IF(B76=1,"Only "&(Audit!$J$24-Audit!$J$6)&" day(s) after the audit date.","") | H76: =IF(B76=1,"Book before expiry or ask the forwarder to extend validity.","") | I76: =IF(B76=1,"","") | J76: =IF(B76=1,D76*1000+ROW(),"") | K76: =IF(AND(B76=1,C76="Question"),ROW(),"")
A77: TRANSIT | B77: =IFERROR(IF(AND($AF$34=0,Audit!$C$28=""),1,0),0) -> 0 | C77: ="Question" -> Question | D77: =IF(C77="Error",1,IF(C77="Question",2,3)) -> 2 | E77: =IF(B77=1,"Transit time","") | F77: =IF(B77=1,"Not stated","") | G77: =IF(B77=1,"The client cannot plan delivery without a transit time.","") | H77: =IF(B77=1,"Ask the forwarder for the transit time and routing.","") | I77: =IF(B77=1,"","") | J77: =IF(B77=1,D77*1000+ROW(),"") | K77: =IF(AND(B77=1,C77="Question"),ROW(),"")
A78: FREE | B78: =IFERROR(IF(AND(Audit!$J$25="Sea FCL",Audit!$J$28=""),1,0),0) -> 0 | C78: ="Question" -> Question | D78: =IF(C78="Error",1,IF(C78="Question",2,3)) -> 2 | E78: =IF(B78=1,"Demurrage / detention","") | F78: =IF(B78=1,"Free time not stated","") | G78: =IF(B78=1,"Without free days, container demurrage and detention costs cannot be estimated.","") | H78: =IF(B78=1,"Ask the forwarder how many free days apply at destination.","") | I78: =IF(B78=1,"","") | J78: =IF(B78=1,D78*1000+ROW(),"") | K78: =IF(AND(B78=1,C78="Question"),ROW(),"")
A79: CONT | B79: =IFERROR(IF(AND(Audit!$J$25="Sea FCL",NOT(ISNUMBER(Audit!$C$26))),1,0),0) -> 0 | C79: ="Question" -> Question | D79: =IF(C79="Error",1,IF(C79="Question",2,3)) -> 2 | E79: =IF(B79=1,"Containers","") | F79: =IF(B79=1,"Container quantity not entered","") | G79: =IF(B79=1,"Per-container charges assume 1 container until the quantity is entered.","") | H79: =IF(B79=1,"Enter the quoted container quantity and type.","") | I79: =IF(B79=1,"","") | J79: =IF(B79=1,D79*1000+ROW(),"") | K79: =IF(AND(B79=1,C79="Question"),ROW(),"")
A80: LOAD | B80: =IFERROR(IF(AND(Audit!$J$25="Sea FCL",Audit!$C$29<>"Yes"),1,0),0) -> 0 | C80: ="Question" -> Question | D80: =IF(C80="Error",1,IF(C80="Question",2,3)) -> 2 | E80: =IF(B80=1,"Container "&Audit!$C$26&" x "&Audit!$J$26,"") | F80: =IF(B80=1,"Load plan not confirmed","") | G80: =IF(B80=1,"Cargo: "&Audit!$C$14&" cartons, "&Audit!$J$14&" pallets"&IF(Audit!$C$16<>"","; "&Audit!$C$16,"")&"; stackable: "&IF(Audit!$J$16="","not stated",Audit!$J$16)&". Fit cannot be decided from CBM alone.","") | H80: =IF(B80=1,"Ask the forwarder to confirm the load plan; if a different container is needed, request a revised quotation.","") | I80: =IF(B80=1,"","") | J80: =IF(B80=1,D80*1000+ROW(),"") | K80: =IF(AND(B80=1,C80="Question"),ROW(),"")
A81: ROUTE | B81: =IFERROR(IF(OR(Audit!$J$29="No",Audit!$J$29="Partly"),1,0),0) -> 0 | C81: ="Question" -> Question | D81: =IF(C81="Error",1,IF(C81="Question",2,3)) -> 2 | E81: =IF(B81=1,"Route","") | F81: =IF(B81=1,"Quoted route differs from the request","") | G81: =IF(B81=1,"Quoted: "&Audit!$J$27&" / request: "&Audit!$C$9&" to "&Audit!$J$9,"") | H81: =IF(B81=1,"Ask the forwarder to quote the requested route or explain the change and its cost effect.","") | I81: =IF(B81=1,"","") | J81: =IF(B81=1,D81*1000+ROW(),"") | K81: =IF(AND(B81=1,C81="Question"),ROW(),"")
A82: SPECIAL | B82: =IFERROR(IF(Audit!$J$17="Yes",1,0),0) -> 0 | C82: ="Question" -> Question | D82: =IF(C82="Error",1,IF(C82="Question",2,3)) -> 2 | E82: =IF(B82=1,"Special cargo","") | F82: =IF(B82=1,"Special handling may not be covered","") | G82: =IF(B82=1,"The shipment is marked as special cargo; standard rates usually exclude it.","") | H82: =IF(B82=1,"Ask the forwarder to confirm the quotation covers the special cargo requirements.","") | I82: =IF(B82=1,"","") | J82: =IF(B82=1,D82*1000+ROW(),"") | K82: =IF(AND(B82=1,C82="Question"),ROW(),"")
A83: VOL | B83: =IFERROR(IF(OR(Audit!$J$21="No",Audit!$J$21="Unknown"),1,0),0) -> 0 | C83: ="Question" -> Question | D83: =IF(C83="Error",1,IF(C83="Question",2,3)) -> 2 | E83: =IF(B83=1,"Cargo basis - volume","") | F83: =IF(B83=1,"Packing-list volume may not cover all cargo","") | G83: =IF(B83=1,"Stated "&TEXT(Audit!$J$15,"#,##0.###")&" CBM; "&IF(Audit!$C$16<>"",Audit!$C$16,"see packing list"),"") | H83: =IF(B83=1,"Ask the shipper to confirm the total shipped volume and dimensions; per-CBM charges and the load plan must use the confirmed figure.","") | I83: =IF(B83=1,"","") | J83: =IF(B83=1,D83*1000+ROW(),"") | K83: =IF(AND(B83=1,C83="Question"),ROW(),"")
A84: VOriginNC | B84: =IFERROR(IF(AND($C$55+$C$56>0,Audit!$C$33=""),1,0),0) -> 0 | C84: ="Question" -> Question | D84: =IF(C84="Error",1,IF(C84="Question",2,3)) -> 2 | E84: =IF(B84=1,"Origin charges validity","") | F84: =IF(B84=1,"Not Confirmed","") | G84: =IF(B84=1,"The quotation does not state how long the origin charges are valid; the freight validity date is not applied to them.","") | H84: =IF(B84=1,"Ask the forwarder to confirm the validity of the origin charges.","") | I84: =IF(B84=1,"","") | J84: =IF(B84=1,D84*1000+ROW(),"") | K84: =IF(AND(B84=1,C84="Question"),ROW(),"")
A85: VOriginEXP | B85: =IFERROR(IF(AND($C$55+$C$56>0,ISNUMBER(Audit!$C$33),OR(AND(ISNUMBER(Audit!$J$6),Audit!$C$33<Audit!$J$6),AND(ISNUMBER(Audit!$C$11),Audit!$C$33<Audit!$C$11))),1,0),0) -> 0 | C85: ="Question" -> Question | D85: =IF(C85="Error",1,IF(C85="Question",2,3)) -> 2 | E85: =IF(B85=1,"Origin charges validity","") | F85: =IF(B85=1,"Expired / expires on "&TEXT(Audit!$C$33,"d mmm yyyy"),"") | G85: =IF(B85=1,"The origin charges are no longer valid for this shipment date.","") | H85: =IF(B85=1,"Request revalidated charges before the client proceeds.","") | I85: =IF(B85=1,"","") | J85: =IF(B85=1,D85*1000+ROW(),"") | K85: =IF(AND(B85=1,C85="Question"),ROW(),"")
A86: VOriginSOON | B86: =IFERROR(IF(IF(AND($C$55+$C$56>0,ISNUMBER(Audit!$C$33),ISNUMBER(Audit!$J$6)),AND(Audit!$C$33>=Audit!$J$6,Audit!$C$33-Audit!$J$6<=Lists!$B$42,NOT(AND(ISNUMBER(Audit!$C$11),Audit!$C$33<Audit!$C$11))),FALSE()),1,0),0) -> 0 | C86: ="Risk" -> Risk | D86: =IF(C86="Error",1,IF(C86="Question",2,3)) -> 3 | E86: =IF(B86=1,"Origin charges validity","") | F86: =IF(B86=1,"Expire on "&TEXT(Audit!$C$33,"d mmm yyyy"),"") | G86: =IF(B86=1,"Only "&(Audit!$C$33-Audit!$J$6)&" day(s) after the audit date.","") | H86: =IF(B86=1,"Book before expiry or ask the forwarder to extend validity.","") | I86: =IF(B86=1,"","") | J86: =IF(B86=1,D86*1000+ROW(),"") | K86: =IF(AND(B86=1,C86="Question"),ROW(),"")
A87: VDestinationNC | B87: =IFERROR(IF(AND($C$58+$C$59+$C$60>0,Audit!$J$33=""),1,0),0) -> 0 | C87: ="Question" -> Question | D87: =IF(C87="Error",1,IF(C87="Question",2,3)) -> 2 | E87: =IF(B87=1,"Destination charges validity","") | F87: =IF(B87=1,"Not Confirmed","") | G87: =IF(B87=1,"The quotation does not state how long the destination charges are valid; the freight validity date is not applied to them.","") | H87: =IF(B87=1,"Ask the forwarder to confirm the validity of the destination charges.","") | I87: =IF(B87=1,"","") | J87: =IF(B87=1,D87*1000+ROW(),"") | K87: =IF(AND(B87=1,C87="Question"),ROW(),"")
A88: VDestinationEXP | B88: =IFERROR(IF(AND($C$58+$C$59+$C$60>0,ISNUMBER(Audit!$J$33),OR(AND(ISNUMBER(Audit!$J$6),Audit!$J$33<Audit!$J$6),AND(ISNUMBER(Audit!$C$11),Audit!$J$33<Audit!$C$11))),1,0),0) -> 0 | C88: ="Question" -> Question | D88: =IF(C88="Error",1,IF(C88="Question",2,3)) -> 2 | E88: =IF(B88=1,"Destination charges validity","") | F88: =IF(B88=1,"Expired / expires on "&TEXT(Audit!$J$33,"d mmm yyyy"),"") | G88: =IF(B88=1,"The destination charges are no longer valid for this shipment date.","") | H88: =IF(B88=1,"Request revalidated charges before the client proceeds.","") | I88: =IF(B88=1,"","") | J88: =IF(B88=1,D88*1000+ROW(),"") | K88: =IF(AND(B88=1,C88="Question"),ROW(),"")
A89: VDestinationSOON | B89: =IFERROR(IF(IF(AND($C$58+$C$59+$C$60>0,ISNUMBER(Audit!$J$33),ISNUMBER(Audit!$J$6)),AND(Audit!$J$33>=Audit!$J$6,Audit!$J$33-Audit!$J$6<=Lists!$B$42,NOT(AND(ISNUMBER(Audit!$C$11),Audit!$J$33<Audit!$C$11))),FALSE()),1,0),0) -> 0 | C89: ="Risk" -> Risk | D89: =IF(C89="Error",1,IF(C89="Question",2,3)) -> 3 | E89: =IF(B89=1,"Destination charges validity","") | F89: =IF(B89=1,"Expire on "&TEXT(Audit!$J$33,"d mmm yyyy"),"") | G89: =IF(B89=1,"Only "&(Audit!$J$33-Audit!$J$6)&" day(s) after the audit date.","") | H89: =IF(B89=1,"Book before expiry or ask the forwarder to extend validity.","") | I89: =IF(B89=1,"","") | J89: =IF(B89=1,D89*1000+ROW(),"") | K89: =IF(AND(B89=1,C89="Question"),ROW(),"")
A90: PCS | B90: =IFERROR(IF(LEFT(Audit!$H$35,5)="ERROR",1,0),0) -> 0 | C90: ="Error" -> Error | D90: =IF(C90="Error",1,IF(C90="Question",2,3)) -> 1 | E90: =IF(B90=1,"Cargo basis - pieces","") | F90: =IF(B90=1,"Quoted pieces do not match the CI/PL","") | G90: =IF(B90=1,"Quoted "&Audit!$D$35&" vs CI/PL "&Audit!$C$35,"") | H90: =IF(B90=1,"Ask the forwarder to correct the quotation to the documented quantity.","") | I90: =IF(B90=1,"","") | J90: =IF(B90=1,D90*1000+ROW(),"") | K90: =IF(AND(B90=1,C90="Question"),ROW(),"")
A91: PKG | B91: =IFERROR(IF(LEFT(Audit!$H$36,5)="ERROR",1,0),0) -> 0 | C91: ="Error" -> Error | D91: =IF(C91="Error",1,IF(C91="Question",2,3)) -> 1 | E91: =IF(B91=1,"Cargo basis - packages","") | F91: =IF(B91=1,"Quoted packages do not match the CI/PL","") | G91: =IF(B91=1,"Quoted "&Audit!$D$36&" vs CI/PL "&Audit!$C$36,"") | H91: =IF(B91=1,"Ask the forwarder to correct the quotation to the documented cartons or pallets.","") | I91: =IF(B91=1,"","") | J91: =IF(B91=1,D91*1000+ROW(),"") | K91: =IF(AND(B91=1,C91="Question"),ROW(),"")
